Workbook

Sheet Master_Properties
A1: ID | B1: Name | C1: Developer | D1: Location | E1: Unit Type | F1: Community Type | G1: Start Price (AED) | H1: Price per Sqm (AED) | I1: Service Charge | J1: Payment Plan | K1: Launch Date | L1: Annual Yield % | M1: Cap Appr % | N1: Total Return % | O1: Nearest Schools | P1: Nearest Hospitals | Q1: Nearest Malls | R1: Main Access Roads | S1: Mins to DT | T1: Mins to Marina | U1: Mins to DXB | V1: Mins to DWC | W1: Duplicate_Count_From_Merge | X1: Helper_Start_Price_Min_AED | Y1: Helper_Start_Price_Max_AED | Z1: Helper_Annual_Yield_Low_Pct | AA1: Helper_Annual_Yield_High_Pct | AB1: Helper_Cap_App_Low_Pct | AC1: Helper_Cap_App_High_Pct | AD1: Helper_Total_Return_Low_Pct | AE1: Helper_Total_Return_High_Pct | AF1: Helper_Launch_Year | AG1: Helper_Launch_Quarter | AH1: Helper_Asset_Class | AI1: Helper_Area_Segment | AJ1: Helper_Developer_Tier | AK1: Market_Condition | AL1: Conditions_Notes | AM1: Helper_Cap_App_Mid_Pct | AN1: Helper_Annual_Yield_Mid_Pct | AO1: Helper_Current_Realization_Factor | AP1: Helper_Current_Prime_Premium_Pct | AQ1: Helper_Current_Asset_Adjustment_Pct | AR1: Helper_Current_Supply_Adjustment_Pct | AS1: Helper_Forecast_Segment_Base_Pct | AT1: Helper_Forecast_Developer_Adjustment_Pct | AU1: Helper_Forecast_Yield_Adjustment_Pct | AV1: Helper_Forecast_Risk_Adjustment_Pct | AW1: Current_Adjustment_Rate | AX1: Forecast_12M_Base_Pct | AY1: Current_Value_Low_AED | AZ1: Current_Value_Base_AED | BA1: Current_Value_High_AED | BB1: Forecast_12M_Low_AED | BC1: Forecast_12M_Base_AED | BD1: Forecast_12M_High_AED | BE1: Forecast_24M_Base_AED | BF1: Forecast_Method | BG1: Enrichment_Refresh_Date | BH1: Source_Summary | BI1: Added_Project_Source_URL | BJ1: Added_Project_Status | BK1: Added_On
A2: 1 | B2: Grand Polo Club & Resort | C2: Emaar Properties | D2: Near The Oasis/DIP | E2: Villas & Townhouses | F2: Gated / Golf / Equine | G2: 3.6M (TH) / 5.7M (Villa) | H2: 1400-1600 | I2: TBA | J2: 80/20 | K2: Q1 2025 | L2: 5.5-6.5 | M2: 8-12 | N2: 13.5-18.5 | O2: Victory Heights / South View | P2: NMC Royal DIP | Q2: Damac Mall / First Ave | R2: Yalayis St / E611 | S2: 25 | T2: 20 | U2: 30 | V2: 18 | W2: 2 | X2: 3600000 | Y2: 5700000 | Z2: 5.5 | AA2: 6.5 | AB2: 8 | AC2: 12 | AD2: 13.5 | AE2: 18.5 | AF2: 2025 | AG2: 1 | AH2: Villa/Townhouse | AI2: FamilyVilla | AJ2: TopTier | AK2: Family-villa resilient | AL2: Villa/townhouse demand remains relatively firmer, though growth should be slower than the post-2020 surge. | AM2: 10 | AN2: 6 | AO2: 0.4 | AP2: 0 | AQ2: 0.015 | AR2: 0 | AS2: 0.025 | AT2: 0.005 | AU2: 0 | AV2: -0.005 | AW2: =IF(X2="","",(AM2/100*AO2)+AP2+AQ2+AR2) | AX2: =IF(X2="","",AS2+AT2+AU2+AV2) | AY2: =IF(AZ2="","",ROUND(AZ2*(1+Assumptions!$B$10),0)) | AZ2: =IF(X2="","",ROUND(X2*(1+AW2),0)) | BA2: =IF(AZ2="","",ROUND(AZ2*(1+Assumptions!$B$11),0)) | BB2: =IF(AZ2="","",ROUND(AZ2*(1+AX2+Assumptions!$B$10),0)) | BC2: =IF(AZ2="","",ROUND(AZ2*(1+AX2),0)) | BD2: =IF(AZ2="","",ROUND(AZ2*(1+AX2+Assumptions!$B$11),0)) | BE2: =IF(AZ2="","",ROUND(AZ2*(1+AX2)*(1+AX2),0)) | BF2: Rules-based enrichment using launch-price anchor, cap-app realization, and 2026 segment conditions. | BG2: 2026-03-17 | BH2: DLD / Digital Dubai / CBUAE / Savills / Knight Frank-Moody’s / Reuters
A3: 2 | B3: Equiterra (Phases 1 & 2) | C3: Emaar Properties | D3: Grand Polo Club | E3: Townhouses | F3: Gated Community | G3: 3.6M | H3: 1450 | I3: TBA | J3: 80/20 | K3: Q1 2025 | L3: 5.5-6.0 | M3: 8-12 | N3: 13.5-18.0 | O3: Victory Heights / South View | P3: NMC Royal DIP | Q3: Damac Mall / First Ave | R3: Yalayis St / E611 | S3: 25 | T3: 20 | U3: 30 | V3: 18 | W3: 2 | X3: 3600000 | Y3: 3600000 | Z3: 5.5 | AA3: 6 | AB3: 8 | AC3: 12 | AD3: 13.5 | AE3: 18 | AF3: 2025 | AG3: 1 | AH3: Townhouse | AI3: FamilyVilla | AJ3: TopTier | AK3: Family-villa resilient | AL3: Villa/townhouse demand remains relatively firmer, though growth should be slower than the post-2020 surge. | AM3: 10 | AN3: 5.75 | AO3: 0.4 | AP3: 0 | AQ3: 0.015 | AR3: 0 | AS3: 0.025 | AT3: 0.005 | AU3: 0 | AV3: -0.005 | AW3: =IF(X3="","",(AM3/100*AO3)+AP3+AQ3+AR3) | AX3: =IF(X3="","",AS3+AT3+AU3+AV3) | AY3: =IF(AZ3="","",ROUND(AZ3*(1+Assumptions!$B$10),0)) | AZ3: =IF(X3="","",ROUND(X3*(1+AW3),0)) | BA3: =IF(AZ3="","",ROUND(AZ3*(1+Assumptions!$B$11),0)) | BB3: =IF(AZ3="","",ROUND(AZ3*(1+AX3+Assumptions!$B$10),0)) | BC3: =IF(AZ3="","",ROUND(AZ3*(1+AX3),0)) | BD3: =IF(AZ3="","",ROUND(AZ3*(1+AX3+Assumptions!$B$11),0)) | BE3: =IF(AZ3="","",ROUND(AZ3*(1+AX3)*(1+AX3),0)) | BF3: Rules-based enrichment using launch-price anchor, cap-app realization, and 2026 segment conditions. | BG3: 2026-03-17 | BH3: DLD / Digital Dubai / CBUAE / Savills / Knight Frank-Moody’s / Reuters
A4: 3 | B4: Equestra | C4: Emaar Properties | D4: Grand Polo Club | E4: Townhouses | F4: Gated Community | G4: 3.7M | H4: 1450 | I4: TBA | J4: 80/20 | K4: Q1 2025 | L4: 5.5-6.0 | M4: 8-12 | N4: 13.5-18.0 | O4: Victory Heights / South View | P4: NMC Royal DIP | Q4: Damac Mall / First Ave | R4: Yalayis St / E611 | S4: 25 | T4: 20 | U4: 30 | V4: 18 | W4: 2 | X4: 3700000 | Y4: 3700000 | Z4: 5.5 | AA4: 6 | AB4: 8 | AC4: 12 | AD4: 13.5 | AE4: 18 | AF4: 2025 | AG4: 1 | AH4: Townhouse | AI4: FamilyVilla | AJ4: TopTier | AK4: Family-villa resilient | AL4: Villa/townhouse demand remains relatively firmer, though growth should be slower than the post-2020 surge. | AM4: 10 | AN4: 5.75 | AO4: 0.4 | AP4: 0 | AQ4: 0.015 | AR4: 0 | AS4: 0.025 | AT4: 0.005 | AU4: 0 | AV4: -0.005 | AW4: =IF(X4="","",(AM4/100*AO4)+AP4+AQ4+AR4) | AX4: =IF(X4="","",AS4+AT4+AU4+AV4) | AY4: =IF(AZ4="","",ROUND(AZ4*(1+Assumptions!$B$10),0)) | AZ4: =IF(X4="","",ROUND(X4*(1+AW4),0)) | BA4: =IF(AZ4="","",ROUND(AZ4*(1+Assumptions!$B$11),0)) | BB4: =IF(AZ4="","",ROUND(AZ4*(1+AX4+Assumptions!$B$10),0)) | BC4: =IF(AZ4="","",ROUND(AZ4*(1+AX4),0)) | BD4: =IF(AZ4="","",ROUND(AZ4*(1+AX4+Assumptions!$B$11),0)) | BE4: =IF(AZ4="","",ROUND(AZ4*(1+AX4)*(1+AX4),0)) | BF4: Rules-based enrichment using launch-price anchor, cap-app realization, and 2026 segment conditions. | BG4: 2026-03-17 | BH4: DLD / Digital Dubai / CBUAE / Savills / Knight Frank-Moody’s / Reuters
A5: 4 | B5: Chevalia Estate 2 | C5: Emaar Properties | D5: Grand Polo Club | E5: Villas (Large) | F5: Gated Community | G5: 7.9M | H5: 1600 | I5: TBA | J5: 80/20 | K5: Q1 2025 | L5: 4.5-5.5 | M5: 8-12 | N5: 12.5-17.5 | O5: Victory Heights / South View | P5: NMC Royal DIP | Q5: Damac Mall / First Ave | R5: Yalayis St / E611 | S5: 25 | T5: 20 | U5: 30 | V5: 18 | W5: 2 | X5: 7900000 | Y5: 7900000 | Z5: 4.5 | AA5: 5.5 | AB5: 8 | AC5: 12 | AD5: 12.5 | AE5: 17.5 | AF5: 2025 | AG5: 1 | AH5: Villa | AI5: FamilyVilla | AJ5: TopTier | AK5: Family-villa resilient | AL5: Villa/townhouse demand remains relatively firmer, though growth should be slower than the post-2020 surge. | AM5: 10 | AN5: 5 | AO5: 0.4 | AP5: 0 | AQ5: 0.015 | AR5: 0 | AS5: 0.025 | AT5: 0.005 | AU5: 0 | AV5: -0.005 | AW5: =IF(X5="","",(AM5/100*AO5)+AP5+AQ5+AR5) | AX5: =IF(X5="","",AS5+AT5+AU5+AV5) | AY5: =IF(AZ5="","",ROUND(AZ5*(1+Assumptions!$B$10),0)) | AZ5: =IF(X5="","",ROUND(X5*(1+AW5),0)) | BA5: =IF(AZ5="","",ROUND(AZ5*(1+Assumptions!$B$11),0)) | BB5: =IF(AZ5="","",ROUND(AZ5*(1+AX5+Assumptions!$B$10),0)) | BC5: =IF(AZ5="","",ROUND(AZ5*(1+AX5),0)) | BD5: =IF(AZ5="","",ROUND(AZ5*(1+AX5+Assumptions!$B$11),0)) | BE5: =IF(AZ5="","",ROUND(AZ5*(1+AX5)*(1+AX5),0)) | BF5: Rules-based enrichment using launch-price anchor, cap-app realization, and 2026 segment conditions. | BG5: 2026-03-17 | BH5: DLD / Digital Dubai / CBUAE / Savills / Knight Frank-Moody’s / Reuters
A6: 5 | B6: Selvara (Phases 3 & 4) | C6: Emaar Properties | D6: Grand Polo Club | E6: Villas | F6: Gated Community | G6: 6.2M | H6: 1550 | I6: TBA | J6: 80/20 | K6: Q1 2025 | L6: 5.0-5.5 | M6: 8-12 | N6: 13.0-17.5 | O6: Victory Heights / South View | P6: NMC Royal DIP | Q6: Damac Mall / First Ave | R6: Yalayis St / E611 | S6: 25 | T6: 20 | U6: 30 | V6: 18 | W6: 2 | X6: 6200000 | Y6: 6200000 | Z6: 5 | AA6: 5.5 | AB6: 8 | AC6: 12 | AD6: 13 | AE6: 17.5 | AF6: 2025 | AG6: 1 | AH6: Villa | AI6: FamilyVilla | AJ6: TopTier | AK6: Family-villa resilient | AL6: Villa/townhouse demand remains relatively firmer, though growth should be slower than the post-2020 surge. | AM6: 10 | AN6: 5.25 | AO6: 0.4 | AP6: 0 | AQ6: 0.015 | AR6: 0 | AS6: 0.025 | AT6: 0.005 | AU6: 0 | AV6: -0.005 | AW6: =IF(X6="","",(AM6/100*AO6)+AP6+AQ6+AR6) | AX6: =IF(X6="","",AS6+AT6+AU6+AV6) | AY6: =IF(AZ6="","",ROUND(AZ6*(1+Assumptions!$B$10),0)) | AZ6: =IF(X6="","",ROUND(X6*(1+AW6),0)) | BA6: =IF(AZ6="","",ROUND(AZ6*(1+Assumptions!$B$11),0)) | BB6: =IF(AZ6="","",ROUND(AZ6*(1+AX6+Assumptions!$B$10),0)) | BC6: =IF(AZ6="","",ROUND(AZ6*(1+AX6),0)) | BD6: =IF(AZ6="","",ROUND(AZ6*(1+AX6+Assumptions!$B$11),0)) | BE6: =IF(AZ6="","",ROUND(AZ6*(1+AX6)*(1+AX6),0)) | BF6: Rules-based enrichment using launch-price anchor, cap-app realization, and 2026 segment conditions. | BG6: 2026-03-17 | BH6: DLD / Digital Dubai / CBUAE / Savills / Knight Frank-Moody’s / Reuters
A7: 6 | B7: Rashid Yachts & Marina | C7: Emaar Properties | D7: Mina Rashid | E7: Mixed | F7: Waterfront / Marina | I7: 25-30 | J7: Varies | K7: 2023-2025 | L7: 5.5-6.5 | M7: 10-15 | N7: 15.5-21.5 | O7: New Academy School | P7: Aster Hospital Mankhool | Q7: Dubai Mall / City Centre | R7: Al Khaleej / E11 | S7: 15 | T7: 25 | U7: 15 | V7: 45 | W7: 2 | Z7: 5.5 | AA7: 6.5 | AB7: 10 | AC7: 15 | AD7: 15.5 | AE7: 21.5 | AF7: 2023 | AH7: Mixed/Other | AI7: MainstreamSelective | AJ7: TopTier | AK7: Balanced / selective | AL7: Market remains active but increasingly differentiated by developer, micro-location, livability, and pricing discipline. | AM7: 12.5 | AN7: 6 | AO7: 0.55 | AP7: 0 | AQ7: 0 | AR7: 0 | AS7: 0.01 | AT7: 0.005 | AU7: 0 | AV7: -0.005 | AW7: =IF(X7="","",(AM7/100*AO7)+AP7+AQ7+AR7) | AX7: =IF(X7="","",AS7+AT7+AU7+AV7) | AY7: =IF(AZ7="","",ROUND(AZ7*(1+Assumptions!$B$10),0)) | AZ7: =IF(X7="","",ROUND(X7*(1+AW7),0)) | BA7: =IF(AZ7="","",ROUND(AZ7*(1+Assumptions!$B$11),0)) | BB7: =IF(AZ7="","",ROUND(AZ7*(1+AX7+Assumptions!$B$10),0)) | BC7: =IF(AZ7="","",ROUND(AZ7*(1+AX7),0)) | BD7: =IF(AZ7="","",ROUND(AZ7*(1+AX7+Assumptions!$B$11),0)) | BE7: =IF(AZ7="","",ROUND(AZ7*(1+AX7)*(1+AX7),0)) | BF7: Rules-based enrichment using launch-price anchor, cap-app realization, and 2026 segment conditions. | BG7: 2026-03-17 | BH7: DLD / Digital Dubai / CBUAE / Savills / Knight Frank-Moody’s / Reuters
A8: 7 | B8: Aurea | C8: Emaar Properties | D8: Rashid Yachts & Marina | E8: Apartments | F8: Waterfront | G8: 1.8M | H8: 2200 | I8: 25 | J8: 80/20 | K8: 2024 | L8: 5.5-6.0 | M8: 10-12 | N8: 15.5-18.0 | O8: New Academy School | P8: Aster Hospital Mankhool | Q8: Dubai Mall / City Centre | R8: Al Khaleej / E11 | S8: 15 | T8: 25 | U8: 15 | V8: 45 | W8: 2 | X8: 1800000 | Y8: 1800000 | Z8: 5.5 | AA8: 6 | AB8: 10 | AC8: 12 | AD8: 15.5 | AE8: 18 | AF8: 2024 | AH8: Apartment | AI8: MainstreamSelective | AJ8: TopTier | AK8: Balanced / selective | AL8: Market remains active but increasingly differentiated by developer, micro-location, livability, and pricing discipline. | AM8: 11 | AN8: 5.75 | AO8: 0.55 | AP8: 0 | AQ8: 0 | AR8: 0 | AS8: 0.01 | AT8: 0.005 | AU8: 0 | AV8: -0.005 | AW8: =IF(X8="","",(AM8/100*AO8)+AP8+AQ8+AR8) | AX8: =IF(X8="","",AS8+AT8+AU8+AV8) | AY8: =IF(AZ8="","",ROUND(AZ8*(1+Assumptions!$B$10),0)) | AZ8: =IF(X8="","",ROUND(X8*(1+AW8),0)) | BA8: =IF(AZ8="","",ROUND(AZ8*(1+Assumptions!$B$11),0)) | BB8: =IF(AZ8="","",ROUND(AZ8*(1+AX8+Assumptions!$B$10),0)) | BC8: =IF(AZ8="","",ROUND(AZ8*(1+AX8),0)) | BD8: =IF(AZ8="","",ROUND(AZ8*(1+AX8+Assumptions!$B$11),0)) | BE8: =IF(AZ8="","",ROUND(AZ8*(1+AX8)*(1+AX8),0)) | BF8: Rules-based enrichment using launch-price anchor, cap-app realization, and 2026 segment conditions. | BG8: 2026-03-17 | BH8: DLD / Digital Dubai / CBUAE / Savills / Knight Frank-Moody’s / Reuters
A9: 8 | B9: Pier Point | C9: Emaar Properties | D9: Rashid Yachts & Marina | E9: Apartments | F9: Waterfront | G9: 2.1M | H9: 2300 | I9: 25 | J9: 80/20 | K9: 2024 | L9: 5.5-6.0 | M9: 10-12 | N9: 15.5-18.0 | O9: New Academy School | P9: Aster Hospital Mankhool | Q9: Dubai Mall / City Centre | R9: Al Khaleej / E11 | S9: 15 | T9: 25 | U9: 15 | V9: 45 | W9: 2 | X9: 2100000 | Y9: 2100000 | Z9: 5.5 | AA9: 6 | AB9: 10 | AC9: 12 | AD9: 15.5 | AE9: 18 | AF9: 2024 | AH9: Apartment | AI9: MainstreamSelective | AJ9: TopTier | AK9: Balanced / selective | AL9: Market remains active but increasingly differentiated by developer, micro-location, livability, and pricing discipline. | AM9: 11 | AN9: 5.75 | AO9: 0.55 | AP9: 0 | AQ9: 0 | AR9: 0 | AS9: 0.01 | AT9: 0.005 | AU9: 0 | AV9: -0.005 | AW9: =IF(X9="","",(AM9/100*AO9)+AP9+AQ9+AR9) | AX9: =IF(X9="","",AS9+AT9+AU9+AV9) | AY9: =IF(AZ9="","",ROUND(AZ9*(1+Assumptions!$B$10),0)) | AZ9: =IF(X9="","",ROUND(X9*(1+AW9),0)) | BA9: =IF(AZ9="","",ROUND(AZ9*(1+Assumptions!$B$11),0)) | BB9: =IF(AZ9="","",ROUND(AZ9*(1+AX9+Assumptions!$B$10),0)) | BC9: =IF(AZ9="","",ROUND(AZ9*(1+AX9),0)) | BD9: =IF(AZ9="","",ROUND(AZ9*(1+AX9+Assumptions!$B$11),0)) | BE9: =IF(AZ9="","",ROUND(AZ9*(1+AX9)*(1+AX9),0)) | BF9: Rules-based enrichment using launch-price anchor, cap-app realization, and 2026 segment conditions. | BG9: 2026-03-17 | BH9: DLD / Digital Dubai / CBUAE / Savills / Knight Frank-Moody’s / Reuters
A10: 9 | B10: Marina Cove | C10: Emaar Properties | D10: Rashid Yachts & Marina | E10: Apartments | F10: Waterfront | G10: 1.9M | H10: 2250 | I10: 25 | J10: 80/20 | K10: 2024 | L10: 5.5-6.0 | M10: 10-12 | N10: 15.5-18.0 | O10: New Academy School | P10: Aster Hospital Mankhool | Q10: Dubai Mall / City Centre | R10: Al Khaleej / E11 | S10: 15 | T10: 25 | U10: 15 | V10: 45 | W10: 2 | X10: 1900000 | Y10: 1900000 | Z10: 5.5 | AA10: 6 | AB10: 10 | AC10: 12 | AD10: 15.5 | AE10: 18 | AF10: 2024 | AH10: Apartment | AI10: MainstreamSelective | AJ10: TopTier | AK10: Balanced / selective | AL10: Market remains active but increasingly differentiated by developer, micro-location, livability, and pricing discipline. | AM10: 11 | AN10: 5.75 | AO10: 0.55 | AP10: 0 | AQ10: 0 | AR10: 0 | AS10: 0.01 | AT10: 0.005 | AU10: 0 | AV10: -0.005 | AW10: =IF(X10="","",(AM10/100*AO10)+AP10+AQ10+AR10) | AX10: =IF(X10="","",AS10+AT10+AU10+AV10) | AY10: =IF(AZ10="","",ROUND(AZ10*(1+Assumptions!$B$10),0)) | AZ10: =IF(X10="","",ROUND(X10*(1+AW10),0)) | BA10: =IF(AZ10="","",ROUND(AZ10*(1+Assumptions!$B$11),0)) | BB10: =IF(AZ10="","",ROUND(AZ10*(1+AX10+Assumptions!$B$10),0)) | BC10: =IF(AZ10="","",ROUND(AZ10*(1+AX10),0)) | BD10: =IF(AZ10="","",ROUND(AZ10*(1+AX10+Assumptions!$B$11),0)) | BE10: =IF(AZ10="","",ROUND(AZ10*(1+AX10)*(1+AX10),0)) | BF10: Rules-based enrichment using launch-price anchor, cap-app realization, and 2026 segment conditions. | BG10: 2026-03-17 | BH10: DLD / Digital Dubai / CBUAE / Savills / Knight Frank-Moody’s / Reuters
A11: 10 | B11: Sera 2 | C11: Emaar Properties | D11: Rashid Yachts & Marina | E11: Apartments | F11: Waterfront | G11: 1.7M | H11: 2100 | I11: 25 | J11: 80/20 | K11: 2024 | L11: 6.0-6.5 | M11: 10-12 | N11: 16.0-18.5 | O11: New Academy School | P11: Aster Hospital Mankhool | Q11: Dubai Mall / City Centre | R11: Al Khaleej / E11 | S11: 15 | T11: 25 | U11: 15 | V11: 45 | W11: 2 | X11: 1700000 | Y11: 1700000 | Z11: 6 | AA11: 6.5 | AB11: 10 | AC11: 12 | AD11: 16 | AE11: 18.5 | AF11: 2024 | AH11: Apartment | AI11: MainstreamSelective | AJ11: TopTier | AK11: Balanced / selective | AL11: Market remains active but increasingly differentiated by developer, micro-location, livability, and pricing discipline. | AM11: 11 | AN11: 6.25 | AO11: 0.55 | AP11: 0 | AQ11: 0 | AR11: 0 | AS11: 0.01 | AT11: 0.005 | AU11: 0.0025 | AV11: -0.005 | AW11: =IF(X11="","",(AM11/100*AO11)+AP11+AQ11+AR11) | AX11: =IF(X11="","",AS11+AT11+AU11+AV11) | AY11: =IF(AZ11="","",ROUND(AZ11*(1+Assumptions!$B$10),0)) | AZ11: =IF(X11="","",ROUND(X11*(1+AW11),0)) | BA11: =IF(AZ11="","",ROUND(AZ11*(1+Assumptions!$B$11),0)) | BB11: =IF(AZ11="","",ROUND(AZ11*(1+AX11+Assumptions!$B$10),0)) | BC11: =IF(AZ11="","",ROUND(AZ11*(1+AX11),0)) | BD11: =IF(AZ11="","",ROUND(AZ11*(1+AX11+Assumptions!$B$11),0)) | BE11: =IF(AZ11="","",ROUND(AZ11*(1+AX11)*(1+AX11),0)) | BF11: Rules-based enrichment using launch-price anchor, cap-app realization, and 2026 segment conditions. | BG11: 2026-03-17 | BH11: DLD / Digital Dubai / CBUAE / Savills / Knight Frank-Moody’s / Reuters
A12: 11 | B12: Ocean Cove | C12: Emaar Properties | D12: Rashid Yachts & Marina | E12: Apartments | F12: Waterfront | G12: 1.8M | H12: 2200 | I12: 25 | J12: 80/20 | K12: 2024 | L12: 5.5-6.0 | M12: 10-12 | N12: 15.5-18.0 | O12: New Academy School | P12: Aster Hospital Mankhool | Q12: Dubai Mall / City Centre | R12: Al Khaleej / E11 | S12: 15 | T12: 25 | U12: 15 | V12: 45 | W12: 2 | X12: 1800000 | Y12: 1800000 | Z12: 5.5 | AA12: 6 | AB12: 10 | AC12: 12 | AD12: 15.5 | AE12: 18 | AF12: 2024 | AH12: Apartment | AI12: MainstreamSelective | AJ12: TopTier | AK12: Balanced / selective | AL12: Market remains active but increasingly differentiated by developer, micro-location, livability, and pricing discipline. | AM12: 11 | AN12: 5.75 | AO12: 0.55 | AP12: 0 | AQ12: 0 | AR12: 0 | AS12: 0.01 | AT12: 0.005 | AU12: 0 | AV12: -0.005 | AW12: =IF(X12="","",(AM12/100*AO12)+AP12+AQ12+AR12) | AX12: =IF(X12="","",AS12+AT12+AU12+AV12) | AY12: =IF(AZ12="","",ROUND(AZ12*(1+Assumptions!$B$10),0)) | AZ12: =IF(X12="","",ROUND(X12*(1+AW12),0)) | BA12: =IF(AZ12="","",ROUND(AZ12*(1+Assumptions!$B$11),0)) | BB12: =IF(AZ12="","",ROUND(AZ12*(1+AX12+Assumptions!$B$10),0)) | BC12: =IF(AZ12="","",ROUND(AZ12*(1+AX12),0)) | BD12: =IF(AZ12="","",ROUND(AZ12*(1+AX12+Assumptions!$B$11),0)) | BE12: =IF(AZ12="","",ROUND(AZ12*(1+AX12)*(1+AX12),0)) | BF12: Rules-based enrichment using launch-price anchor, cap-app realization, and 2026 segment conditions. | BG12: 2026-03-17 | BH12: DLD / Digital Dubai / CBUAE / Savills / Knight Frank-Moody’s / Reuters
A13: 12 | B13: Baystar | C13: Emaar Properties | D13: Rashid Yachts & Marina | E13: Apartments | F13: Waterfront | G13: 1.75M | H13: 2150 | I13: 25 | J13: 80/20 | K13: 2024 | L13: 5.5-6.0 | M13: 10-12 | N13: 15.5-18.0 | O13: New Academy School | P13: Aster Hospital Mankhool | Q13: Dubai Mall / City Centre | R13: Al Khaleej / E11 | S13: 15 | T13: 25 | U13: 15 | V13: 45 | W13: 2 | X13: 1750000 | Y13: 1750000 | Z13: 5.5 | AA13: 6 | AB13: 10 | AC13: 12 | AD13: 15.5 | AE13: 18 | AF13: 2024 | AH13: Apartment | AI13: MainstreamSelective | AJ13: TopTier | AK13: Balanced / selective | AL13: Market remains active but increasingly differentiated by developer, micro-location, livability, and pricing discipline. | AM13: 11 | AN13: 5.75 | AO13: 0.55 | AP13: 0 | AQ13: 0 | AR13: 0 | AS13: 0.01 | AT13: 0.005 | AU13: 0 | AV13: -0.005 | AW13: =IF(X13="","",(AM13/100*AO13)+AP13+AQ13+AR13) | AX13: =IF(X13="","",AS13+AT13+AU13+AV13) | AY13: =IF(AZ13="","",ROUND(AZ13*(1+Assumptions!$B$10),0)) | AZ13: =IF(X13="","",ROUND(X13*(1+AW13),0)) | BA13: =IF(AZ13="","",ROUND(AZ13*(1+Assumptions!$B$11),0)) | BB13: =IF(AZ13="","",ROUND(AZ13*(1+AX13+Assumptions!$B$10),0)) | BC13: =IF(AZ13="","",ROUND(AZ13*(1+AX13),0)) | BD13: =IF(AZ13="","",ROUND(AZ13*(1+AX13+Assumptions!$B$11),0)) | BE13: =IF(AZ13="","",ROUND(AZ13*(1+AX13)*(1+AX13),0)) | BF13: Rules-based enrichment using launch-price anchor, cap-app realization, and 2026 segment conditions. | BG13: 2026-03-17 | BH13: DLD / Digital Dubai / CBUAE / Savills / Knight Frank-Moody’s / Reuters
A14: 13 | B14: Seagate | C14: Emaar Properties | D14: Rashid Yachts & Marina | E14: Apartments | F14: Waterfront | G14: 1.6M | H14: 2000 | I14: 25 | J14: 80/20 | K14: 2023 | L14: 6.0-6.5 | M14: 8-10 | N14: 14.0-16.5 | O14: New Academy School | P14: Aster Hospital Mankhool | Q14: Dubai Mall / City Centre | R14: Al Khaleej / E11 | S14: 15 | T14: 25 | U14: 15 | V14: 45 | W14: 2 | X14: 1600000 | Y14: 1600000 | Z14: 6 | AA14: 6.5 | AB14: 8 | AC14: 10 | AD14: 14 | AE14: 16.5 | AF14: 2023 | AH14: Apartment | AI14: MainstreamSelective | AJ14: TopTier | AK14: Balanced / selective | AL14: Market remains active but increasingly differentiated by developer, micro-location, livability, and pricing discipline. | AM14: 9 | AN14: 6.25 | AO14: 0.55 | AP14: 0 | AQ14: 0 | AR14: 0 | AS14: 0.01 | AT14: 0.005 | AU14: 0.0025 | AV14: -0.005 | AW14: =IF(X14="","",(AM14/100*AO14)+AP14+AQ14+AR14) | AX14: =IF(X14="","",AS14+AT14+AU14+AV14) | AY14: =IF(AZ14="","",ROUND(AZ14*(1+Assumptions!$B$10),0)) | AZ14: =IF(X14="","",ROUND(X14*(1+AW14),0)) | BA14: =IF(AZ14="","",ROUND(AZ14*(1+Assumptions!$B$11),0)) | BB14: =IF(AZ14="","",ROUND(AZ14*(1+AX14+Assumptions!$B$10),0)) | BC14: =IF(AZ14="","",ROUND(AZ14*(1+AX14),0)) | BD14: =IF(AZ14="","",ROUND(AZ14*(1+AX14+Assumptions!$B$11),0)) | BE14: =IF(AZ14="","",ROUND(AZ14*(1+AX14)*(1+AX14),0)) | BF14: Rules-based enrichment using launch-price anchor, cap-app realization, and 2026 segment conditions. | BG14: 2026-03-17 | BH14: DLD / Digital Dubai / CBUAE / Savills / Knight Frank-Moody’s / Reuters
A15: 14 | B15: Clearpoint | C15: Emaar Properties | D15: Rashid Yachts & Marina | E15: Apartments | F15: Waterfront | G15: 1.6M | H15: 2000 | I15: 25 | J15: 80/20 | K15: 2023 | L15: 6.0-6.5 | M15: 8-10 | N15: 14.0-16.5 | O15: New Academy School | P15: Aster Hospital Mankhool | Q15: Dubai Mall / City Centre | R15: Al Khaleej / E11 | S15: 15 | T15: 25 | U15: 15 | V15: 45 | W15: 2 | X15: 1600000 | Y15: 1600000 | Z15: 6 | AA15: 6.5 | AB15: 8 | AC15: 10 | AD15: 14 | AE15: 16.5 | AF15: 2023 | AH15: Apartment | AI15: MainstreamSelective | AJ15: TopTier | AK15: Balanced / selective | AL15: Market remains active but increasingly differentiated by developer, micro-location, livability, and pricing discipline. | AM15: 9 | AN15: 6.25 | AO15: 0.55 | AP15: 0 | AQ15: 0 | AR15: 0 | AS15: 0.01 | AT15: 0.005 | AU15: 0.0025 | AV15: -0.005 | AW15: =IF(X15="","",(AM15/100*AO15)+AP15+AQ15+AR15) | AX15: =IF(X15="","",AS15+AT15+AU15+AV15) | AY15: =IF(AZ15="","",ROUND(AZ15*(1+Assumptions!$B$10),0)) | AZ15: =IF(X15="","",ROUND(X15*(1+AW15),0)) | BA15: =IF(AZ15="","",ROUND(AZ15*(1+Assumptions!$B$11),0)) | BB15: =IF(AZ15="","",ROUND(AZ15*(1+AX15+Assumptions!$B$10),0)) | BC15: =IF(AZ15="","",ROUND(AZ15*(1+AX15),0)) | BD15: =IF(AZ15="","",ROUND(AZ15*(1+AX15+Assumptions!$B$11),0)) | BE15: =IF(AZ15="","",ROUND(AZ15*(1+AX15)*(1+AX15),0)) | BF15: Rules-based enrichment using launch-price anchor, cap-app realization, and 2026 segment conditions. | BG15: 2026-03-17 | BH15: DLD / Digital Dubai / CBUAE / Savills / Knight Frank-Moody’s / Reuters
A16: 15 | B16: Sunridge | C16: Emaar Properties | D16: Rashid Yachts & Marina | E16: Apartments | F16: Waterfront | G16: 1.55M | H16: 1950 | I16: 25 | J16: 80/20 | K16: 2023 | L16: 6.0-6.5 | M16: 8-10 | N16: 14.0-16.5 | O16: New Academy School | P16: Aster Hospital Mankhool | Q16: Dubai Mall / City Centre | R16: Al Khaleej / E11 | S16: 15 | T16: 25 | U16: 15 | V16: 45 | W16: 2 | X16: 1550000 | Y16: 1550000 | Z16: 6 | AA16: 6.5 | AB16: 8 | AC16: 10 | AD16: 14 | AE16: 16.5 | AF16: 2023 | AH16: Apartment | AI16: MainstreamSelective | AJ16: TopTier | AK16: Balanced / selective | AL16: Market remains active but increasingly differentiated by developer, micro-location, livability, and pricing discipline. | AM16: 9 | AN16: 6.25 | AO16: 0.55 | AP16: 0 | AQ16: 0 | AR16: 0 | AS16: 0.01 | AT16: 0.005 | AU16: 0.0025 | AV16: -0.005 | AW16: =IF(X16="","",(AM16/100*AO16)+AP16+AQ16+AR16) | AX16: =IF(X16="","",AS16+AT16+AU16+AV16) | AY16: =IF(AZ16="","",ROUND(AZ16*(1+Assumptions!$B$10),0)) | AZ16: =IF(X16="","",ROUND(X16*(1+AW16),0)) | BA16: =IF(AZ16="","",ROUND(AZ16*(1+Assumptions!$B$11),0)) | BB16: =IF(AZ16="","",ROUND(AZ16*(1+AX16+Assumptions!$B$10),0)) | BC16: =IF(AZ16="","",ROUND(AZ16*(1+AX16),0)) | BD16: =IF(AZ16="","",ROUND(AZ16*(1+AX16+Assumptions!$B$11),0)) | BE16: =IF(AZ16="","",ROUND(AZ16*(1+AX16)*(1+AX16),0)) | BF16: Rules-based enrichment using launch-price anchor, cap-app realization, and 2026 segment conditions. | BG16: 2026-03-17 | BH16: DLD / Digital Dubai / CBUAE / Savills / Knight Frank-Moody’s / Reuters
A17: 16 | B17: Dubai Creek Harbour | C17: Emaar Properties | D17: The Creek | E17: Mixed | F17: Waterfront / City | I17: 25-30 | J17: Varies | K17: Ongoing | L17: 5.5-6.5 | M17: 9-12 | N17: 14.5-18.5 | O17: Swiss Intl School | P17: American Hospital | Q17: Dubai Festival City | R17: Ras Al Khor / E44 | S17: 12 | T17: 25 | U17: 10 | V17: 40 | W17: 2 | Z17: 5.5 | AA17: 6.5 | AB17: 9 | AC17: 12 | AD17: 14.5 | AE17: 18.5 | AH17: Mixed/Other | AI17: MainstreamSelective | AJ17: TopTier | AK17: Balanced / selective | AL17: Market remains active but increasingly differentiated by developer, micro-location, livability, and pricing discipline. | AM17: 10.5 | AN17: 6 | AO17: 0.25 | AP17: 0 | AQ17: 0 | AR17: 0 | AS17: 0.01 | AT17: 0.005 | AU17: 0 | AV17: -0.005 | AW17: =IF(X17="","",(AM17/100*AO17)+AP17+AQ17+AR17) | AX17: =IF(X17="","",AS17+AT17+AU17+AV17) | AY17: =IF(AZ17="","",ROUND(AZ17*(1+Assumptions!$B$10),0)) | AZ17: =IF(X17="","",ROUND(X17*(1+AW17),0)) | BA17: =IF(AZ17="","",ROUND(AZ17*(1+Assumptions!$B$11),0)) | BB17: =IF(AZ17="","",ROUND(AZ17*(1+AX17+Assumptions!$B$10),0)) | BC17: =IF(AZ17="","",ROUND(AZ17*(1+AX17),0)) | BD17: =IF(AZ17="","",ROUND(AZ17*(1+AX17+Assumptions!$B$11),0)) | BE17: =IF(AZ17="","",ROUND(AZ17*(1+AX17)*(1+AX17),0)) | BF17: Rules-based enrichment using launch-price anchor, cap-app realization, and 2026 segment conditions. | BG17: 2026-03-17 | BH17: DLD / Digital Dubai / CBUAE / Savills / Knight Frank-Moody’s / Reuters
A18: 17 | B18: Valo | C18: Emaar Properties | D18: Dubai Creek Harbour | E18: Apartments | F18: Waterfront / Metro | G18: 1.9M | H18: 2300 | I18: 25 | J18: 80/20 | K18: 2024 | L18: 5.5-6.0 | M18: 9-12 | N18: 14.5-18.0 | O18: Swiss Intl School | P18: American Hospital | Q18: Dubai Festival City | R18: Ras Al Khor / E44 | S18: 12 | T18: 25 | U18: 10 | V18: 40 | W18: 2 | X18: 1900000 | Y18: 1900000 | Z18: 5.5 | AA18: 6 | AB18: 9 | AC18: 12 | AD18: 14.5 | AE18: 18 | AF18: 2024 | AH18: Apartment | AI18: Prime | AJ18: TopTier | AK18: Prime resilient / selective | AL18: Better support from quality, branding, and scarcer prime stock; still entry-price sensitive. | AM18: 10.5 | AN18: 5.75 | AO18: 0.55 | AP18: 0.02 | AQ18: 0 | AR18: 0 | AS18: 0.03 | AT18: 0.005 | AU18: 0 | AV18: -0.005 | AW18: =IF(X18="","",(AM18/100*AO18)+AP18+AQ18+AR18) | AX18: =IF(X18="","",AS18+AT18+AU18+AV18) | AY18: =IF(AZ18="","",ROUND(AZ18*(1+Assumptions!$B$10),0)) | AZ18: =IF(X18="","",ROUND(X18*(1+AW18),0)) | BA18: =IF(AZ18="","",ROUND(AZ18*(1+Assumptions!$B$11),0)) | BB18: =IF(AZ18="","",ROUND(AZ18*(1+AX18+Assumptions!$B$10),0)) | BC18: =IF(AZ18="","",ROUND(AZ18*(1+AX18),0)) | BD18: =IF(AZ18="","",ROUND(AZ18*(1+AX18+Assumptions!$B$11),0)) | BE18: =IF(AZ18="","",ROUND(AZ18*(1+AX18)*(1+AX18),0)) | BF18: Rules-based enrichment using launch-price anchor, cap-app realization, and 2026 segment conditions. | BG18: 2026-03-17 | BH18: DLD / Digital Dubai / CBUAE / Savills / Knight Frank-Moody’s / Reuters
A19: 18 | B19: Aeon | C19: Emaar Properties | D19: Dubai Creek Harbour | E19: Apartments | F19: Waterfront | G19: 1.8M | H19: 2200 | I19: 25 | J19: 80/20 | K19: 2024 | L19: 5.5-6.0 | M19: 9-12 | N19: 14.5-18.0 | O19: Swiss Intl School | P19: American Hospital | Q19: Dubai Festival City | R19: Ras Al Khor / E44 | S19: 12 | T19: 25 | U19: 10 | V19: 40 | W19: 2 | X19: 1800000 | Y19: 1800000 | Z19: 5.5 | AA19: 6 | AB19: 9 | AC19: 12 | AD19: 14.5 | AE19: 18 | AF19: 2024 | AH19: Apartment | AI19: Prime | AJ19: TopTier | AK19: Prime resilient / selective | AL19: Better support from quality, branding, and scarcer prime stock; still entry-price sensitive. | AM19: 10.5 | AN19: 5.75 | AO19: 0.55 | AP19: 0.02 | AQ19: 0 | AR19: 0 | AS19: 0.03 | AT19: 0.005 | AU19: 0 | AV19: -0.005 | AW19: =IF(X19="","",(AM19/100*AO19)+AP19+AQ19+AR19) | AX19: =IF(X19="","",AS19+AT19+AU19+AV19) | AY19: =IF(AZ19="","",ROUND(AZ19*(1+Assumptions!$B$10),0)) | AZ19: =IF(X19="","",ROUND(X19*(1+AW19),0)) | BA19: =IF(AZ19="","",ROUND(AZ19*(1+Assumptions!$B$11),0)) | BB19: =IF(AZ19="","",ROUND(AZ19*(1+AX19+Assumptions!$B$10),0)) | BC19: =IF(AZ19="","",ROUND(AZ19*(1+AX19),0)) | BD19: =IF(AZ19="","",ROUND(AZ19*(1+AX19+Assumptions!$B$11),0)) | BE19: =IF(AZ19="","",ROUND(AZ19*(1+AX19)*(1+AX19),0)) | BF19: Rules-based enrichment using launch-price anchor, cap-app realization, and 2026 segment conditions. | BG19: 2026-03-17 | BH19: DLD / Digital Dubai / CBUAE / Savills / Knight Frank-Moody’s / Reuters
A20: 19 | B20: Oria | C20: Emaar Properties | D20: Dubai Creek Harbour | E20: Apartments | F20: Waterfront | G20: 1.7M | H20: 2100 | I20: 25 | J20: 80/20 | K20: 2024 | L20: 6.0-6.5 | M20: 9-12 | N20: 15.0-18.5 | O20: Swiss Intl School | P20: American Hospital | Q20: Dubai Festival City | R20: Ras Al Khor / E44 | S20: 12 | T20: 25 | U20: 10 | V20: 40 | W20: 2 | X20: 1700000 | Y20: 1700000 | Z20: 6 | AA20: 6.5 | AB20: 9 | AC20: 12 | AD20: 15 | AE20: 18.5 | AF20: 2024 | AH20: Apartment | AI20: Prime | AJ20: TopTier | AK20: Prime resilient / selective | AL20: Better support from quality, branding, and scarcer prime stock; still entry-price sensitive. | AM20: 10.5 | AN20: 6.25 | AO20: 0.55 | AP20: 0.02 | AQ20: 0 | AR20: 0 | AS20: 0.03 | AT20: 0.005 | AU20: 0.0025 | AV20: -0.005 | AW20: =IF(X20="","",(AM20/100*AO20)+AP20+AQ20+AR20) | AX20: =IF(X20="","",AS20+AT20+AU20+AV20) | AY20: =IF(AZ20="","",ROUND(AZ20*(1+Assumptions!$B$10),0)) | AZ20: =IF(X20="","",ROUND(X20*(1+AW20),0)) | BA20: =IF(AZ20="","",ROUND(AZ20*(1+Assumptions!$B$11),0)) | BB20: =IF(AZ20="","",ROUND(AZ20*(1+AX20+Assumptions!$B$10),0)) | BC20: =IF(AZ20="","",ROUND(AZ20*(1+AX20),0)) | BD20: =IF(AZ20="","",ROUND(AZ20*(1+AX20+Assumptions!$B$11),0)) | BE20: =IF(AZ20="","",ROUND(AZ20*(1+AX20)*(1+AX20),0)) | BF20: Rules-based enrichment using launch-price anchor, cap-app realization, and 2026 segment conditions. | BG20: 2026-03-17 | BH20: DLD / Digital Dubai / CBUAE / Savills / Knight Frank-Moody’s / Reuters
A21: 20 | B21: Mangrove (Creek Beach) | C21: Emaar Properties | D21: Dubai Creek Harbour | E21: Apartments | F21: Beachfront | G21: 1.6M | H21: 2000 | I21: 25 | J21: 80/20 | K21: 2024 | L21: 6.0-6.5 | M21: 9-12 | N21: 15.0-18.5 | O21: Swiss Intl School | P21: American Hospital | Q21: Dubai Festival City | R21: Ras Al Khor / E44 | S21: 12 | T21: 25 | U21: 10 | V21: 40 | W21: 2 | X21: 1600000 | Y21: 1600000 | Z21: 6 | AA21: 6.5 | AB21: 9 | AC21: 12 | AD21: 15 | AE21: 18.5 | AF21: 2024 | AH21: Apartment | AI21: Prime | AJ21: TopTier | AK21: Prime resilient / selective | AL21: Better support from quality, branding, and scarcer prime stock; still entry-price sensitive. | AM21: 10.5 | AN21: 6.25 | AO21: 0.55 | AP21: 0.02 | AQ21: 0 | AR21: 0 | AS21: 0.03 | AT21: 0.005 | AU21: 0.0025 | AV21: -0.005 | AW21: =IF(X21="","",(AM21/100*AO21)+AP21+AQ21+AR21) | AX21: =IF(X21="","",AS21+AT21+AU21+AV21) | AY21: =IF(AZ21="","",ROUND(AZ21*(1+Assumptions!$B$10),0)) | AZ21: =IF(X21="","",ROUND(X21*(1+AW21),0)) | BA21: =IF(AZ21="","",ROUND(AZ21*(1+Assumptions!$B$11),0)) | BB21: =IF(AZ21="","",ROUND(AZ21*(1+AX21+Assumptions!$B$10),0)) | BC21: =IF(AZ21="","",ROUND(AZ21*(1+AX21),0)) | BD21: =IF(AZ21="","",ROUND(AZ21*(1+AX21+Assumptions!$B$11),0)) | BE21: =IF(AZ21="","",ROUND(AZ21*(1+AX21)*(1+AX21),0)) | BF21: Rules-based enrichment using launch-price anchor, cap-app realization, and 2026 segment conditions. | BG21: 2026-03-17 | BH21: DLD / Digital Dubai / CBUAE / Savills / Knight Frank-Moody’s / Reuters
A22: 21 | B22: Altan | C22: Emaar Properties | D22: Dubai Creek Harbour | E22: Apartments | F22: Waterfront | G22: 1.8M | H22: 2200 | I22: 25 | J22: 80/20 | K22: 2024 | L22: 5.5-6.0 | M22: 9-12 | N22: 14.5-18.0 | O22: Swiss Intl School | P22: American Hospital | Q22: Dubai Festival City | R22: Ras Al Khor / E44 | S22: 12 | T22: 25 | U22: 10 | V22: 40 | W22: 2 | X22: 1800000 | Y22: 1800000 | Z22: 5.5 | AA22: 6 | AB22: 9 | AC22: 12 | AD22: 14.5 | AE22: 18 | AF22: 2024 | AH22: Apartment | AI22: Prime | AJ22: TopTier | AK22: Prime resilient / selective | AL22: Better support from quality, branding, and scarcer prime stock; still entry-price sensitive. | AM22: 10.5 | AN22: 5.75 | AO22: 0.55 | AP22: 0.02 | AQ22: 0 | AR22: 0 | AS22: 0.03 | AT22: 0.005 | AU22: 0 | AV22: -0.005 | AW22: =IF(X22="","",(AM22/100*AO22)+AP22+AQ22+AR22) | AX22: =IF(X22="","",AS22+AT22+AU22+AV22) | AY22: =IF(AZ22="","",ROUND(AZ22*(1+Assumptions!$B$10),0)) | AZ22: =IF(X22="","",ROUND(X22*(1+AW22),0)) | BA22: =IF(AZ22="","",ROUND(AZ22*(1+Assumptions!$B$11),0)) | BB22: =IF(AZ22="","",ROUND(AZ22*(1+AX22+Assumptions!$B$10),0)) | BC22: =IF(AZ22="","",ROUND(AZ22*(1+AX22),0)) | BD22: =IF(AZ22="","",ROUND(AZ22*(1+AX22+Assumptions!$B$11),0)) | BE22: =IF(AZ22="","",ROUND(AZ22*(1+AX22)*(1+AX22),0)) | BF22: Rules-based enrichment using launch-price anchor, cap-app realization, and 2026 segment conditions. | BG22: 2026-03-17 | BH22: DLD / Digital Dubai / CBUAE / Savills / Knight Frank-Moody’s / Reuters
A23: 22 | B23: Silva | C23: Emaar Properties | D23: Dubai Creek Harbour | E23: Apartments | F23: Waterfront | G23: 1.85M | H23: 2250 | I23: 25 | J23: 80/20 | K23: 2024 | L23: 5.5-6.0 | M23: 9-12 | N23: 14.5-18.0 | O23: Swiss Intl School | P23: American Hospital | Q23: Dubai Festival City | R23: Ras Al Khor / E44 | S23: 12 | T23: 25 | U23: 10 | V23: 40 | W23: 2 | X23: 1850000 | Y23: 1850000 | Z23: 5.5 | AA23: 6 | AB23: 9 | AC23: 12 | AD23: 14.5 | AE23: 18 | AF23: 2024 | AH23: Apartment | AI23: Prime | AJ23: TopTier | AK23: Prime resilient / selective | AL23: Better support from quality, branding, and scarcer prime stock; still entry-price sensitive. | AM23: 10.5 | AN23: 5.75 | AO23: 0.55 | AP23: 0.02 | AQ23: 0 | AR23: 0 | AS23: 0.03 | AT23: 0.005 | AU23: 0 | AV23: -0.005 | AW23: =IF(X23="","",(AM23/100*AO23)+AP23+AQ23+AR23) | AX23: =IF(X23="","",AS23+AT23+AU23+AV23) | AY23: =IF(AZ23="","",ROUND(AZ23*(1+Assumptions!$B$10),0)) | AZ23: =IF(X23="","",ROUND(X23*(1+AW23),0)) | BA23: =IF(AZ23="","",ROUND(AZ23*(1+Assumptions!$B$11),0)) | BB23: =IF(AZ23="","",ROUND(AZ23*(1+AX23+Assumptions!$B$10),0)) | BC23: =IF(AZ23="","",ROUND(AZ23*(1+AX23),0)) | BD23: =IF(AZ23="","",ROUND(AZ23*(1+AX23+Assumptions!$B$11),0)) | BE23: =IF(AZ23="","",ROUND(AZ23*(1+AX23)*(1+AX23),0)) | BF23: Rules-based enrichment using launch-price anchor, cap-app realization, and 2026 segment conditions. | BG23: 2026-03-17 | BH23: DLD / Digital Dubai / CBUAE / Savills / Knight Frank-Moody’s / Reuters
A24: 23 | B24: Albero | C24: Emaar Properties | D24: Dubai Creek Harbour | E24: Apartments | F24: Waterfront | G24: 1.75M | H24: 2150 | I24: 25 | J24: 80/20 | K24: 2024 | L24: 5.5-6.0 | M24: 9-12 | N24: 14.5-18.0 | O24: Swiss Intl School | P24: American Hospital | Q24: Dubai Festival City | R24: Ras Al Khor / E44 | S24: 12 | T24: 25 | U24: 10 | V24: 40 | W24: 2 | X24: 1750000 | Y24: 1750000 | Z24: 5.5 | AA24: 6 | AB24: 9 | AC24: 12 | AD24: 14.5 | AE24: 18 | AF24: 2024 | AH24: Apartment | AI24: Prime | AJ24: TopTier | AK24: Prime resilient / selective | AL24: Better support from quality, branding, and scarcer prime stock; still entry-price sensitive. | AM24: 10.5 | AN24: 5.75 | AO24: 0.55 | AP24: 0.02 | AQ24: 0 | AR24: 0 | AS24: 0.03 | AT24: 0.005 | AU24: 0 | AV24: -0.005 | AW24: =IF(X24="","",(AM24/100*AO24)+AP24+AQ24+AR24) | AX24: =IF(X24="","",AS24+AT24+AU24+AV24) | AY24: =IF(AZ24="","",ROUND(AZ24*(1+Assumptions!$B$10),0)) | AZ24: =IF(X24="","",ROUND(X24*(1+AW24),0)) | BA24: =IF(AZ24="","",ROUND(AZ24*(1+Assumptions!$B$11),0)) | BB24: =IF(AZ24="","",ROUND(AZ24*(1+AX24+Assumptions!$B$10),0)) | BC24: =IF(AZ24="","",ROUND(AZ24*(1+AX24),0)) | BD24: =IF(AZ24="","",ROUND(AZ24*(1+AX24+Assumptions!$B$11),0)) | BE24: =IF(AZ24="","",ROUND(AZ24*(1+AX24)*(1+AX24),0)) | BF24: Rules-based enrichment using launch-price anchor, cap-app realization, and 2026 segment conditions. | BG24: 2026-03-17 | BH24: DLD / Digital Dubai / CBUAE / Savills / Knight Frank-Moody’s / Reuters
A25: 24 | B25: Montiva | C25: Emaar Properties | D25: Dubai Creek Harbour | E25: Apartments | F25: Waterfront | G25: 1.8M | H25: 2200 | I25: 25 | J25: 80/20 | K25: 2024 | L25: 5.5-6.0 | M25: 9-12 | N25: 14.5-18.0 | O25: Swiss Intl School | P25: American Hospital | Q25: Dubai Festival City | R25: Ras Al Khor / E44 | S25: 12 | T25: 25 | U25: 10 | V25: 40 | W25: 2 | X25: 1800000 | Y25: 1800000 | Z25: 5.5 | AA25: 6 | AB25: 9 | AC25: 12 | AD25: 14.5 | AE25: 18 | AF25: 2024 | AH25: Apartment | AI25: Prime | AJ25: TopTier | AK25: Prime resilient / selective | AL25: Better support from quality, branding, and scarcer prime stock; still entry-price sensitive. | AM25: 10.5 | AN25: 5.75 | AO25: 0.55 | AP25: 0.02 | AQ25: 0 | AR25: 0 | AS25: 0.03 | AT25: 0.005 | AU25: 0 | AV25: -0.005 | AW25: =IF(X25="","",(AM25/100*AO25)+AP25+AQ25+AR25) | AX25: =IF(X25="","",AS25+AT25+AU25+AV25) | AY25: =IF(AZ25="","",ROUND(AZ25*(1+Assumptions!$B$10),0)) | AZ25: =IF(X25="","",ROUND(X25*(1+AW25),0)) | BA25: =IF(AZ25="","",ROUND(AZ25*(1+Assumptions!$B$11),0)) | BB25: =IF(AZ25="","",ROUND(AZ25*(1+AX25+Assumptions!$B$10),0)) | BC25: =IF(AZ25="","",ROUND(AZ25*(1+AX25),0)) | BD25: =IF(AZ25="","",ROUND(AZ25*(1+AX25+Assumptions!$B$11),0)) | BE25: =IF(AZ25="","",ROUND(AZ25*(1+AX25)*(1+AX25),0)) | BF25: Rules-based enrichment using launch-price anchor, cap-app realization, and 2026 segment conditions. | BG25: 2026-03-17 | BH25: DLD / Digital Dubai / CBUAE / Savills / Knight Frank-Moody’s / Reuters
A26: 25 | B26: Creek Waters 1 | C26: Emaar Properties | D26: Dubai Creek Harbour | E26: Apartments | F26: Waterfront / Island | G26: 2.2M | H26: 2400 | I26: 25 | J26: 80/20 | K26: 2023 | L26: 5.0-5.5 | M26: 8-10 | N26: 13.0-15.5 | O26: Swiss Intl School | P26: American Hospital | Q26: Dubai Festival City | R26: Ras Al Khor / E44 | S26: 12 | T26: 25 | U26: 10 | V26: 40 | W26: 2 | X26: 2200000 | Y26: 2200000 | Z26: 5 | AA26: 5.5 | AB26: 8 | AC26: 10 | AD26: 13 | AE26: 15.5 | AF26: 2023 | AH26: Apartment | AI26: Prime | AJ26: TopTier | AK26: Prime resilient / selective | AL26: Better support from quality, branding, and scarcer prime stock; still entry-price sensitive. | AM26: 9 | AN26: 5.25 | AO26: 0.55 | AP26: 0.02 | AQ26: 0 | AR26: 0 | AS26: 0.03 | AT26: 0.005 | AU26: 0 | AV26: -0.005 | AW26: =IF(X26="","",(AM26/100*AO26)+AP26+AQ26+AR26) | AX26: =IF(X26="","",AS26+AT26+AU26+AV26) | AY26: =IF(AZ26="","",ROUND(AZ26*(1+Assumptions!$B$10),0)) | AZ26: =IF(X26="","",ROUND(X26*(1+AW26),0)) | BA26: =IF(AZ26="","",ROUND(AZ26*(1+Assumptions!$B$11),0)) | BB26: =IF(AZ26="","",ROUND(AZ26*(1+AX26+Assumptions!$B$10),0)) | BC26: =IF(AZ26="","",ROUND(AZ26*(1+AX26),0)) | BD26: =IF(AZ26="","",ROUND(AZ26*(1+AX26+Assumptions!$B$11),0)) | BE26: =IF(AZ26="","",ROUND(AZ26*(1+AX26)*(1+AX26),0)) | BF26: Rules-based enrichment using launch-price anchor, cap-app realization, and 2026 segment conditions. | BG26: 2026-03-17 | BH26: DLD / Digital Dubai / CBUAE / Savills / Knight Frank-Moody’s / Reuters
A27: 26 | B27: Creek Waters 2 | C27: Emaar Properties | D27: Dubai Creek Harbour | E27: Apartments | F27: Waterfront / Island | G27: 2.3M | H27: 2450 | I27: 25 | J27: 80/20 | K27: 2023 | L27: 5.0-5.5 | M27: 8-10 | N27: 13.0-15.5 | O27: Swiss Intl School | P27: American Hospital | Q27: Dubai Festival City | R27: Ras Al Khor / E44 | S27: 12 | T27: 25 | U27: 10 | V27: 40 | W27: 2 | X27: 2300000 | Y27: 2300000 | Z27: 5 | AA27: 5.5 | AB27: 8 | AC27: 10 | AD27: 13 | AE27: 15.5 | AF27: 2023 | AH27: Apartment | AI27: Prime | AJ27: TopTier | AK27: Prime resilient / selective | AL27: Better support from quality, branding, and scarcer prime stock; still entry-price sensitive. | AM27: 9 | AN27: 5.25 | AO27: 0.55 | AP27: 0.02 | AQ27: 0 | AR27: 0 | AS27: 0.03 | AT27: 0.005 | AU27: 0 | AV27: -0.005 | AW27: =IF(X27="","",(AM27/100*AO27)+AP27+AQ27+AR27) | AX27: =IF(X27="","",AS27+AT27+AU27+AV27) | AY27: =IF(AZ27="","",ROUND(AZ27*(1+Assumptions!$B$10),0)) | AZ27: =IF(X27="","",ROUND(X27*(1+AW27),0)) | BA27: =IF(AZ27="","",ROUND(AZ27*(1+Assumptions!$B$11),0)) | BB27: =IF(AZ27="","",ROUND(AZ27*(1+AX27+Assumptions!$B$10),0)) | BC27: =IF(AZ27="","",ROUND(AZ27*(1+AX27),0)) | BD27: =IF(AZ27="","",ROUND(AZ27*(1+AX27+Assumptions!$B$11),0)) | BE27: =IF(AZ27="","",ROUND(AZ27*(1+AX27)*(1+AX27),0)) | BF27: Rules-based enrichment using launch-price anchor, cap-app realization, and 2026 segment conditions. | BG27: 2026-03-17 | BH27: DLD / Digital Dubai / CBUAE / Savills / Knight Frank-Moody’s / Reuters
A28: 27 | B28: Creek Gate | C28: Emaar Properties | D28: Dubai Creek Harbour | E28: Apartments | F28: Waterfront | G28: Resale | H28: 1800 | I28: 25 | J28: Completed | K28: 2017 | L28: 6.0-6.5 | M28: 5-7 | N28: 11.0-13.5 | O28: Swiss Intl School | P28: American Hospital | Q28: Dubai Festival City | R28: Ras Al Khor / E44 | S28: 12 | T28: 25 | U28: 10 | V28: 40 | W28: 2 | Z28: 6 | AA28: 6.5 | AB28: 5 | AC28: 7 | AD28: 11 | AE28: 13.5 | AF28: 2017 | AH28: Apartment | AI28: Prime | AJ28: TopTier | AK28: Prime resilient / selective | AL28: Better support from quality, branding, and scarcer prime stock; still entry-price sensitive. | AM28: 6 | AN28: 6.25 | AO28: 0.55 | AP28: 0.02 | AQ28: 0 | AR28: 0 | AS28: 0.03 | AT28: 0.005 | AU28: 0.0025 | AV28: -0.005 | AW28: =IF(X28="","",(AM28/100*AO28)+AP28+AQ28+AR28) | AX28: =IF(X28="","",AS28+AT28+AU28+AV28) | AY28: =IF(AZ28="","",ROUND(AZ28*(1+Assumptions!$B$10),0)) | AZ28: =IF(X28="","",ROUND(X28*(1+AW28),0)) | BA28: =IF(AZ28="","",ROUND(AZ28*(1+Assumptions!$B$11),0)) | BB28: =IF(AZ28="","",ROUND(AZ28*(1+AX28+Assumptions!$B$10),0)) | BC28: =IF(AZ28="","",ROUND(AZ28*(1+AX28),0)) | BD28: =IF(AZ28="","",ROUND(AZ28*(1+AX28+Assumptions!$B$11),0)) | BE28: =IF(AZ28="","",ROUND(AZ28*(1+AX28)*(1+AX28),0)) | BF28: Rules-based enrichment using launch-price anchor, cap-app realization, and 2026 segment conditions. | BG28: 2026-03-17 | BH28: DLD / Digital Dubai / CBUAE / Savills / Knight Frank-Moody’s / Reuters
A29: 28 | B29: Address Grand Creek | C29: Emaar Properties | D29: Dubai Creek Harbour | E29: Branded Residences | F29: Luxury Hotel | G29: 3.5M | H29: 3500 | I29: 45+ | J29: Varies | K29: 2023 | L29: 4.0-5.0 | M29: 8-10 | N29: 12.0-15.0 | O29: Swiss Intl School | P29: American Hospital | Q29: Dubai Festival City | R29: Ras Al Khor / E44 | S29: 12 | T29: 25 | U29: 10 | V29: 40 | W29: 2 | X29: 3500000 | Y29: 3500000 | Z29: 4 | AA29: 5 | AB29: 8 | AC29: 10 | AD29: 12 | AE29: 15 | AF29: 2023 | AH29: Apartment | AI29: Prime | AJ29: TopTier | AK29: Prime resilient / selective | AL29: Better support from quality, branding, and scarcer prime stock; still entry-price sensitive. | AM29: 9 | AN29: 4.5 | AO29: 0.55 | AP29: 0.02 | AQ29: 0 | AR29: 0 | AS29: 0.03 | AT29: 0.005 | AU29: 0 | AV29: -0.005 | AW29: =IF(X29="","",(AM29/100*AO29)+AP29+AQ29+AR29) | AX29: =IF(X29="","",AS29+AT29+AU29+AV29) | AY29: =IF(AZ29="","",ROUND(AZ29*(1+Assumptions!$B$10),0)) | AZ29: =IF(X29="","",ROUND(X29*(1+AW29),0)) | BA29: =IF(AZ29="","",ROUND(AZ29*(1+Assumptions!$B$11),0)) | BB29: =IF(AZ29="","",ROUND(AZ29*(1+AX29+Assumptions!$B$10),0)) | BC29: =IF(AZ29="","",ROUND(AZ29*(1+AX29),0)) | BD29: =IF(AZ29="","",ROUND(AZ29*(1+AX29+Assumptions!$B$11),0)) | BE29: =IF(AZ29="","",ROUND(AZ29*(1+AX29)*(1+AX29),0)) | BF29: Rules-based enrichment using launch-price anchor, cap-app realization, and 2026 segment conditions. | BG29: 2026-03-17 | BH29: DLD / Digital Dubai / CBUAE / Savills / Knight Frank-Moody’s / Reuters
A30: 29 | B30: Dubai Hills Estate | C30: Emaar Properties | D30: Al Khail Road | E30: Mixed | F30: Golf / Central Park | I30: 20-25 | J30: Varies | K30: Ongoing | L30: 5.5-6.5 | M30: 8-12 | N30: 13.5-18.5 | O30: GEMS Wellington | P30: King's College Hospital | Q30: Dubai Hills Mall | R30: Al Khail E44 | S30: 15 | T30: 15 | U30: 20 | V30: 30 | W30: 2 | Z30: 5.5 | AA30: 6.5 | AB30: 8 | AC30: 12 | AD30: 13.5 | AE30: 18.5 | AH30: Mixed/Other | AI30: MainstreamSelective | AJ30: TopTier | AK30: Balanced / selective | AL30: Market remains active but increasingly differentiated by developer, micro-location, livability, and pricing discipline. | AM30: 10 | AN30: 6 | AO30: 0.25 | AP30: 0 | AQ30: 0 | AR30: 0 | AS30: 0.01 | AT30: 0.005 | AU30: 0 | AV30: -0.005 | AW30: =IF(X30="","",(AM30/100*AO30)+AP30+AQ30+AR30) | AX30: =IF(X30="","",AS30+AT30+AU30+AV30) | AY30: =IF(AZ30="","",ROUND(AZ30*(1+Assumptions!$B$10),0)) | AZ30: =IF(X30="","",ROUND(X30*(1+AW30),0)) | BA30: =IF(AZ30="","",ROUND(AZ30*(1+Assumptions!$B$11),0)) | BB30: =IF(AZ30="","",ROUND(AZ30*(1+AX30+Assumptions!$B$10),0)) | BC30: =IF(AZ30="","",ROUND(AZ30*(1+AX30),0)) | BD30: =IF(AZ30="","",ROUND(AZ30*(1+AX30+Assumptions!$B$11),0)) | BE30: =IF(AZ30="","",ROUND(AZ30*(1+AX30)*(1+AX30),0)) | BF30: Rules-based enrichment using launch-price anchor, cap-app realization, and 2026 segment conditions. | BG30: 2026-03-17 | BH30: DLD / Digital Dubai / CBUAE / Savills / Knight Frank-Moody’s / Reuters
A31: 30 | B31: Park Gate 2 | C31: Emaar Properties | D31: Dubai Hills Estate | E31: Villas | F31: Gated / Park | G31: 4.5M | H31: 1800 | I31: 20 | J31: 80/20 | K31: 2024 | L31: 5.0-5.5 | M31: 8-12 | N31: 13.0-17.5 | O31: GEMS Wellington | P31: King's College Hospital | Q31: Dubai Hills Mall | R31: Al Khail E44 | S31: 15 | T31: 15 | U31: 20 | V31: 30 | W31: 2 | X31: 4500000 | Y31: 4500000 | Z31: 5 | AA31: 5.5 | AB31: 8 | AC31: 12 | AD31: 13 | AE31: 17.5 | AF31: 2024 | AH31: Villa | AI31: Prime | AJ31: TopTier | AK31: Prime resilient / selective | AL31: Better support from quality, branding, and scarcer prime stock; still entry-price sensitive. | AM31: 10 | AN31: 5.25 | AO31: 0.55 | AP31: 0.02 | AQ31: 0.015 | AR31: 0 | AS31: 0.03 | AT31: 0.005 | AU31: 0 | AV31: -0.005 | AW31: =IF(X31="","",(AM31/100*AO31)+AP31+AQ31+AR31) | AX31: =IF(X31="","",AS31+AT31+AU31+AV31) | AY31: =IF(AZ31="","",ROUND(AZ31*(1+Assumptions!$B$10),0)) | AZ31: =IF(X31="","",ROUND(X31*(1+AW31),0)) | BA31: =IF(AZ31="","",ROUND(AZ31*(1+Assumptions!$B$11),0)) | BB31: =IF(AZ31="","",ROUND(AZ31*(1+AX31+Assumptions!$B$10),0)) | BC31: =IF(AZ31="","",ROUND(AZ31*(1+AX31),0)) | BD31: =IF(AZ31="","",ROUND(AZ31*(1+AX31+Assumptions!$B$11),0)) | BE31: =IF(AZ31="","",ROUND(AZ31*(1+AX31)*(1+AX31),0)) | BF31: Rules-based enrichment using launch-price anchor, cap-app realization, and 2026 segment conditions. | BG31: 2026-03-17 | BH31: DLD / Digital Dubai / CBUAE / Savills / Knight Frank-Moody’s / Reuters
A32: 31 | B32: Rosehill | C32: Emaar Properties | D32: Dubai Hills Estate | E32: Apartments | F32: Community View | G32: 1.6M | H32: 1900 | I32: 22 | J32: 80/20 | K32: 2024 | L32: 6.0-6.5 | M32: 8-12 | N32: 14.0-18.5 | O32: GEMS Wellington | P32: King's College Hospital | Q32: Dubai Hills Mall | R32: Al Khail E44 | S32: 15 | T32: 15 | U32: 20 | V32: 30 | W32: 2 | X32: 1600000 | Y32: 1600000 | Z32: 6 | AA32: 6.5 | AB32: 8 | AC32: 12 | AD32: 14 | AE32: 18.5 | AF32: 2024 | AH32: Apartment | AI32: Prime | AJ32: TopTier | AK32: Prime resilient / selective | AL32: Better support from quality, branding, and scarcer prime stock; still entry-price sensitive. | AM32: 10 | AN32: 6.25 | AO32: 0.55 | AP32: 0.02 | AQ32: 0 | AR32: 0 | AS32: 0.03 | AT32: 0.005 | AU32: 0.0025 | AV32: -0.005 | AW32: =IF(X32="","",(AM32/100*AO32)+AP32+AQ32+AR32) | AX32: =IF(X32="","",AS32+AT32+AU32+AV32) | AY32: =IF(AZ32="","",ROUND(AZ32*(1+Assumptions!$B$10),0)) | AZ32: =IF(X32="","",ROUND(X32*(1+AW32),0)) | BA32: =IF(AZ32="","",ROUND(AZ32*(1+Assumptions!$B$11),0)) | BB32: =IF(AZ32="","",ROUND(AZ32*(1+AX32+Assumptions!$B$10),0)) | BC32: =IF(AZ32="","",ROUND(AZ32*(1+AX32),0)) | BD32: =IF(AZ32="","",ROUND(AZ32*(1+AX32+Assumptions!$B$11),0)) | BE32: =IF(AZ32="","",ROUND(AZ32*(1+AX32)*(1+AX32),0)) | BF32: Rules-based enrichment using launch-price anchor, cap-app realization, and 2026 segment conditions. | BG32: 2026-03-17 | BH32: DLD / Digital Dubai / CBUAE / Savills / Knight Frank-Moody’s / Reuters
A33: 32 | B33: Greencrest | C33: Emaar Properties | D33: Dubai Hills Estate | E33: Apartments | F33: Community View | G33: 1.55M | H33: 1850 | I33: 22 | J33: 80/20 | K33: 2024 | L33: 6.0-6.5 | M33: 8-12 | N33: 14.0-18.5 | O33: GEMS Wellington | P33: King's College Hospital | Q33: Dubai Hills Mall | R33: Al Khail E44 | S33: 15 | T33: 15 | U33: 20 | V33: 30 | W33: 2 | X33: 1550000 | Y33: 1550000 | Z33: 6 | AA33: 6.5 | AB33: 8 | AC33: 12 | AD33: 14 | AE33: 18.5 | AF33: 2024 | AH33: Apartment | AI33: Prime | AJ33: TopTier | AK33: Prime resilient / selective | AL33: Better support from quality, branding, and scarcer prime stock; still entry-price sensitive. | AM33: 10 | AN33: 6.25 | AO33: 0.55 | AP33: 0.02 | AQ33: 0 | AR33: 0 | AS33: 0.03 | AT33: 0.005 | AU33: 0.0025 | AV33: -0.005 | AW33: =IF(X33="","",(AM33/100*AO33)+AP33+AQ33+AR33) | AX33: =IF(X33="","",AS33+AT33+AU33+AV33) | AY33: =IF(AZ33="","",ROUND(AZ33*(1+Assumptions!$B$10),0)) | AZ33: =IF(X33="","",ROUND(X33*(1+AW33),0)) | BA33: =IF(AZ33="","",ROUND(AZ33*(1+Assumptions!$B$11),0)) | BB33: =IF(AZ33="","",ROUND(AZ33*(1+AX33+Assumptions!$B$10),0)) | BC33: =IF(AZ33="","",ROUND(AZ33*(1+AX33),0)) | BD33: =IF(AZ33="","",ROUND(AZ33*(1+AX33+Assumptions!$B$11),0)) | BE33: =IF(AZ33="","",ROUND(AZ33*(1+AX33)*(1+AX33),0)) | BF33: Rules-based enrichment using launch-price anchor, cap-app realization, and 2026 segment conditions. | BG33: 2026-03-17 | BH33: DLD / Digital Dubai / CBUAE / Savills / Knight Frank-Moody’s / Reuters
A34: 33 | B34: Palace Residences Hillside | C34: Emaar Properties | D34: Dubai Hills Estate | E34: Branded Apartments | F34: Golf / Park | G34: 2.5M | H34: 2400 | I34: 35 | J34: 80/20 | K34: 2024 | L34: 4.5-5.0 | M34: 8-12 | N34: 12.5-17.0 | O34: GEMS Wellington | P34: King's College Hospital | Q34: Dubai Hills Mall | R34: Al Khail E44 | S34: 15 | T34: 15 | U34: 20 | V34: 30 | W34: 2 | X34: 2500000 | Y34: 2500000 | Z34: 4.5 | AA34: 5 | AB34: 8 | AC34: 12 | AD34: 12.5 | AE34: 17 | AF34: 2024 | AH34: Apartment | AI34: Prime | AJ34: TopTier | AK34: Prime resilient / selective | AL34: Better support from quality, branding, and scarcer prime stock; still entry-price sensitive. | AM34: 10 | AN34: 4.75 | AO34: 0.55 | AP34: 0.02 | AQ34: 0 | AR34: 0 | AS34: 0.03 | AT34: 0.005 | AU34: 0 | AV34: -0.005 | AW34: =IF(X34="","",(AM34/100*AO34)+AP34+AQ34+AR34) | AX34: =IF(X34="","",AS34+AT34+AU34+AV34) | AY34: =IF(AZ34="","",ROUND(AZ34*(1+Assumptions!$B$10),0)) | AZ34: =IF(X34="","",ROUND(X34*(1+AW34),0)) | BA34: =IF(AZ34="","",ROUND(AZ34*(1+Assumptions!$B$11),0)) | BB34: =IF(AZ34="","",ROUND(AZ34*(1+AX34+Assumptions!$B$10),0)) | BC34: =IF(AZ34="","",ROUND(AZ34*(1+AX34),0)) | BD34: =IF(AZ34="","",ROUND(AZ34*(1+AX34+Assumptions!$B$11),0)) | BE34: =IF(AZ34="","",ROUND(AZ34*(1+AX34)*(1+AX34),0)) | BF34: Rules-based enrichment using launch-price anchor, cap-app realization, and 2026 segment conditions. | BG34: 2026-03-17 | BH34: DLD / Digital Dubai / CBUAE / Savills / Knight Frank-Moody’s / Reuters
A35: 34 | B35: Vida Residences Hillside | C35: Emaar Properties | D35: Dubai Hills Estate | E35: Branded Apartments | F35: Golf / Park | G35: 2.2M | H35: 2200 | I35: 30 | J35: 80/20 | K35: 2024 | L35: 5.0-5.5 | M35: 8-12 | N35: 13.0-17.5 | O35: GEMS Wellington | P35: King's College Hospital | Q35: Dubai Hills Mall | R35: Al Khail E44 | S35: 15 | T35: 15 | U35: 20 | V35: 30 | W35: 2 | X35: 2200000 | Y35: 2200000 | Z35: 5 | AA35: 5.5 | AB35: 8 | AC35: 12 | AD35: 13 | AE35: 17.5 | AF35: 2024 | AH35: Apartment | AI35: Prime | AJ35: TopTier | AK35: Prime resilient / selective | AL35: Better support from quality, branding, and scarcer prime stock; still entry-price sensitive. | AM35: 10 | AN35: 5.25 | AO35: 0.55 | AP35: 0.02 | AQ35: 0 | AR35: 0 | AS35: 0.03 | AT35: 0.005 | AU35: 0 | AV35: -0.005 | AW35: =IF(X35="","",(AM35/100*AO35)+AP35+AQ35+AR35) | AX35: =IF(X35="","",AS35+AT35+AU35+AV35) | AY35: =IF(AZ35="","",ROUND(AZ35*(1+Assumptions!$B$10),0)) | AZ35: =IF(X35="","",ROUND(X35*(1+AW35),0)) | BA35: =IF(AZ35="","",ROUND(AZ35*(1+Assumptions!$B$11),0)) | BB35: =IF(AZ35="","",ROUND(AZ35*(1+AX35+Assumptions!$B$10),0)) | BC35: =IF(AZ35="","",ROUND(AZ35*(1+AX35),0)) | BD35: =IF(AZ35="","",ROUND(AZ35*(1+AX35+Assumptions!$B$11),0)) | BE35: =IF(AZ35="","",ROUND(AZ35*(1+AX35)*(1+AX35),0)) | BF35: Rules-based enrichment using launch-price anchor, cap-app realization, and 2026 segment conditions. | BG35: 2026-03-17 | BH35: DLD / Digital Dubai / CBUAE / Savills / Knight Frank-Moody’s / Reuters
A36: 35 | B36: Golf Hillside | C36: Emaar Properties | D36: Dubai Hills Estate | E36: Apartments | F36: Golf Course | G36: 1.8M | H36: 2000 | I36: 22 | J36: 80/20 | K36: 2024 | L36: 5.5-6.0 | M36: 8-12 | N36: 13.5-18.0 | O36: GEMS Wellington | P36: King's College Hospital | Q36: Dubai Hills Mall | R36: Al Khail E44 | S36: 15 | T36: 15 | U36: 20 | V36: 30 | W36: 2 | X36: 1800000 | Y36: 1800000 | Z36: 5.5 | AA36: 6 | AB36: 8 | AC36: 12 | AD36: 13.5 | AE36: 18 | AF36: 2024 | AH36: Apartment | AI36: Prime | AJ36: TopTier | AK36: Prime resilient / selective | AL36: Better support from quality, branding, and scarcer prime stock; still entry-price sensitive. | AM36: 10 | AN36: 5.75 | AO36: 0.55 | AP36: 0.02 | AQ36: 0 | AR36: 0 | AS36: 0.03 | AT36: 0.005 | AU36: 0 | AV36: -0.005 | AW36: =IF(X36="","",(AM36/100*AO36)+AP36+AQ36+AR36) | AX36: =IF(X36="","",AS36+AT36+AU36+AV36) | AY36: =IF(AZ36="","",ROUND(AZ36*(1+Assumptions!$B$10),0)) | AZ36: =IF(X36="","",ROUND(X36*(1+AW36),0)) | BA36: =IF(AZ36="","",ROUND(AZ36*(1+Assumptions!$B$11),0)) | BB36: =IF(AZ36="","",ROUND(AZ36*(1+AX36+Assumptions!$B$10),0)) | BC36: =IF(AZ36="","",ROUND(AZ36*(1+AX36),0)) | BD36: =IF(AZ36="","",ROUND(AZ36*(1+AX36+Assumptions!$B$11),0)) | BE36: =IF(AZ36="","",ROUND(AZ36*(1+AX36)*(1+AX36),0)) | BF36: Rules-based enrichment using launch-price anchor, cap-app realization, and 2026 segment conditions. | BG36: 2026-03-17 | BH36: DLD / Digital Dubai / CBUAE / Savills / Knight Frank-Moody’s / Reuters
A37: 36 | B37: Parkland | C37: Emaar Properties | D37: Dubai Hills Estate | E37: Apartments | F37: Park View | G37: 1.7M | H37: 1950 | I37: 22 | J37: 80/20 | K37: 2024 | L37: 5.5-6.0 | M37: 8-12 | N37: 13.5-18.0 | O37: GEMS Wellington | P37: King's College Hospital | Q37: Dubai Hills Mall | R37: Al Khail E44 | S37: 15 | T37: 15 | U37: 20 | V37: 30 | W37: 2 | X37: 1700000 | Y37: 1700000 | Z37: 5.5 | AA37: 6 | AB37: 8 | AC37: 12 | AD37: 13.5 | AE37: 18 | AF37: 2024 | AH37: Apartment | AI37: Prime | AJ37: TopTier | AK37: Prime resilient / selective | AL37: Better support from quality, branding, and scarcer prime stock; still entry-price sensitive. | AM37: 10 | AN37: 5.75 | AO37: 0.55 | AP37: 0.02 | AQ37: 0 | AR37: 0 | AS37: 0.03 | AT37: 0.005 | AU37: 0 | AV37: -0.005 | AW37: =IF(X37="","",(AM37/100*AO37)+AP37+AQ37+AR37) | AX37: =IF(X37="","",AS37+AT37+AU37+AV37) | AY37: =IF(AZ37="","",ROUND(AZ37*(1+Assumptions!$B$10),0)) | AZ37: =IF(X37="","",ROUND(X37*(1+AW37),0)) | BA37: =IF(AZ37="","",ROUND(AZ37*(1+Assumptions!$B$11),0)) | BB37: =IF(AZ37="","",ROUND(AZ37*(1+AX37+Assumptions!$B$10),0)) | BC37: =IF(AZ37="","",ROUND(AZ37*(1+AX37),0)) | BD37: =IF(AZ37="","",ROUND(AZ37*(1+AX37+Assumptions!$B$11),0)) | BE37: =IF(AZ37="","",ROUND(AZ37*(1+AX37)*(1+AX37),0)) | BF37: Rules-based enrichment using launch-price anchor, cap-app realization, and 2026 segment conditions. | BG37: 2026-03-17 | BH37: DLD / Digital Dubai / CBUAE / Savills / Knight Frank-Moody’s / Reuters
A38: 37 | B38: Sidra Villas | C38: Emaar Properties | D38: Dubai Hills Estate | E38: Villas | F38: Gated Community | G38: Resale (5M+) | H38: 1600 | I38: 15 | J38: Completed | K38: 2016 | L38: 5.5-6.0 | M38: 6-8 | N38: 11.5-14.0 | O38: GEMS Wellington | P38: King's College Hospital | Q38: Dubai Hills Mall | R38: Al Khail E44 | S38: 15 | T38: 15 | U38: 20 | V38: 30 | W38: 2 | X38: 5000000 | Y38: 5000000 | Z38: 5.5 | AA38: 6 | AB38: 6 | AC38: 8 | AD38: 11.5 | AE38: 14 | AF38: 2016 | AH38: Villa | AI38: Prime | AJ38: TopTier | AK38: Prime resilient / selective | AL38: Better support from quality, branding, and scarcer prime stock; still entry-price sensitive. | AM38: 7 | AN38: 5.75 | AO38: 0.55 | AP38: 0.02 | AQ38: 0.015 | AR38: 0 | AS38: 0.03 | AT38: 0.005 | AU38: 0 | AV38: -0.005 | AW38: =IF(X38="","",(AM38/100*AO38)+AP38+AQ38+AR38) | AX38: =IF(X38="","",AS38+AT38+AU38+AV38) | AY38: =IF(AZ38="","",ROUND(AZ38*(1+Assumptions!$B$10),0)) | AZ38: =IF(X38="","",ROUND(X38*(1+AW38),0)) | BA38: =IF(AZ38="","",ROUND(AZ38*(1+Assumptions!$B$11),0)) | BB38: =IF(AZ38="","",ROUND(AZ38*(1+AX38+Assumptions!$B$10),0)) | BC38: =IF(AZ38="","",ROUND(AZ38*(1+AX38),0)) | BD38: =IF(AZ38="","",ROUND(AZ38*(1+AX38+Assumptions!$B$11),0)) | BE38: =IF(AZ38="","",ROUND(AZ38*(1+AX38)*(1+AX38),0)) | BF38: Rules-based enrichment using launch-price anchor, cap-app realization, and 2026 segment conditions. | BG38: 2026-03-17 | BH38: DLD / Digital Dubai / CBUAE / Savills / Knight Frank-Moody’s / Reuters
A39: 38 | B39: Maple Townhouses | C39: Emaar Properties | D39: Dubai Hills Estate | E39: Townhouses | F39: Gated Community | G39: Resale (3.5M+) | H39: 1500 | I39: 15 | J39: Completed | K39: 2016 | L39: 6.0-6.5 | M39: 6-8 | N39: 12.0-14.5 | O39: GEMS Wellington | P39: King's College Hospital | Q39: Dubai Hills Mall | R39: Al Khail E44 | S39: 15 | T39: 15 | U39: 20 | V39: 30 | W39: 2 | X39: 3500000 | Y39: 3500000 | Z39: 6 | AA39: 6.5 | AB39: 6 | AC39: 8 | AD39: 12 | AE39: 14.5 | AF39: 2016 | AH39: Townhouse | AI39: Prime | AJ39: TopTier | AK39: Prime resilient / selective | AL39: Better support from quality, branding, and scarcer prime stock; still entry-price sensitive. | AM39: 7 | AN39: 6.25 | AO39: 0.55 | AP39: 0.02 | AQ39: 0.015 | AR39: 0 | AS39: 0.03 | AT39: 0.005 | AU39: 0.0025 | AV39: -0.005 | AW39: =IF(X39="","",(AM39/100*AO39)+AP39+AQ39+AR39) | AX39: =IF(X39="","",AS39+AT39+AU39+AV39) | AY39: =IF(AZ39="","",ROUND(AZ39*(1+Assumptions!$B$10),0)) | AZ39: =IF(X39="","",ROUND(X39*(1+AW39),0)) | BA39: =IF(AZ39="","",ROUND(AZ39*(1+Assumptions!$B$11),0)) | BB39: =IF(AZ39="","",ROUND(AZ39*(1+AX39+Assumptions!$B$10),0)) | BC39: =IF(AZ39="","",ROUND(AZ39*(1+AX39),0)) | BD39: =IF(AZ39="","",ROUND(AZ39*(1+AX39+Assumptions!$B$11),0)) | BE39: =IF(AZ39="","",ROUND(AZ39*(1+AX39)*(1+AX39),0)) | BF39: Rules-based enrichment using launch-price anchor, cap-app realization, and 2026 segment conditions. | BG39: 2026-03-17 | BH39: DLD / Digital Dubai / CBUAE / Savills / Knight Frank-Moody’s / Reuters
A40: 39 | B40: Address Villas Hillcrest | C40: Emaar Properties | D40: Dubai Hills Estate | E40: Villas | F40: Luxury / Golf | G40: 8.0M | H40: 2200 | I40: 25 | J40: 80/20 | K40: 2023 | L40: 4.5-5.0 | M40: 8-10 | N40: 12.5-15.0 | O40: GEMS Wellington | P40: King's College Hospital | Q40: Dubai Hills Mall | R40: Al Khail E44 | S40: 15 | T40: 15 | U40: 20 | V40: 30 | W40: 2 | X40: 8000000 | Y40: 8000000 | Z40: 4.5 | AA40: 5 | AB40: 8 | AC40: 10 | AD40: 12.5 | AE40: 15 | AF40: 2023 | AH40: Villa | AI40: Prime | AJ40: TopTier | AK40: Prime resilient / selective | AL40: Better support from quality, branding, and scarcer prime stock; still entry-price sensitive. | AM40: 9 | AN40: 4.75 | AO40: 0.55 | AP40: 0.02 | AQ40: 0.015 | AR40: 0 | AS40: 0.03 | AT40: 0.005 | AU40: 0 | AV40: -0.005 | AW40: =IF(X40="","",(AM40/100*AO40)+AP40+AQ40+AR40) | AX40: =IF(X40="","",AS40+AT40+AU40+AV40) | AY40: =IF(AZ40="","",ROUND(AZ40*(1+Assumptions!$B$10),0)) | AZ40: =IF(X40="","",ROUND(X40*(1+AW40),0)) | BA40: =IF(AZ40="","",ROUND(AZ40*(1+Assumptions!$B$11),0)) | BB40: =IF(AZ40="","",ROUND(AZ40*(1+AX40+Assumptions!$B$10),0)) | BC40: =IF(AZ40="","",ROUND(AZ40*(1+AX40),0)) | BD40: =IF(AZ40="","",ROUND(AZ40*(1+AX40+Assumptions!$B$11),0)) | BE40: =IF(AZ40="","",ROUND(AZ40*(1+AX40)*(1+AX40),0)) | BF40: Rules-based enrichment using launch-price anchor, cap-app realization, and 2026 segment conditions. | BG40: 2026-03-17 | BH40: DLD / Digital Dubai / CBUAE / Savills / Knight Frank-Moody’s / Reuters
A41: 40 | B41: The Valley (Master Community) | C41: Emaar Properties | D41: Dubailand (Al Ain Rd) | E41: Mixed | F41: Suburban / Family | I41: 12-15 | J41: Varies | K41: Ongoing | L41: 6.5-7.5 | M41: 10-15 | N41: 16.5-22.5 | O41: The Aquila School | P41: Fakeeh University Hosp | Q41: Dubai Outlet Mall | R41: Al Ain Rd E66 | S41: 25 | T41: 35 | U41: 25 | V41: 35 | W41: 2 | Z41: 6.5 | AA41: 7.5 | AB41: 10 | AC41: 15 | AD41: 16.5 | AE41: 22.5 | AH41: Mixed/Other | AI41: MainstreamSelective | AJ41: TopTier | AK41: Balanced / selective | AL41: Market remains active but increasingly differentiated by developer, micro-location, livability, and pricing discipline. | AM41: 12.5 | AN41: 7 | AO41: 0.25 | AP41: 0 | AQ41: 0 | AR41: 0 | AS41: 0.01 | AT41: 0.005 | AU41: 0.0025 | AV41: -0.005 | AW41: =IF(X41="","",(AM41/100*AO41)+AP41+AQ41+AR41) | AX41: =IF(X41="","",AS41+AT41+AU41+AV41) | AY41: =IF(AZ41="","",ROUND(AZ41*(1+Assumptions!$B$10),0)) | AZ41: =IF(X41="","",ROUND(X41*(1+AW41),0)) | BA41: =IF(AZ41="","",ROUND(AZ41*(1+Assumptions!$B$11),0)) | BB41: =IF(AZ41="","",ROUND(AZ41*(1+AX41+Assumptions!$B$10),0)) | BC41: =IF(AZ41="","",ROUND(AZ41*(1+AX41),0)) | BD41: =IF(AZ41="","",ROUND(AZ41*(1+AX41+Assumptions!$B$11),0)) | BE41: =IF(AZ41="","",ROUND(AZ41*(1+AX41)*(1+AX41),0)) | BF41: Rules-based enrichment using launch-price anchor, cap-app realization, and 2026 segment conditions. | BG41: 2026-03-17 | BH41: DLD / Digital Dubai / CBUAE / Savills / Knight Frank-Moody’s / Reuters
A42: 41 | B42: Velora | C42: Emaar Properties | D42: The Valley (Phase 2) | E42: Townhouses | F42: Nature / Hills | G42: 2.48M | H42: 1100 | I42: 15 | J42: 80/20 | K42: Aug 2028 | L42: 6.5-7.0 | M42: 10-15 | N42: 16.5-22.0 | O42: The Aquila School | P42: Fakeeh University Hosp | Q42: Dubai Outlet Mall | R42: Al Ain Rd E66 | S42: 25 | T42: 35 | U42: 25 | V42: 35 | W42: 2 | X42: 2480000 | Y42: 2480000 | Z42: 6.5 | AA42: 7 | AB42: 10 | AC42: 15 | AD42: 16.5 | AE42: 22 | AF42: 2028 | AH42: Townhouse | AI42: MainstreamSelective | AJ42: TopTier | AK42: Family-villa resilient | AL42: Villa/townhouse demand remains relatively firmer, though growth should be slower than the post-2020 surge. | AM42: 12.5 | AN42: 6.75 | AO42: 0.25 | AP42: 0 | AQ42: 0.015 | AR42: 0 | AS42: 0.025 | AT42: 0.005 | AU42: 0.0025 | AV42: -0.005 | AW42: =IF(X42="","",(AM42/100*AO42)+AP42+AQ42+AR42) | AX42: =IF(X42="","",AS42+AT42+AU42+AV42) | AY42: =IF(AZ42="","",ROUND(AZ42*(1+Assumptions!$B$10),0)) | AZ42: =IF(X42="","",ROUND(X42*(1+AW42),0)) | BA42: =IF(AZ42="","",ROUND(AZ42*(1+Assumptions!$B$11),0)) | BB42: =IF(AZ42="","",ROUND(AZ42*(1+AX42+Assumptions!$B$10),0)) | BC42: =IF(AZ42="","",ROUND(AZ42*(1+AX42),0)) | BD42: =IF(AZ42="","",ROUND(AZ42*(1+AX42+Assumptions!$B$11),0)) | BE42: =IF(AZ42="","",ROUND(AZ42*(1+AX42)*(1+AX42),0)) | BF42: Rules-based enrichment using launch-price anchor, cap-app realization, and 2026 segment conditions. | BG42: 2026-03-17 | BH42: DLD / Digital Dubai / CBUAE / Savills / Knight Frank-Moody’s / Reuters
A43: 42 | B43: Venera | C43: Emaar Properties | D43: The Valley (Phase 2) | E43: Townhouses | F43: Nature / Hills | G43: 2.5M | H43: 1100 | I43: 15 | J43: 80/20 | K43: 2024 | L43: 6.5-7.0 | M43: 10-15 | N43: 16.5-22.0 | O43: The Aquila School | P43: Fakeeh University Hosp | Q43: Dubai Outlet Mall | R43: Al Ain Rd E66 | S43: 25 | T43: 35 | U43: 25 | V43: 35 | W43: 2 | X43: 2500000 | Y43: 2500000 | Z43: 6.5 | AA43: 7 | AB43: 10 | AC43: 15 | AD43: 16.5 | AE43: 22 | AF43: 2024 | AH43: Townhouse | AI43: MainstreamSelective | AJ43: TopTier | AK43: Family-villa resilient | AL43: Villa/townhouse demand remains relatively firmer, though growth should be slower than the post-2020 surge. | AM43: 12.5 | AN43: 6.75 | AO43: 0.55 | AP43: 0 | AQ43: 0.015 | AR43: 0 | AS43: 0.025 | AT43: 0.005 | AU43: 0.0025 | AV43: -0.005 | AW43: =IF(X43="","",(AM43/100*AO43)+AP43+AQ43+AR43) | AX43: =IF(X43="","",AS43+AT43+AU43+AV43) | AY43: =IF(AZ43="","",ROUND(AZ43*(1+Assumptions!$B$10),0)) | AZ43: =IF(X43="","",ROUND(X43*(1+AW43),0)) | BA43: =IF(AZ43="","",ROUND(AZ43*(1+Assumptions!$B$11),0)) | BB43: =IF(AZ43="","",ROUND(AZ43*(1+AX43+Assumptions!$B$10),0)) | BC43: =IF(AZ43="","",ROUND(AZ43*(1+AX43),0)) | BD43: =IF(AZ43="","",ROUND(AZ43*(1+AX43+Assumptions!$B$11),0)) | BE43: =IF(AZ43="","",ROUND(AZ43*(1+AX43)*(1+AX43),0)) | BF43: Rules-based enrichment using launch-price anchor, cap-app realization, and 2026 segment conditions. | BG43: 2026-03-17 | BH43: DLD / Digital Dubai / CBUAE / Savills / Knight Frank-Moody’s / Reuters
A44: 43 | B44: Rivera | C44: Emaar Properties | D44: The Valley | E44: Townhouses | F44: Water / Lagoon | G44: 2.6M | H44: 1150 | I44: 15 | J44: 80/20 | K44: 2024 | L44: 6.5-7.0 | M44: 10-15 | N44: 16.5-22.0 | O44: The Aquila School | P44: Fakeeh University Hosp | Q44: Dubai Outlet Mall | R44: Al Ain Rd E66 | S44: 25 | T44: 35 | U44: 25 | V44: 35 | W44: 2 | X44: 2600000 | Y44: 2600000 | Z44: 6.5 | AA44: 7 | AB44: 10 | AC44: 15 | AD44: 16.5 | AE44: 22 | AF44: 2024 | AH44: Townhouse | AI44: FamilyVilla | AJ44: TopTier | AK44: Family-villa resilient | AL44: Villa/townhouse demand remains relatively firmer, though growth should be slower than the post-2020 surge. | AM44: 12.5 | AN44: 6.75 | AO44: 0.55 | AP44: 0 | AQ44: 0.015 | AR44: 0 | AS44: 0.025 | AT44: 0.005 | AU44: 0.0025 | AV44: -0.005 | AW44: =IF(X44="","",(AM44/100*AO44)+AP44+AQ44+AR44) | AX44: =IF(X44="","",AS44+AT44+AU44+AV44) | AY44: =IF(AZ44="","",ROUND(AZ44*(1+Assumptions!$B$10),0)) | AZ44: =IF(X44="","",ROUND(X44*(1+AW44),0)) | BA44: =IF(AZ44="","",ROUND(AZ44*(1+Assumptions!$B$11),0)) | BB44: =IF(AZ44="","",ROUND(AZ44*(1+AX44+Assumptions!$B$10),0)) | BC44: =IF(AZ44="","",ROUND(AZ44*(1+AX44),0)) | BD44: =IF(AZ44="","",ROUND(AZ44*(1+AX44+Assumptions!$B$11),0)) | BE44: =IF(AZ44="","",ROUND(AZ44*(1+AX44)*(1+AX44),0)) | BF44: Rules-based enrichment using launch-price anchor, cap-app realization, and 2026 segment conditions. | BG44: 2026-03-17 | BH44: DLD / Digital Dubai / CBUAE / Savills / Knight Frank-Moody’s / Reuters
A45: 44 | B45: Avena | C45: Emaar Properties | D45: The Valley | E45: Villas | F45: Nature | G45: 3.2M | H45: 1200 | I45: 15 | J45: 80/20 | K45: 2024 | L45: 6.0-6.5 | M45: 10-15 | N45: 16.0-21.5 | O45: The Aquila School | P45: Fakeeh University Hosp | Q45: Dubai Outlet Mall | R45: Al Ain Rd E66 | S45: 25 | T45: 35 | U45: 25 | V45: 35 | W45: 2 | X45: 3200000 | Y45: 3200000 | Z45: 6 | AA45: 6.5 | AB45: 10 | AC45: 15 | AD45: 16 | AE45: 21.5 | AF45: 2024 | AH45: Villa | AI45: FamilyVilla | AJ45: TopTier | AK45: Family-villa resilient | AL45: Villa/townhouse demand remains relatively firmer, though growth should be slower than the post-2020 surge. | AM45: 12.5 | AN45: 6.25 | AO45: 0.55 | AP45: 0 | AQ45: 0.015 | AR45: 0 | AS45: 0.025 | AT45: 0.005 | AU45: 0.0025 | AV45: -0.005 | AW45: =IF(X45="","",(AM45/100*AO45)+AP45+AQ45+AR45) | AX45: =IF(X45="","",AS45+AT45+AU45+AV45) | AY45: =IF(AZ45="","",ROUND(AZ45*(1+Assumptions!$B$10),0)) | AZ45: =IF(X45="","",ROUND(X45*(1+AW45),0)) | BA45: =IF(AZ45="","",ROUND(AZ45*(1+Assumptions!$B$11),0)) | BB45: =IF(AZ45="","",ROUND(AZ45*(1+AX45+Assumptions!$B$10),0)) | BC45: =IF(AZ45="","",ROUND(AZ45*(1+AX45),0)) | BD45: =IF(AZ45="","",ROUND(AZ45*(1+AX45+Assumptions!$B$11),0)) | BE45: =IF(AZ45="","",ROUND(AZ45*(1+AX45)*(1+AX45),0)) | BF45: Rules-based enrichment using launch-price anchor, cap-app realization, and 2026 segment conditions. | BG45: 2026-03-17 | BH45: DLD / Digital Dubai / CBUAE / Savills / Knight Frank-Moody’s / Reuters
A46: 45 | B46: Ovelle | C46: Emaar Properties | D46: The Valley | E46: Townhouses | F46: Family | G46: 2.4M | H46: 1050 | I46: 15 | J46: 80/20 | K46: 2024 | L46: 6.5-7.0 | M46: 10-15 | N46: 16.5-22.0 | O46: The Aquila School | P46: Fakeeh University Hosp | Q46: Dubai Outlet Mall | R46: Al Ain Rd E66 | S46: 25 | T46: 35 | U46: 25 | V46: 35 | W46: 2 | X46: 2400000 | Y46: 2400000 | Z46: 6.5 | AA46: 7 | AB46: 10 | AC46: 15 | AD46: 16.5 | AE46: 22 | AF46: 2024 | AH46: Townhouse | AI46: FamilyVilla | AJ46: TopTier | AK46: Family-villa resilient | AL46: Villa/townhouse demand remains relatively firmer, though growth should be slower than the post-2020 surge. | AM46: 12.5 | AN46: 6.75 | AO46: 0.55 | AP46: 0 | AQ46: 0.015 | AR46: 0 | AS46: 0.025 | AT46: 0.005 | AU46: 0.0025 | AV46: -0.005 | AW46: =IF(X46="","",(AM46/100*AO46)+AP46+AQ46+AR46) | AX46: =IF(X46="","",AS46+AT46+AU46+AV46) | AY46: =IF(AZ46="","",ROUND(AZ46*(1+Assumptions!$B$10),0)) | AZ46: =IF(X46="","",ROUND(X46*(1+AW46),0)) | BA46: =IF(AZ46="","",ROUND(AZ46*(1+Assumptions!$B$11),0)) | BB46: =IF(AZ46="","",ROUND(AZ46*(1+AX46+Assumptions!$B$10),0)) | BC46: =IF(AZ46="","",ROUND(AZ46*(1+AX46),0)) | BD46: =IF(AZ46="","",ROUND(AZ46*(1+AX46+Assumptions!$B$11),0)) | BE46: =IF(AZ46="","",ROUND(AZ46*(1+AX46)*(1+AX46),0)) | BF46: Rules-based enrichment using launch-price anchor, cap-app realization, and 2026 segment conditions. | BG46: 2026-03-17 | BH46: DLD / Digital Dubai / CBUAE / Savills / Knight Frank-Moody’s / Reuters
A47: 46 | B47: Avelia | C47: Emaar Properties | D47: The Valley | E47: Townhouses | F47: Family | G47: 2.3M | H47: 1000 | I47: 15 | J47: 80/20 | K47: 2024 | L47: 6.5-7.0 | M47: 10-15 | N47: 16.5-22.0 | O47: The Aquila School | P47: Fakeeh University Hosp | Q47: Dubai Outlet Mall | R47: Al Ain Rd E66 | S47: 25 | T47: 35 | U47: 25 | V47: 35 | W47: 2 | X47: 2300000 | Y47: 2300000 | Z47: 6.5 | AA47: 7 | AB47: 10 | AC47: 15 | AD47: 16.5 | AE47: 22 | AF47: 2024 | AH47: Townhouse | AI47: FamilyVilla | AJ47: TopTier | AK47: Family-villa resilient | AL47: Villa/townhouse demand remains relatively firmer, though growth should be slower than the post-2020 surge. | AM47: 12.5 | AN47: 6.75 | AO47: 0.55 | AP47: 0 | AQ47: 0.015 | AR47: 0 | AS47: 0.025 | AT47: 0.005 | AU47: 0.0025 | AV47: -0.005 | AW47: =IF(X47="","",(AM47/100*AO47)+AP47+AQ47+AR47) | AX47: =IF(X47="","",AS47+AT47+AU47+AV47) | AY47: =IF(AZ47="","",ROUND(AZ47*(1+Assumptions!$B$10),0)) | AZ47: =IF(X47="","",ROUND(X47*(1+AW47),0)) | BA47: =IF(AZ47="","",ROUND(AZ47*(1+Assumptions!$B$11),0)) | BB47: =IF(AZ47="","",ROUND(AZ47*(1+AX47+Assumptions!$B$10),0)) | BC47: =IF(AZ47="","",ROUND(AZ47*(1+AX47),0)) | BD47: =IF(AZ47="","",ROUND(AZ47*(1+AX47+Assumptions!$B$11),0)) | BE47: =IF(AZ47="","",ROUND(AZ47*(1+AX47)*(1+AX47),0)) | BF47: Rules-based enrichment using launch-price anchor, cap-app realization, and 2026 segment conditions. | BG47: 2026-03-17 | BH47: DLD / Digital Dubai / CBUAE / Savills / Knight Frank-Moody’s / Reuters
A48: 47 | B48: Elora | C48: Emaar Properties | D48: The Valley | E48: Townhouses | F48: Family | G48: 2.1M | H48: 1000 | I48: 15 | J48: 80/20 | K48: 2023 | L48: 7.0-7.5 | M48: 10-12 | N48: 17.0-19.5 | O48: The Aquila School | P48: Fakeeh University Hosp | Q48: Dubai Outlet Mall | R48: Al Ain Rd E66 | S48: 25 | T48: 35 | U48: 25 | V48: 35 | W48: 2 | X48: 2100000 | Y48: 2100000 | Z48: 7 | AA48: 7.5 | AB48: 10 | AC48: 12 | AD48: 17 | AE48: 19.5 | AF48: 2023 | AH48: Townhouse | AI48: FamilyVilla | AJ48: TopTier | AK48: Family-villa resilient | AL48: Villa/townhouse demand remains relatively firmer, though growth should be slower than the post-2020 surge. | AM48: 11 | AN48: 7.25 | AO48: 0.55 | AP48: 0 | AQ48: 0.015 | AR48: 0 | AS48: 0.025 | AT48: 0.005 | AU48: 0.0025 | AV48: -0.005 | AW48: =IF(X48="","",(AM48/100*AO48)+AP48+AQ48+AR48) | AX48: =IF(X48="","",AS48+AT48+AU48+AV48) | AY48: =IF(AZ48="","",ROUND(AZ48*(1+Assumptions!$B$10),0)) | AZ48: =IF(X48="","",ROUND(X48*(1+AW48),0)) | BA48: =IF(AZ48="","",ROUND(AZ48*(1+Assumptions!$B$11),0)) | BB48: =IF(AZ48="","",ROUND(AZ48*(1+AX48+Assumptions!$B$10),0)) | BC48: =IF(AZ48="","",ROUND(AZ48*(1+AX48),0)) | BD48: =IF(AZ48="","",ROUND(AZ48*(1+AX48+Assumptions!$B$11),0)) | BE48: =IF(AZ48="","",ROUND(AZ48*(1+AX48)*(1+AX48),0)) | BF48: Rules-based enrichment using launch-price anchor, cap-app realization, and 2026 segment conditions. | BG48: 2026-03-17 | BH48: DLD / Digital Dubai / CBUAE / Savills / Knight Frank-Moody’s / Reuters
A49: 48 | B49: Rivana | C49: Emaar Properties | D49: The Valley | E49: Villas | F49: Twin Villas | G49: 2.8M | H49: 1100 | I49: 15 | J49: 80/20 | K49: 2023 | L49: 6.5-7.0 | M49: 10-12 | N49: 16.5-19.0 | O49: The Aquila School | P49: Fakeeh University Hosp | Q49: Dubai Outlet Mall | R49: Al Ain Rd E66 | S49: 25 | T49: 35 | U49: 25 | V49: 35 | W49: 2 | X49: 2800000 | Y49: 2800000 | Z49: 6.5 | AA49: 7 | AB49: 10 | AC49: 12 | AD49: 16.5 | AE49: 19 | AF49: 2023 | AH49: Villa | AI49: FamilyVilla | AJ49: TopTier | AK49: Family-villa resilient | AL49: Villa/townhouse demand remains relatively firmer, though growth should be slower than the post-2020 surge. | AM49: 11 | AN49: 6.75 | AO49: 0.55 | AP49: 0 | AQ49: 0.015 | AR49: 0 | AS49: 0.025 | AT49: 0.005 | AU49: 0.0025 | AV49: -0.005 | AW49: =IF(X49="","",(AM49/100*AO49)+AP49+AQ49+AR49) | AX49: =IF(X49="","",AS49+AT49+AU49+AV49) | AY49: =IF(AZ49="","",ROUND(AZ49*(1+Assumptions!$B$10),0)) | AZ49: =IF(X49="","",ROUND(X49*(1+AW49),0)) | BA49: =IF(AZ49="","",ROUND(AZ49*(1+Assumptions!$B$11),0)) | BB49: =IF(AZ49="","",ROUND(AZ49*(1+AX49+Assumptions!$B$10),0)) | BC49: =IF(AZ49="","",ROUND(AZ49*(1+AX49),0)) | BD49: =IF(AZ49="","",ROUND(AZ49*(1+AX49+Assumptions!$B$11),0)) | BE49: =IF(AZ49="","",ROUND(AZ49*(1+AX49)*(1+AX49),0)) | BF49: Rules-based enrichment using launch-price anchor, cap-app realization, and 2026 segment conditions. | BG49: 2026-03-17 | BH49: DLD / Digital Dubai / CBUAE / Savills / Knight Frank-Moody’s / Reuters
A50: 49 | B50: Farm Gardens | C50: Emaar Properties | D50: The Valley | E50: Villas (Estate) | F50: Farm / Luxury | G50: 5.5M | H50: 1300 | I50: 15 | J50: 80/20 | K50: 2023 | L50: 5.5-6.0 | M50: 10-12 | N50: 15.5-18.0 | O50: The Aquila School | P50: Fakeeh University Hosp | Q50: Dubai Outlet Mall | R50: Al Ain Rd E66 | S50: 25 | T50: 35 | U50: 25 | V50: 35 | W50: 2 | X50: 5500000 | Y50: 5500000 | Z50: 5.5 | AA50: 6 | AB50: 10 | AC50: 12 | AD50: 15.5 | AE50: 18 | AF50: 2023 | AH50: Villa | AI50: FamilyVilla | AJ50: TopTier | AK50: Family-villa resilient | AL50: Villa/townhouse demand remains relatively firmer, though growth should be slower than the post-2020 surge. | AM50: 11 | AN50: 5.75 | AO50: 0.55 | AP50: 0 | AQ50: 0.015 | AR50: 0 | AS50: 0.025 | AT50: 0.005 | AU50: 0 | AV50: -0.005 | AW50: =IF(X50="","",(AM50/100*AO50)+AP50+AQ50+AR50) | AX50: =IF(X50="","",AS50+AT50+AU50+AV50) | AY50: =IF(AZ50="","",ROUND(AZ50*(1+Assumptions!$B$10),0)) | AZ50: =IF(X50="","",ROUND(X50*(1+AW50),0)) | BA50: =IF(AZ50="","",ROUND(AZ50*(1+Assumptions!$B$11),0)) | BB50: =IF(AZ50="","",ROUND(AZ50*(1+AX50+Assumptions!$B$10),0)) | BC50: =IF(AZ50="","",ROUND(AZ50*(1+AX50),0)) | BD50: =IF(AZ50="","",ROUND(AZ50*(1+AX50+Assumptions!$B$11),0)) | BE50: =IF(AZ50="","",ROUND(AZ50*(1+AX50)*(1+AX50),0)) | BF50: Rules-based enrichment using launch-price anchor, cap-app realization, and 2026 segment conditions. | BG50: 2026-03-17 | BH50: DLD / Digital Dubai / CBUAE / Savills / Knight Frank-Moody’s / Reuters
A51: 50 | B51: The Oasis (Master Community) | C51: Emaar Properties | D51: Near DIP | E51: Villas & Mansions | F51: Blue Lagoons / Luxury | I51: TBA | J51: Varies | K51: 2024 | L51: 4.5-5.5 | M51: 12-18 | N51: 16.5-23.5 | O51: Victory Heights | P51: NMC Royal DIP | Q51: First Avenue Mall | R51: Yalayis St / E611 | S51: 25 | T51: 20 | U51: 30 | V51: 18 | W51: 2 | Z51: 4.5 | AA51: 5.5 | AB51: 12 | AC51: 18 | AD51: 16.5 | AE51: 23.5 | AF51: 2024 | AH51: Villa | AI51: MainstreamSelective | AJ51: TopTier | AK51: Family-villa resilient | AL51: Villa/townhouse demand remains relatively firmer, though growth should be slower than the post-2020 surge. | AM51: 15 | AN51: 5 | AO51: 0.55 | AP51: 0 | AQ51: 0.015 | AR51: 0 | AS51: 0.025 | AT51: 0.005 | AU51: 0 | AV51: -0.005 | AW51: =IF(X51="","",(AM51/100*AO51)+AP51+AQ51+AR51) | AX51: =IF(X51="","",AS51+AT51+AU51+AV51) | AY51: =IF(AZ51="","",ROUND(AZ51*(1+Assumptions!$B$10),0)) | AZ51: =IF(X51="","",ROUND(X51*(1+AW51),0)) | BA51: =IF(AZ51="","",ROUND(AZ51*(1+Assumptions!$B$11),0)) | BB51: =IF(AZ51="","",ROUND(AZ51*(1+AX51+Assumptions!$B$10),0)) | BC51: =IF(AZ51="","",ROUND(AZ51*(1+AX51),0)) | BD51: =IF(AZ51="","",ROUND(AZ51*(1+AX51+Assumptions!$B$11),0)) | BE51: =IF(AZ51="","",ROUND(AZ51*(1+AX51)*(1+AX51),0)) | BF51: Rules-based enrichment using launch-price anchor, cap-app realization, and 2026 segment conditions. | BG51: 2026-03-17 | BH51: DLD / Digital Dubai / CBUAE / Savills / Knight Frank-Moody’s / Reuters
A52: 51 | B52: Palmiera | C52: Emaar Properties | D52: The Oasis | E52: Villas | F52: Luxury / Water | G52: 8.5M | H52: 1800 | I52: 20 | J52: 80/20 | K52: 2024 | L52: 4.5-5.0 | M52: 12-18 | N52: 16.5-23.0 | O52: Victory Heights | P52: NMC Royal DIP | Q52: First Avenue Mall | R52: Yalayis St / E611 | S52: 25 | T52: 20 | U52: 30 | V52: 18 | W52: 2 | X52: 8500000 | Y52: 8500000 | Z52: 4.5 | AA52: 5 | AB52: 12 | AC52: 18 | AD52: 16.5 | AE52: 23 | AF52: 2024 | AH52: Villa | AI52: FamilyVilla | AJ52: TopTier | AK52: Family-villa resilient | AL52: Villa/townhouse demand remains relatively firmer, though growth should be slower than the post-2020 surge. | AM52: 15 | AN52: 4.75 | AO52: 0.55 | AP52: 0 | AQ52: 0.015 | AR52: 0 | AS52: 0.025 | AT52: 0.005 | AU52: 0 | AV52: -0.005 | AW52: =IF(X52="","",(AM52/100*AO52)+AP52+AQ52+AR52) | AX52: =IF(X52="","",AS52+AT52+AU52+AV52) | AY52: =IF(AZ52="","",ROUND(AZ52*(1+Assumptions!$B$10),0)) | AZ52: =IF(X52="","",ROUND(X52*(1+AW52),0)) | BA52: =IF(AZ52="","",ROUND(AZ52*(1+Assumptions!$B$11),0)) | BB52: =IF(AZ52="","",ROUND(AZ52*(1+AX52+Assumptions!$B$10),0)) | BC52: =IF(AZ52="","",ROUND(AZ52*(1+AX52),0)) | BD52: =IF(AZ52="","",ROUND(AZ52*(1+AX52+Assumptions!$B$11),0)) | BE52: =IF(AZ52="","",ROUND(AZ52*(1+AX52)*(1+AX52),0)) | BF52: Rules-based enrichment using launch-price anchor, cap-app realization, and 2026 segment conditions. | BG52: 2026-03-17 | BH52: DLD / Digital Dubai / CBUAE / Savills / Knight Frank-Moody’s / Reuters
A53: 52 | B53: Marèva 1 | C53: Emaar Properties | D53: The Oasis | E53: Villas | F53: Luxury / Water | G53: 9.0M | H53: 1900 | I53: 20 | J53: 80/20 | K53: 2024 | L53: 4.5-5.0 | M53: 12-18 | N53: 16.5-23.0 | O53: Victory Heights | P53: NMC Royal DIP | Q53: First Avenue Mall | R53: Yalayis St / E611 | S53: 25 | T53: 20 | U53: 30 | V53: 18 | W53: 2 | X53: 9000000 | Y53: 9000000 | Z53: 4.5 | AA53: 5 | AB53: 12 | AC53: 18 | AD53: 16.5 | AE53: 23 | AF53: 2024 | AH53: Villa | AI53: FamilyVilla | AJ53: TopTier | AK53: Family-villa resilient | AL53: Villa/townhouse demand remains relatively firmer, though growth should be slower than the post-2020 surge. | AM53: 15 | AN53: 4.75 | AO53: 0.55 | AP53: 0 | AQ53: 0.015 | AR53: 0 | AS53: 0.025 | AT53: 0.005 | AU53: 0 | AV53: -0.005 | AW53: =IF(X53="","",(AM53/100*AO53)+AP53+AQ53+AR53) | AX53: =IF(X53="","",AS53+AT53+AU53+AV53) | AY53: =IF(AZ53="","",ROUND(AZ53*(1+Assumptions!$B$10),0)) | AZ53: =IF(X53="","",ROUND(X53*(1+AW53),0)) | BA53: =IF(AZ53="","",ROUND(AZ53*(1+Assumptions!$B$11),0)) | BB53: =IF(AZ53="","",ROUND(AZ53*(1+AX53+Assumptions!$B$10),0)) | BC53: =IF(AZ53="","",ROUND(AZ53*(1+AX53),0)) | BD53: =IF(AZ53="","",ROUND(AZ53*(1+AX53+Assumptions!$B$11),0)) | BE53: =IF(AZ53="","",ROUND(AZ53*(1+AX53)*(1+AX53),0)) | BF53: Rules-based enrichment using launch-price anchor, cap-app realization, and 2026 segment conditions. | BG53: 2026-03-17 | BH53: DLD / Digital Dubai / CBUAE / Savills / Knight Frank-Moody’s / Reuters
A54: 53 | B54: Marèva 2 | C54: Emaar Properties | D54: The Oasis | E54: Villas | F54: Luxury / Water | G54: 13.47M | H54: 2000 | I54: 20 | J54: 80/20 | K54: 2024 | L54: 4.0-4.5 | M54: 12-18 | N54: 16.0-22.5 | O54: Victory Heights | P54: NMC Royal DIP | Q54: First Avenue Mall | R54: Yalayis St / E611 | S54: 25 | T54: 20 | U54: 30 | V54: 18 | W54: 2 | X54: 13470000 | Y54: 13470000 | Z54: 4 | AA54: 4.5 | AB54: 12 | AC54: 18 | AD54: 16 | AE54: 22.5 | AF54: 2024 | AH54: Villa | AI54: FamilyVilla | AJ54: TopTier | AK54: Family-villa resilient | AL54: Villa/townhouse demand remains relatively firmer, though growth should be slower than the post-2020 surge. | AM54: 15 | AN54: 4.25 | AO54: 0.55 | AP54: 0 | AQ54: 0.015 | AR54: 0 | AS54: 0.025 | AT54: 0.005 | AU54: 0 | AV54: -0.005 | AW54: =IF(X54="","",(AM54/100*AO54)+AP54+AQ54+AR54) | AX54: =IF(X54="","",AS54+AT54+AU54+AV54) | AY54: =IF(AZ54="","",ROUND(AZ54*(1+Assumptions!$B$10),0)) | AZ54: =IF(X54="","",ROUND(X54*(1+AW54),0)) | BA54: =IF(AZ54="","",ROUND(AZ54*(1+Assumptions!$B$11),0)) | BB54: =IF(AZ54="","",ROUND(AZ54*(1+AX54+Assumptions!$B$10),0)) | BC54: =IF(AZ54="","",ROUND(AZ54*(1+AX54),0)) | BD54: =IF(AZ54="","",ROUND(AZ54*(1+AX54+Assumptions!$B$11),0)) | BE54: =IF(AZ54="","",ROUND(AZ54*(1+AX54)*(1+AX54),0)) | BF54: Rules-based enrichment using launch-price anchor, cap-app realization, and 2026 segment conditions. | BG54: 2026-03-17 | BH54: DLD / Digital Dubai / CBUAE / Savills / Knight Frank-Moody’s / Reuters
A55: 54 | B55: Emaar South (Master Community) | C55: Emaar Properties | D55: Dubai South (Airport) | E55: Mixed | F55: Golf / Airport | I55: 10-12 | J55: Varies | K55: Ongoing | L55: 7.0-8.5 | M55: 8-12 | N55: 15.0-20.5 | O55: Greenfield Intl | P55: NMC Royal DIP | Q55: Urban Centre (Local) | R55: Expo Rd / E611 | S55: 40 | T55: 25 | U55: 45 | V55: 7 | W55: 2 | Z55: 7 | AA55: 8.5 | AB55: 8 | AC55: 12 | AD55: 15 | AE55: 20.5 | AH55: Mixed/Other | AI55: MainstreamSelective | AJ55: TopTier | AK55: Balanced / selective | AL55: Market remains active but increasingly differentiated by developer, micro-location, livability, and pricing discipline. | AM55: 10 | AN55: 7.75 | AO55: 0.25 | AP55: 0 | AQ55: 0 | AR55: 0 | AS55: 0.01 | AT55: 0.005 | AU55: 0.0025 | AV55: -0.005 | AW55: =IF(X55="","",(AM55/100*AO55)+AP55+AQ55+AR55) | AX55: =IF(X55="","",AS55+AT55+AU55+AV55) | AY55: =IF(AZ55="","",ROUND(AZ55*(1+Assumptions!$B$10),0)) | AZ55: =IF(X55="","",ROUND(X55*(1+AW55),0)) | BA55: =IF(AZ55="","",ROUND(AZ55*(1+Assumptions!$B$11),0)) | BB55: =IF(AZ55="","",ROUND(AZ55*(1+AX55+Assumptions!$B$10),0)) | BC55: =IF(AZ55="","",ROUND(AZ55*(1+AX55),0)) | BD55: =IF(AZ55="","",ROUND(AZ55*(1+AX55+Assumptions!$B$11),0)) | BE55: =IF(AZ55="","",ROUND(AZ55*(1+AX55)*(1+AX55),0)) | BF55: Rules-based enrichment using launch-price anchor, cap-app realization, and 2026 segment conditions. | BG55: 2026-03-17 | BH55: DLD / Digital Dubai / CBUAE / Savills / Knight Frank-Moody’s / Reuters
A56: 55 | B56: Golf Hills 2 | C56: Emaar Properties | D56: Emaar South | E56: Apartments | F56: Golf View | G56: 1.1M | H56: 1200 | I56: 15 | J56: 80/20 | K56: 2024 | L56: 7.0-7.5 | M56: 8-12 | N56: 15.0-19.5 | O56: Greenfield Intl | P56: NMC Royal DIP | Q56: Urban Centre (Local) | R56: Expo Rd / E611 | S56: 40 | T56: 25 | U56: 45 | V56: 7 | W56: 2 | X56: 1100000 | Y56: 1100000 | Z56: 7 | AA56: 7.5 | AB56: 8 | AC56: 12 | AD56: 15 | AE56: 19.5 | AF56: 2024 | AH56: Apartment | AI56: MainstreamSelective | AJ56: TopTier | AK56: Balanced / selective | AL56: Market remains active but increasingly differentiated by developer, micro-location, livability, and pricing discipline. | AM56: 10 | AN56: 7.25 | AO56: 0.55 | AP56: 0 | AQ56: 0 | AR56: 0 | AS56: 0.01 | AT56: 0.005 | AU56: 0.0025 | AV56: -0.005 | AW56: =IF(X56="","",(AM56/100*AO56)+AP56+AQ56+AR56) | AX56: =IF(X56="","",AS56+AT56+AU56+AV56) | AY56: =IF(AZ56="","",ROUND(AZ56*(1+Assumptions!$B$10),0)) | AZ56: =IF(X56="","",ROUND(X56*(1+AW56),0)) | BA56: =IF(AZ56="","",ROUND(AZ56*(1+Assumptions!$B$11),0)) | BB56: =IF(AZ56="","",ROUND(AZ56*(1+AX56+Assumptions!$B$10),0)) | BC56: =IF(AZ56="","",ROUND(AZ56*(1+AX56),0)) | BD56: =IF(AZ56="","",ROUND(AZ56*(1+AX56+Assumptions!$B$11),0)) | BE56: =IF(AZ56="","",ROUND(AZ56*(1+AX56)*(1+AX56),0)) | BF56: Rules-based enrichment using launch-price anchor, cap-app realization, and 2026 segment conditions. | BG56: 2026-03-17 | BH56: DLD / Digital Dubai / CBUAE / Savills / Knight Frank-Moody’s / Reuters
A57: 56 | B57: Vista Ridge | C57: Emaar Properties | D57: Emaar South | E57: Townhouses | F57: Golf View | G57: 1.8M | H57: 1100 | I57: 15 | J57: 80/20 | K57: 2024 | L57: 6.5-7.0 | M57: 8-12 | N57: 14.5-19.0 | O57: Greenfield Intl | P57: NMC Royal DIP | Q57: Urban Centre (Local) | R57: Expo Rd / E611 | S57: 40 | T57: 25 | U57: 45 | V57: 7 | W57: 2 | X57: 1800000 | Y57: 1800000 | Z57: 6.5 | AA57: 7 | AB57: 8 | AC57: 12 | AD57: 14.5 | AE57: 19 | AF57: 2024 | AH57: Townhouse | AI57: MainstreamSelective | AJ57: TopTier | AK57: Family-villa resilient | AL57: Villa/townhouse demand remains relatively firmer, though growth should be slower than the post-2020 surge. | AM57: 10 | AN57: 6.75 | AO57: 0.55 | AP57: 0 | AQ57: 0.015 | AR57: 0 | AS57: 0.025 | AT57: 0.005 | AU57: 0.0025 | AV57: -0.005 | AW57: =IF(X57="","",(AM57/100*AO57)+AP57+AQ57+AR57) | AX57: =IF(X57="","",AS57+AT57+AU57+AV57) | AY57: =IF(AZ57="","",ROUND(AZ57*(1+Assumptions!$B$10),0)) | AZ57: =IF(X57="","",ROUND(X57*(1+AW57),0)) | BA57: =IF(AZ57="","",ROUND(AZ57*(1+Assumptions!$B$11),0)) | BB57: =IF(AZ57="","",ROUND(AZ57*(1+AX57+Assumptions!$B$10),0)) | BC57: =IF(AZ57="","",ROUND(AZ57*(1+AX57),0)) | BD57: =IF(AZ57="","",ROUND(AZ57*(1+AX57+Assumptions!$B$11),0)) | BE57: =IF(AZ57="","",ROUND(AZ57*(1+AX57)*(1+AX57),0)) | BF57: Rules-based enrichment using launch-price anchor, cap-app realization, and 2026 segment conditions. | BG57: 2026-03-17 | BH57: DLD / Digital Dubai / CBUAE / Savills / Knight Frank-Moody’s / Reuters
A58: 57 | B58: Grove Ridge | C58: Emaar Properties | D58: Emaar South | E58: Townhouses | F58: Family | G58: 1.7M | H58: 1050 | I58: 15 | J58: 80/20 | K58: 2024 | L58: 6.5-7.0 | M58: 8-12 | N58: 14.5-19.0 | O58: Greenfield Intl | P58: NMC Royal DIP | Q58: Urban Centre (Local) | R58: Expo Rd / E611 | S58: 40 | T58: 25 | U58: 45 | V58: 7 | W58: 2 | X58: 1700000 | Y58: 1700000 | Z58: 6.5 | AA58: 7 | AB58: 8 | AC58: 12 | AD58: 14.5 | AE58: 19 | AF58: 2024 | AH58: Townhouse | AI58: MainstreamSelective | AJ58: TopTier | AK58: Family-villa resilient | AL58: Villa/townhouse demand remains relatively firmer, though growth should be slower than the post-2020 surge. | AM58: 10 | AN58: 6.75 | AO58: 0.55 | AP58: 0 | AQ58: 0.015 | AR58: 0 | AS58: 0.025 | AT58: 0.005 | AU58: 0.0025 | AV58: -0.005 | AW58: =IF(X58="","",(AM58/100*AO58)+AP58+AQ58+AR58) | AX58: =IF(X58="","",AS58+AT58+AU58+AV58) | AY58: =IF(AZ58="","",ROUND(AZ58*(1+Assumptions!$B$10),0)) | AZ58: =IF(X58="","",ROUND(X58*(1+AW58),0)) | BA58: =IF(AZ58="","",ROUND(AZ58*(1+Assumptions!$B$11),0)) | BB58: =IF(AZ58="","",ROUND(AZ58*(1+AX58+Assumptions!$B$10),0)) | BC58: =IF(AZ58="","",ROUND(AZ58*(1+AX58),0)) | BD58: =IF(AZ58="","",ROUND(AZ58*(1+AX58+Assumptions!$B$11),0)) | BE58: =IF(AZ58="","",ROUND(AZ58*(1+AX58)*(1+AX58),0)) | BF58: Rules-based enrichment using launch-price anchor, cap-app realization, and 2026 segment conditions. | BG58: 2026-03-17 | BH58: DLD / Digital Dubai / CBUAE / Savills / Knight Frank-Moody’s / Reuters
A59: 58 | B59: Expo Golf Villas | C59: Emaar Properties | D59: Emaar South | E59: Villas | F59: Golf | G59: Resale (1.5M+) | H59: 1000 | I59: 15 | J59: Completed | K59: 2019 | L59: 7.0-7.5 | M59: 6-8 | N59: 13.0-15.5 | O59: Greenfield Intl | P59: NMC Royal DIP | Q59: Urban Centre (Local) | R59: Expo Rd / E611 | S59: 40 | T59: 25 | U59: 45 | V59: 7 | W59: 2 | X59: 1500000 | Y59: 1500000 | Z59: 7 | AA59: 7.5 | AB59: 6 | AC59: 8 | AD59: 13 | AE59: 15.5 | AF59: 2019 | AH59: Villa | AI59: MainstreamSelective | AJ59: TopTier | AK59: Family-villa resilient | AL59: Villa/townhouse demand remains relatively firmer, though growth should be slower than the post-2020 surge. | AM59: 7 | AN59: 7.25 | AO59: 0.55 | AP59: 0 | AQ59: 0.015 | AR59: 0 | AS59: 0.025 | AT59: 0.005 | AU59: 0.0025 | AV59: -0.005 | AW59: =IF(X59="","",(AM59/100*AO59)+AP59+AQ59+AR59) | AX59: =IF(X59="","",AS59+AT59+AU59+AV59) | AY59: =IF(AZ59="","",ROUND(AZ59*(1+Assumptions!$B$10),0)) | AZ59: =IF(X59="","",ROUND(X59*(1+AW59),0)) | BA59: =IF(AZ59="","",ROUND(AZ59*(1+Assumptions!$B$11),0)) | BB59: =IF(AZ59="","",ROUND(AZ59*(1+AX59+Assumptions!$B$10),0)) | BC59: =IF(AZ59="","",ROUND(AZ59*(1+AX59),0)) | BD59: =IF(AZ59="","",ROUND(AZ59*(1+AX59+Assumptions!$B$11),0)) | BE59: =IF(AZ59="","",ROUND(AZ59*(1+AX59)*(1+AX59),0)) | BF59: Rules-based enrichment using launch-price anchor, cap-app realization, and 2026 segment conditions. | BG59: 2026-03-17 | BH59: DLD / Digital Dubai / CBUAE / Savills / Knight Frank-Moody’s / Reuters
A60: 59 | B60: Urbana | C60: Emaar Properties | D60: Emaar South | E60: Townhouses | F60: Gated | G60: Resale (1.2M+) | H60: 950 | I60: 15 | J60: Completed | K60: 2018 | L60: 7.5-8.0 | M60: 6-8 | N60: 13.5-16.0 | O60: Greenfield Intl | P60: NMC Royal DIP | Q60: Urban Centre (Local) | R60: Expo Rd / E611 | S60: 40 | T60: 25 | U60: 45 | V60: 7 | W60: 2 | X60: 1200000 | Y60: 1200000 | Z60: 7.5 | AA60: 8 | AB60: 6 | AC60: 8 | AD60: 13.5 | AE60: 16 | AF60: 2018 | AH60: Townhouse | AI60: MainstreamSelective | AJ60: TopTier | AK60: Family-villa resilient | AL60: Villa/townhouse demand remains relatively firmer, though growth should be slower than the post-2020 surge. | AM60: 7 | AN60: 7.75 | AO60: 0.55 | AP60: 0 | AQ60: 0.015 | AR60: 0 | AS60: 0.025 | AT60: 0.005 | AU60: 0.0025 | AV60: -0.005 | AW60: =IF(X60="","",(AM60/100*AO60)+AP60+AQ60+AR60) | AX60: =IF(X60="","",AS60+AT60+AU60+AV60) | AY60: =IF(AZ60="","",ROUND(AZ60*(1+Assumptions!$B$10),0)) | AZ60: =IF(X60="","",ROUND(X60*(1+AW60),0)) | BA60: =IF(AZ60="","",ROUND(AZ60*(1+Assumptions!$B$11),0)) | BB60: =IF(AZ60="","",ROUND(AZ60*(1+AX60+Assumptions!$B$10),0)) | BC60: =IF(AZ60="","",ROUND(AZ60*(1+AX60),0)) | BD60: =IF(AZ60="","",ROUND(AZ60*(1+AX60+Assumptions!$B$11),0)) | BE60: =IF(AZ60="","",ROUND(AZ60*(1+AX60)*(1+AX60),0)) | BF60: Rules-based enrichment using launch-price anchor, cap-app realization, and 2026 segment conditions. | BG60: 2026-03-17 | BH60: DLD / Digital Dubai / CBUAE / Savills / Knight Frank-Moody’s / Reuters
A61: 60 | B61: Expo Living (Master Community) | C61: Emaar Properties | D61: Dubai South | E61: Apartments | F61: Expo City Proximity | I61: 15 | J61: Varies | K61: 2024 | L61: 7.0-8.0 | M61: 10-12 | N61: 17.0-20.0 | O61: Dove Green | P61: NMC Royal DIP | Q61: Expo City Mall | R61: Expo Rd | S61: 35 | T61: 20 | U61: 40 | V61: 10 | W61: 2 | Z61: 7 | AA61: 8 | AB61: 10 | AC61: 12 | AD61: 17 | AE61: 20 | AF61: 2024 | AH61: Apartment | AI61: SupplySensitiveApartment | AJ61: TopTier | AK61: Supply-sensitive / selective | AL61: Higher delivery risk in more price-sensitive apartment clusters; building selection and exit liquidity matter. | AM61: 11 | AN61: 7.5 | AO61: 0.55 | AP61: 0 | AQ61: 0 | AR61: -0.01 | AS61: -0.01 | AT61: 0.005 | AU61: 0.0025 | AV61: -0.005 | AW61: =IF(X61="","",(AM61/100*AO61)+AP61+AQ61+AR61) | AX61: =IF(X61="","",AS61+AT61+AU61+AV61) | AY61: =IF(AZ61="","",ROUND(AZ61*(1+Assumptions!$B$10),0)) | AZ61: =IF(X61="","",ROUND(X61*(1+AW61),0)) | BA61: =IF(AZ61="","",ROUND(AZ61*(1+Assumptions!$B$11),0)) | BB61: =IF(AZ61="","",ROUND(AZ61*(1+AX61+Assumptions!$B$10),0)) | BC61: =IF(AZ61="","",ROUND(AZ61*(1+AX61),0)) | BD61: =IF(AZ61="","",ROUND(AZ61*(1+AX61+Assumptions!$B$11),0)) | BE61: =IF(AZ61="","",ROUND(AZ61*(1+AX61)*(1+AX61),0)) | BF61: Rules-based enrichment using launch-price anchor, cap-app realization, and 2026 segment conditions. | BG61: 2026-03-17 | BH61: DLD / Digital Dubai / CBUAE / Savills / Knight Frank-Moody’s / Reuters
A62: 61 | B62: Terra Gardens | C62: Emaar Properties | D62: Expo Living | E62: Apartments | F62: Green / Modern | G62: 1.3M | H62: 1400 | I62: 15 | J62: 80/20 | K62: 2024 | L62: 7.0-7.5 | M62: 10-12 | N62: 17.0-19.5 | O62: Dove Green | P62: NMC Royal DIP | Q62: Expo City Mall | R62: Expo Rd | S62: 35 | T62: 20 | U62: 40 | V62: 10 | W62: 2 | X62: 1300000 | Y62: 1300000 | Z62: 7 | AA62: 7.5 | AB62: 10 | AC62: 12 | AD62: 17 | AE62: 19.5 | AF62: 2024 | AH62: Apartment | AI62: MainstreamSelective | AJ62: TopTier | AK62: Balanced / selective | AL62: Market remains active but increasingly differentiated by developer, micro-location, livability, and pricing discipline. | AM62: 11 | AN62: 7.25 | AO62: 0.55 | AP62: 0 | AQ62: 0 | AR62: 0 | AS62: 0.01 | AT62: 0.005 | AU62: 0.0025 | AV62: -0.005 | AW62: =IF(X62="","",(AM62/100*AO62)+AP62+AQ62+AR62) | AX62: =IF(X62="","",AS62+AT62+AU62+AV62) | AY62: =IF(AZ62="","",ROUND(AZ62*(1+Assumptions!$B$10),0)) | AZ62: =IF(X62="","",ROUND(X62*(1+AW62),0)) | BA62: =IF(AZ62="","",ROUND(AZ62*(1+Assumptions!$B$11),0)) | BB62: =IF(AZ62="","",ROUND(AZ62*(1+AX62+Assumptions!$B$10),0)) | BC62: =IF(AZ62="","",ROUND(AZ62*(1+AX62),0)) | BD62: =IF(AZ62="","",ROUND(AZ62*(1+AX62+Assumptions!$B$11),0)) | BE62: =IF(AZ62="","",ROUND(AZ62*(1+AX62)*(1+AX62),0)) | BF62: Rules-based enrichment using launch-price anchor, cap-app realization, and 2026 segment conditions. | BG62: 2026-03-17 | BH62: DLD / Digital Dubai / CBUAE / Savills / Knight Frank-Moody’s / Reuters
A63: 62 | B63: St. Regis Residences | C63: Emaar Properties | D63: Downtown Dubai | E63: Branded Apartments | F63: Luxury / Burj View | G63: 3.8M | H63: 3500 | I63: 45+ | J63: 70/30 | K63: 2022 | L63: 4.0-4.5 | M63: 10-15 | N63: 14.0-19.5 | O63: Hartland Intl | P63: Mediclinic Dubai Mall | Q63: Dubai Mall | R63: Financial Ctr Rd | S63: 5 | T63: 20 | U63: 15 | V63: 35 | W63: 2 | X63: 3800000 | Y63: 3800000 | Z63: 4 | AA63: 4.5 | AB63: 10 | AC63: 15 | AD63: 14 | AE63: 19.5 | AF63: 2022 | AH63: Apartment | AI63: Prime | AJ63: TopTier | AK63: Prime resilient / selective | AL63: Better support from quality, branding, and scarcer prime stock; still entry-price sensitive. | AM63: 12.5 | AN63: 4.25 | AO63: 0.55 | AP63: 0.02 | AQ63: 0 | AR63: 0 | AS63: 0.03 | AT63: 0.005 | AU63: 0 | AV63: -0.005 | AW63: =IF(X63="","",(AM63/100*AO63)+AP63+AQ63+AR63) | AX63: =IF(X63="","",AS63+AT63+AU63+AV63) | AY63: =IF(AZ63="","",ROUND(AZ63*(1+Assumptions!$B$10),0)) | AZ63: =IF(X63="","",ROUND(X63*(1+AW63),0)) | BA63: =IF(AZ63="","",ROUND(AZ63*(1+Assumptions!$B$11),0)) | BB63: =IF(AZ63="","",ROUND(AZ63*(1+AX63+Assumptions!$B$10),0)) | BC63: =IF(AZ63="","",ROUND(AZ63*(1+AX63),0)) | BD63: =IF(AZ63="","",ROUND(AZ63*(1+AX63+Assumptions!$B$11),0)) | BE63: =IF(AZ63="","",ROUND(AZ63*(1+AX63)*(1+AX63),0)) | BF63: Rules-based enrichment using launch-price anchor, cap-app realization, and 2026 segment conditions. | BG63: 2026-03-17 | BH63: DLD / Digital Dubai / CBUAE / Savills / Knight Frank-Moody’s / Reuters
A64: 63 | B64: Burj Crown | C64: Emaar Properties | D64: Downtown Dubai | E64: Apartments | F64: City Centre | G64: 2.2M | H64: 2800 | I64: 30 | J64: Completed | K64: 2020 | L64: 5.0-5.5 | M64: 8-10 | N64: 13.0-15.5 | O64: Hartland Intl | P64: Mediclinic Dubai Mall | Q64: Dubai Mall | R64: Financial Ctr Rd | S64: 5 | T64: 20 | U64: 15 | V64: 35 | W64: 2 | X64: 2200000 | Y64: 2200000 | Z64: 5 | AA64: 5.5 | AB64: 8 | AC64: 10 | AD64: 13 | AE64: 15.5 | AF64: 2020 | AH64: Apartment | AI64: Prime | AJ64: TopTier | AK64: Prime resilient / selective | AL64: Better support from quality, branding, and scarcer prime stock; still entry-price sensitive. | AM64: 9 | AN64: 5.25 | AO64: 0.55 | AP64: 0.02 | AQ64: 0 | AR64: 0 | AS64: 0.03 | AT64: 0.005 | AU64: 0 | AV64: -0.005 | AW64: =IF(X64="","",(AM64/100*AO64)+AP64+AQ64+AR64) | AX64: =IF(X64="","",AS64+AT64+AU64+AV64) | AY64: =IF(AZ64="","",ROUND(AZ64*(1+Assumptions!$B$10),0)) | AZ64: =IF(X64="","",ROUND(X64*(1+AW64),0)) | BA64: =IF(AZ64="","",ROUND(AZ64*(1+Assumptions!$B$11),0)) | BB64: =IF(AZ64="","",ROUND(AZ64*(1+AX64+Assumptions!$B$10),0)) | BC64: =IF(AZ64="","",ROUND(AZ64*(1+AX64),0)) | BD64: =IF(AZ64="","",ROUND(AZ64*(1+AX64+Assumptions!$B$11),0)) | BE64: =IF(AZ64="","",ROUND(AZ64*(1+AX64)*(1+AX64),0)) | BF64: Rules-based enrichment using launch-price anchor, cap-app realization, and 2026 segment conditions. | BG64: 2026-03-17 | BH64: DLD / Digital Dubai / CBUAE / Savills / Knight Frank-Moody’s / Reuters
A65: 64 | B65: Grande | C65: Emaar Properties | D65: Downtown Dubai | E65: Apartments | F65: Opera District | G65: 2.5M | H65: 3000 | I65: 30 | J65: Completed | K65: 2019 | L65: 5.0-5.5 | M65: 8-10 | N65: 13.0-15.5 | O65: Hartland Intl | P65: Mediclinic Dubai Mall | Q65: Dubai Mall | R65: Financial Ctr Rd | S65: 5 | T65: 20 | U65: 15 | V65: 35 | W65: 2 | X65: 2500000 | Y65: 2500000 | Z65: 5 | AA65: 5.5 | AB65: 8 | AC65: 10 | AD65: 13 | AE65: 15.5 | AF65: 2019 | AH65: Apartment | AI65: Prime | AJ65: TopTier | AK65: Prime resilient / selective | AL65: Better support from quality, branding, and scarcer prime stock; still entry-price sensitive. | AM65: 9 | AN65: 5.25 | AO65: 0.55 | AP65: 0.02 | AQ65: 0 | AR65: 0 | AS65: 0.03 | AT65: 0.005 | AU65: 0 | AV65: -0.005 | AW65: =IF(X65="","",(AM65/100*AO65)+AP65+AQ65+AR65) | AX65: =IF(X65="","",AS65+AT65+AU65+AV65) | AY65: =IF(AZ65="","",ROUND(AZ65*(1+Assumptions!$B$10),0)) | AZ65: =IF(X65="","",ROUND(X65*(1+AW65),0)) | BA65: =IF(AZ65="","",ROUND(AZ65*(1+Assumptions!$B$11),0)) | BB65: =IF(AZ65="","",ROUND(AZ65*(1+AX65+Assumptions!$B$10),0)) | BC65: =IF(AZ65="","",ROUND(AZ65*(1+AX65),0)) | BD65: =IF(AZ65="","",ROUND(AZ65*(1+AX65+Assumptions!$B$11),0)) | BE65: =IF(AZ65="","",ROUND(AZ65*(1+AX65)*(1+AX65),0)) | BF65: Rules-based enrichment using launch-price anchor, cap-app realization, and 2026 segment conditions. | BG65: 2026-03-17 | BH65: DLD / Digital Dubai / CBUAE / Savills / Knight Frank-Moody’s / Reuters
A66: 65 | B66: Act One | Act Two | C66: Emaar Properties | D66: Downtown Dubai | E66: Apartments | F66: Opera District | G66: 2.1M | H66: 2600 | I66: 30 | J66: Completed | K66: 2018 | L66: 5.5-6.0 | M66: 7-9 | N66: 12.5-15.0 | O66: Hartland Intl | P66: Mediclinic Dubai Mall | Q66: Dubai Mall | R66: Financial Ctr Rd | S66: 5 | T66: 20 | U66: 15 | V66: 35 | W66: 2 | X66: 2100000 | Y66: 2100000 | Z66: 5.5 | AA66: 6 | AB66: 7 | AC66: 9 | AD66: 12.5 | AE66: 15 | AF66: 2018 | AH66: Apartment | AI66: Prime | AJ66: TopTier | AK66: Prime resilient / selective | AL66: Better support from quality, branding, and scarcer prime stock; still entry-price sensitive. | AM66: 8 | AN66: 5.75 | AO66: 0.55 | AP66: 0.02 | AQ66: 0 | AR66: 0 | AS66: 0.03 | AT66: 0.005 | AU66: 0 | AV66: -0.005 | AW66: =IF(X66="","",(AM66/100*AO66)+AP66+AQ66+AR66) | AX66: =IF(X66="","",AS66+AT66+AU66+AV66) | AY66: =IF(AZ66="","",ROUND(AZ66*(1+Assumptions!$B$10),0)) | AZ66: =IF(X66="","",ROUND(X66*(1+AW66),0)) | BA66: =IF(AZ66="","",ROUND(AZ66*(1+Assumptions!$B$11),0)) | BB66: =IF(AZ66="","",ROUND(AZ66*(1+AX66+Assumptions!$B$10),0)) | BC66: =IF(AZ66="","",ROUND(AZ66*(1+AX66),0)) | BD66: =IF(AZ66="","",ROUND(AZ66*(1+AX66+Assumptions!$B$11),0)) | BE66: =IF(AZ66="","",ROUND(AZ66*(1+AX66)*(1+AX66),0)) | BF66: Rules-based enrichment using launch-price anchor, cap-app realization, and 2026 segment conditions. | BG66: 2026-03-17 | BH66: DLD / Digital Dubai / CBUAE / Savills / Knight Frank-Moody’s / Reuters
A67: 66 | B67: Il Primo | C67: Emaar Properties | D67: Downtown Dubai | E67: Penthouse/Luxury | F67: Opera District | G67: 18M+ | H67: 4500 | I67: 45+ | J67: Completed | K67: 2018 | L67: 3.5-4.0 | M67: 8-10 | N67: 11.5-14.0 | O67: Hartland Intl | P67: Mediclinic Dubai Mall | Q67: Dubai Mall | R67: Financial Ctr Rd | S67: 5 | T67: 20 | U67: 15 | V67: 35 | W67: 2 | X67: 18000000 | Y67: 18000000 | Z67: 3.5 | AA67: 4 | AB67: 8 | AC67: 10 | AD67: 11.5 | AE67: 14 | AF67: 2018 | AH67: Mixed/Other | AI67: Prime | AJ67: TopTier | AK67: Prime resilient / selective | AL67: Better support from quality, branding, and scarcer prime stock; still entry-price sensitive. | AM67: 9 | AN67: 3.75 | AO67: 0.55 | AP67: 0.02 | AQ67: 0 | AR67: 0 | AS67: 0.03 | AT67: 0.005 | AU67: 0 | AV67: -0.005 | AW67: =IF(X67="","",(AM67/100*AO67)+AP67+AQ67+AR67) | AX67: =IF(X67="","",AS67+AT67+AU67+AV67) | AY67: =IF(AZ67="","",ROUND(AZ67*(1+Assumptions!$B$10),0)) | AZ67: =IF(X67="","",ROUND(X67*(1+AW67),0)) | BA67: =IF(AZ67="","",ROUND(AZ67*(1+Assumptions!$B$11),0)) | BB67: =IF(AZ67="","",ROUND(AZ67*(1+AX67+Assumptions!$B$10),0)) | BC67: =IF(AZ67="","",ROUND(AZ67*(1+AX67),0)) | BD67: =IF(AZ67="","",ROUND(AZ67*(1+AX67+Assumptions!$B$11),0)) | BE67: =IF(AZ67="","",ROUND(AZ67*(1+AX67)*(1+AX67),0)) | BF67: Rules-based enrichment using launch-price anchor, cap-app realization, and 2026 segment conditions. | BG67: 2026-03-17 | BH67: DLD / Digital Dubai / CBUAE / Savills / Knight Frank-Moody’s / Reuters
A68: 67 | B68: Palm Jebel Ali | C68: Nakheel | D68: Jebel Ali Waterfront | E68: Villas & Plots | F68: Mega Island / Beach | G68: 18.5M | H68: 2500+ | I68: TBA | J68: 80/20 | K68: 2023 | L68: 3.5-4.5 | M68: 15-20 | N68: 18.5-24.5 | O68: Dove Green (DIP) | P68: Aster Cedars Jebel Ali | Q68: Ibn Battuta Mall | R68: Sheikh Zayed E11 | S68: 40 | T68: 20 | U68: 45 | V68: 20 | W68: 2 | X68: 18500000 | Y68: 18500000 | Z68: 3.5 | AA68: 4.5 | AB68: 15 | AC68: 20 | AD68: 18.5 | AE68: 24.5 | AF68: 2023 | AH68: Villa | AI68: MainstreamSelective | AJ68: TopTier | AK68: Family-villa resilient | AL68: Villa/townhouse demand remains relatively firmer, though growth should be slower than the post-2020 surge. | AM68: 17.5 | AN68: 4 | AO68: 0.55 | AP68: 0 | AQ68: 0.015 | AR68: 0 | AS68: 0.025 | AT68: 0.005 | AU68: 0 | AV68: -0.005 | AW68: =IF(X68="","",(AM68/100*AO68)+AP68+AQ68+AR68) | AX68: =IF(X68="","",AS68+AT68+AU68+AV68) | AY68: =IF(AZ68="","",ROUND(AZ68*(1+Assumptions!$B$10),0)) | AZ68: =IF(X68="","",ROUND(X68*(1+AW68),0)) | BA68: =IF(AZ68="","",ROUND(AZ68*(1+Assumptions!$B$11),0)) | BB68: =IF(AZ68="","",ROUND(AZ68*(1+AX68+Assumptions!$B$10),0)) | BC68: =IF(AZ68="","",ROUND(AZ68*(1+AX68),0)) | BD68: =IF(AZ68="","",ROUND(AZ68*(1+AX68+Assumptions!$B$11),0)) | BE68: =IF(AZ68="","",ROUND(AZ68*(1+AX68)*(1+AX68),0)) | BF68: Rules-based enrichment using launch-price anchor, cap-app realization, and 2026 segment conditions. | BG68: 2026-03-17 | BH68: DLD / Digital Dubai / CBUAE / Savills / Knight Frank-Moody’s / Reuters
A69: 68 | B69: The Fronds: Coral Collection | C69: Nakheel | D69: Palm Jebel Ali | E69: Villas (7 Beds) | F69: Luxury Beachfront | G69: 22M+ | H69: 2800 | I69: TBA | J69: 80/20 | K69: 2023 | L69: 3.5-4.0 | M69: 15-20 | N69: 18.5-24.0 | O69: Dove Green (DIP) | P69: Aster Cedars Jebel Ali | Q69: Ibn Battuta Mall | R69: Sheikh Zayed E11 | S69: 40 | T69: 20 | U69: 45 | V69: 20 | W69: 2 | X69: 22000000 | Y69: 22000000 | Z69: 3.5 | AA69: 4 | AB69: 15 | AC69: 20 | AD69: 18.5 | AE69: 24 | AF69: 2023 | AH69: Villa | AI69: MainstreamSelective | AJ69: TopTier | AK69: Family-villa resilient | AL69: Villa/townhouse demand remains relatively firmer, though growth should be slower than the post-2020 surge. | AM69: 17.5 | AN69: 3.75 | AO69: 0.55 | AP69: 0 | AQ69: 0.015 | AR69: 0 | AS69: 0.025 | AT69: 0.005 | AU69: 0 | AV69: -0.005 | AW69: =IF(X69="","",(AM69/100*AO69)+AP69+AQ69+AR69) | AX69: =IF(X69="","",AS69+AT69+AU69+AV69) | AY69: =IF(AZ69="","",ROUND(AZ69*(1+Assumptions!$B$10),0)) | AZ69: =IF(X69="","",ROUND(X69*(1+AW69),0)) | BA69: =IF(AZ69="","",ROUND(AZ69*(1+Assumptions!$B$11),0)) | BB69: =IF(AZ69="","",ROUND(AZ69*(1+AX69+Assumptions!$B$10),0)) | BC69: =IF(AZ69="","",ROUND(AZ69*(1+AX69),0)) | BD69: =IF(AZ69="","",ROUND(AZ69*(1+AX69+Assumptions!$B$11),0)) | BE69: =IF(AZ69="","",ROUND(AZ69*(1+AX69)*(1+AX69),0)) | BF69: Rules-based enrichment using launch-price anchor, cap-app realization, and 2026 segment conditions. | BG69: 2026-03-17 | BH69: DLD / Digital Dubai / CBUAE / Savills / Knight Frank-Moody’s / Reuters
A70: 69 | B70: The Fronds: Beach Collection | C70: Nakheel | D70: Palm Jebel Ali | E70: Villas (5-6 Beds) | F70: Luxury Beachfront | G70: 18.5M | H70: 2600 | I70: TBA | J70: 80/20 | K70: 2023 | L70: 3.5-4.5 | M70: 15-20 | N70: 18.5-24.5 | O70: Dove Green (DIP) | P70: Aster Cedars Jebel Ali | Q70: Ibn Battuta Mall | R70: Sheikh Zayed E11 | S70: 40 | T70: 20 | U70: 45 | V70: 20 | W70: 2 | X70: 18500000 | Y70: 18500000 | Z70: 3.5 | AA70: 4.5 | AB70: 15 | AC70: 20 | AD70: 18.5 | AE70: 24.5 | AF70: 2023 | AH70: Villa | AI70: MainstreamSelective | AJ70: TopTier | AK70: Family-villa resilient | AL70: Villa/townhouse demand remains relatively firmer, though growth should be slower than the post-2020 surge. | AM70: 17.5 | AN70: 4 | AO70: 0.55 | AP70: 0 | AQ70: 0.015 | AR70: 0 | AS70: 0.025 | AT70: 0.005 | AU70: 0 | AV70: -0.005 | AW70: =IF(X70="","",(AM70/100*AO70)+AP70+AQ70+AR70) | AX70: =IF(X70="","",AS70+AT70+AU70+AV70) | AY70: =IF(AZ70="","",ROUND(AZ70*(1+Assumptions!$B$10),0)) | AZ70: =IF(X70="","",ROUND(X70*(1+AW70),0)) | BA70: =IF(AZ70="","",ROUND(AZ70*(1+Assumptions!$B$11),0)) | BB70: =IF(AZ70="","",ROUND(AZ70*(1+AX70+Assumptions!$B$10),0)) | BC70: =IF(AZ70="","",ROUND(AZ70*(1+AX70),0)) | BD70: =IF(AZ70="","",ROUND(AZ70*(1+AX70+Assumptions!$B$11),0)) | BE70: =IF(AZ70="","",ROUND(AZ70*(1+AX70)*(1+AX70),0)) | BF70: Rules-based enrichment using launch-price anchor, cap-app realization, and 2026 segment conditions. | BG70: 2026-03-17 | BH70: DLD / Digital Dubai / CBUAE / Savills / Knight Frank-Moody’s / Reuters
A71: 70 | B71: Dubai Islands | C71: Nakheel | D71: Deira Waterfront | E71: Mixed | F71: Islands / Resort | I71: 20 | J71: Varies | K71: Ongoing | L71: 6.0-7.0 | M71: 12-15 | N71: 18.0-22.0 | O71: The Elite English | P71: Dubai Hospital | Q71: City Centre Deira | R71: Infinity Bridge | S71: 20 | T71: 35 | U71: 15 | V71: 45 | W71: 2 | Z71: 6 | AA71: 7 | AB71: 12 | AC71: 15 | AD71: 18 | AE71: 22 | AH71: Land | AI71: MainstreamSelective | AJ71: TopTier | AK71: Balanced / selective | AL71: Market remains active but increasingly differentiated by developer, micro-location, livability, and pricing discipline. | AM71: 13.5 | AN71: 6.5 | AO71: 0.25 | AP71: 0 | AQ71: 0 | AR71: 0 | AS71: 0.01 | AT71: 0.005 | AU71: 0.0025 | AV71: -0.005 | AW71: =IF(X71="","",(AM71/100*AO71)+AP71+AQ71+AR71) | AX71: =IF(X71="","",AS71+AT71+AU71+AV71) | AY71: =IF(AZ71="","",ROUND(AZ71*(1+Assumptions!$B$10),0)) | AZ71: =IF(X71="","",ROUND(X71*(1+AW71),0)) | BA71: =IF(AZ71="","",ROUND(AZ71*(1+Assumptions!$B$11),0)) | BB71: =IF(AZ71="","",ROUND(AZ71*(1+AX71+Assumptions!$B$10),0)) | BC71: =IF(AZ71="","",ROUND(AZ71*(1+AX71),0)) | BD71: =IF(AZ71="","",ROUND(AZ71*(1+AX71+Assumptions!$B$11),0)) | BE71: =IF(AZ71="","",ROUND(AZ71*(1+AX71)*(1+AX71),0)) | BF71: Rules-based enrichment using launch-price anchor, cap-app realization, and 2026 segment conditions. | BG71: 2026-03-17 | BH71: DLD / Digital Dubai / CBUAE / Savills / Knight Frank-Moody’s / Reuters
A72: 71 | B72: Rixos Dubai Islands | C72: Nakheel | D72: Dubai Islands | E72: Branded Residences | F72: Resort / Beach | G72: 2.6M | H72: 2400 | I72: 40 | J72: 80/20 | K72: 2023 | L72: 5.0-5.5 | M72: 12-15 | N72: 17.0-20.5 | O72: The Elite English | P72: Dubai Hospital | Q72: City Centre Deira | R72: Infinity Bridge | S72: 20 | T72: 35 | U72: 15 | V72: 45 | W72: 2 | X72: 2600000 | Y72: 2600000 | Z72: 5 | AA72: 5.5 | AB72: 12 | AC72: 15 | AD72: 17 | AE72: 20.5 | AF72: 2023 | AH72: Apartment | AI72: MainstreamSelective | AJ72: TopTier | AK72: Balanced / selective | AL72: Market remains active but increasingly differentiated by developer, micro-location, livability, and pricing discipline. | AM72: 13.5 | AN72: 5.25 | AO72: 0.55 | AP72: 0 | AQ72: 0 | AR72: 0 | AS72: 0.01 | AT72: 0.005 | AU72: 0 | AV72: -0.005 | AW72: =IF(X72="","",(AM72/100*AO72)+AP72+AQ72+AR72) | AX72: =IF(X72="","",AS72+AT72+AU72+AV72) | AY72: =IF(AZ72="","",ROUND(AZ72*(1+Assumptions!$B$10),0)) | AZ72: =IF(X72="","",ROUND(X72*(1+AW72),0)) | BA72: =IF(AZ72="","",ROUND(AZ72*(1+Assumptions!$B$11),0)) | BB72: =IF(AZ72="","",ROUND(AZ72*(1+AX72+Assumptions!$B$10),0)) | BC72: =IF(AZ72="","",ROUND(AZ72*(1+AX72),0)) | BD72: =IF(AZ72="","",ROUND(AZ72*(1+AX72+Assumptions!$B$11),0)) | BE72: =IF(AZ72="","",ROUND(AZ72*(1+AX72)*(1+AX72),0)) | BF72: Rules-based enrichment using launch-price anchor, cap-app realization, and 2026 segment conditions. | BG72: 2026-03-17 | BH72: DLD / Digital Dubai / CBUAE / Savills / Knight Frank-Moody’s / Reuters
A73: 72 | B73: Bay Villas | C73: Nakheel | D73: Dubai Islands | E73: Villas | F73: Waterfront | G73: 4.5M | H73: 1600 | I73: 20 | J73: 80/20 | K73: 2024 | L73: 5.0-5.5 | M73: 12-15 | N73: 17.0-20.5 | O73: The Elite English | P73: Dubai Hospital | Q73: City Centre Deira | R73: Infinity Bridge | S73: 20 | T73: 35 | U73: 15 | V73: 45 | W73: 2 | X73: 4500000 | Y73: 4500000 | Z73: 5 | AA73: 5.5 | AB73: 12 | AC73: 15 | AD73: 17 | AE73: 20.5 | AF73: 2024 | AH73: Villa | AI73: MainstreamSelective | AJ73: TopTier | AK73: Family-villa resilient | AL73: Villa/townhouse demand remains relatively firmer, though growth should be slower than the post-2020 surge. | AM73: 13.5 | AN73: 5.25 | AO73: 0.55 | AP73: 0 | AQ73: 0.015 | AR73: 0 | AS73: 0.025 | AT73: 0.005 | AU73: 0 | AV73: -0.005 | AW73: =IF(X73="","",(AM73/100*AO73)+AP73+AQ73+AR73) | AX73: =IF(X73="","",AS73+AT73+AU73+AV73) | AY73: =IF(AZ73="","",ROUND(AZ73*(1+Assumptions!$B$10),0)) | AZ73: =IF(X73="","",ROUND(X73*(1+AW73),0)) | BA73: =IF(AZ73="","",ROUND(AZ73*(1+Assumptions!$B$11),0)) | BB73: =IF(AZ73="","",ROUND(AZ73*(1+AX73+Assumptions!$B$10),0)) | BC73: =IF(AZ73="","",ROUND(AZ73*(1+AX73),0)) | BD73: =IF(AZ73="","",ROUND(AZ73*(1+AX73+Assumptions!$B$11),0)) | BE73: =IF(AZ73="","",ROUND(AZ73*(1+AX73)*(1+AX73),0)) | BF73: Rules-based enrichment using launch-price anchor, cap-app realization, and 2026 segment conditions. | BG73: 2026-03-17 | BH73: DLD / Digital Dubai / CBUAE / Savills / Knight Frank-Moody’s / Reuters
A74: 73 | B74: Beach Walk Residences | C74: Nakheel | D74: Dubai Islands | E74: Apartments | F74: Beachfront | G74: 1.9M | H74: 1800 | I74: 20 | J74: 80/20 | K74: 2024 | L74: 6.0-6.5 | M74: 12-15 | N74: 18.0-21.5 | O74: The Elite English | P74: Dubai Hospital | Q74: City Centre Deira | R74: Infinity Bridge | S74: 20 | T74: 35 | U74: 15 | V74: 45 | W74: 2 | X74: 1900000 | Y74: 1900000 | Z74: 6 | AA74: 6.5 | AB74: 12 | AC74: 15 | AD74: 18 | AE74: 21.5 | AF74: 2024 | AH74: Apartment | AI74: MainstreamSelective | AJ74: TopTier | AK74: Balanced / selective | AL74: Market remains active but increasingly differentiated by developer, micro-location, livability, and pricing discipline. | AM74: 13.5 | AN74: 6.25 | AO74: 0.55 | AP74: 0 | AQ74: 0 | AR74: 0 | AS74: 0.01 | AT74: 0.005 | AU74: 0.0025 | AV74: -0.005 | AW74: =IF(X74="","",(AM74/100*AO74)+AP74+AQ74+AR74) | AX74: =IF(X74="","",AS74+AT74+AU74+AV74) | AY74: =IF(AZ74="","",ROUND(AZ74*(1+Assumptions!$B$10),0)) | AZ74: =IF(X74="","",ROUND(X74*(1+AW74),0)) | BA74: =IF(AZ74="","",ROUND(AZ74*(1+Assumptions!$B$11),0)) | BB74: =IF(AZ74="","",ROUND(AZ74*(1+AX74+Assumptions!$B$10),0)) | BC74: =IF(AZ74="","",ROUND(AZ74*(1+AX74),0)) | BD74: =IF(AZ74="","",ROUND(AZ74*(1+AX74+Assumptions!$B$11),0)) | BE74: =IF(AZ74="","",ROUND(AZ74*(1+AX74)*(1+AX74),0)) | BF74: Rules-based enrichment using launch-price anchor, cap-app realization, and 2026 segment conditions. | BG74: 2026-03-17 | BH74: DLD / Digital Dubai / CBUAE / Savills / Knight Frank-Moody’s / Reuters
A75: 74 | B75: Palm Jumeirah (Master Community) | C75: Nakheel | D75: Palm Jumeirah | E75: Mixed | F75: Iconic Island | I75: 30+ | K75: Completed | L75: 4.5-5.5 | M75: 8-12 | N75: 12.5-17.5 | O75: Chevalier College | P75: Emirates Hospital | Q75: Nakheel Mall | R75: Sheikh Zayed E11 | S75: 20 | T75: 10 | U75: 25 | V75: 35 | W75: 2 | Z75: 4.5 | AA75: 5.5 | AB75: 8 | AC75: 12 | AD75: 12.5 | AE75: 17.5 | AH75: Land | AI75: Prime | AJ75: TopTier | AK75: Prime resilient / selective | AL75: Better support from quality, branding, and scarcer prime stock; still entry-price sensitive. | AM75: 10 | AN75: 5 | AO75: 0.25 | AP75: 0.02 | AQ75: 0 | AR75: 0 | AS75: 0.03 | AT75: 0.005 | AU75: 0 | AV75: -0.005 | AW75: =IF(X75="","",(AM75/100*AO75)+AP75+AQ75+AR75) | AX75: =IF(X75="","",AS75+AT75+AU75+AV75) | AY75: =IF(AZ75="","",ROUND(AZ75*(1+Assumptions!$B$10),0)) | AZ75: =IF(X75="","",ROUND(X75*(1+AW75),0)) | BA75: =IF(AZ75="","",ROUND(AZ75*(1+Assumptions!$B$11),0)) | BB75: =IF(AZ75="","",ROUND(AZ75*(1+AX75+Assumptions!$B$10),0)) | BC75: =IF(AZ75="","",ROUND(AZ75*(1+AX75),0)) | BD75: =IF(AZ75="","",ROUND(AZ75*(1+AX75+Assumptions!$B$11),0)) | BE75: =IF(AZ75="","",ROUND(AZ75*(1+AX75)*(1+AX75),0)) | BF75: Rules-based enrichment using launch-price anchor, cap-app realization, and 2026 segment conditions. | BG75: 2026-03-17 | BH75: DLD / Digital Dubai / CBUAE / Savills / Knight Frank-Moody’s / Reuters
A76: 75 | B76: Como Residences | C76: Nakheel | D76: Palm Jumeirah | E76: Ultra-Luxury Apts | F76: High-Rise/Beach | G76: 21M+ | H76: 6000+ | I76: 40+ | J76: 80/20 | K76: 2023 | L76: 3.0-3.5 | M76: 10-15 | N76: 13.0-18.5 | O76: Chevalier College | P76: Emirates Hospital | Q76: Nakheel Mall | R76: Sheikh Zayed E11 | S76: 20 | T76: 10 | U76: 25 | V76: 35 | W76: 2 | X76: 21000000 | Y76: 21000000 | Z76: 3 | AA76: 3.5 | AB76: 10 | AC76: 15 | AD76: 13 | AE76: 18.5 | AF76: 2023 | AH76: Apartment | AI76: Prime | AJ76: TopTier | AK76: Prime resilient / selective | AL76: Better support from quality, branding, and scarcer prime stock; still entry-price sensitive. | AM76: 12.5 | AN76: 3.25 | AO76: 0.55 | AP76: 0.02 | AQ76: 0 | AR76: 0 | AS76: 0.03 | AT76: 0.005 | AU76: 0 | AV76: -0.005 | AW76: =IF(X76="","",(AM76/100*AO76)+AP76+AQ76+AR76) | AX76: =IF(X76="","",AS76+AT76+AU76+AV76) | AY76: =IF(AZ76="","",ROUND(AZ76*(1+Assumptions!$B$10),0)) | AZ76: =IF(X76="","",ROUND(X76*(1+AW76),0)) | BA76: =IF(AZ76="","",ROUND(AZ76*(1+Assumptions!$B$11),0)) | BB76: =IF(AZ76="","",ROUND(AZ76*(1+AX76+Assumptions!$B$10),0)) | BC76: =IF(AZ76="","",ROUND(AZ76*(1+AX76),0)) | BD76: =IF(AZ76="","",ROUND(AZ76*(1+AX76+Assumptions!$B$11),0)) | BE76: =IF(AZ76="","",ROUND(AZ76*(1+AX76)*(1+AX76),0)) | BF76: Rules-based enrichment using launch-price anchor, cap-app realization, and 2026 segment conditions. | BG76: 2026-03-17 | BH76: DLD / Digital Dubai / CBUAE / Savills / Knight Frank-Moody’s / Reuters
A77: 76 | B77: Palm Beach Towers 1 | C77: Nakheel | D77: Palm Jumeirah | E77: Apartments | F77: Luxury / View | G77: 3.5M | H77: 3000 | I77: 30 | J77: 60/40 | K77: 2022 | L77: 4.5-5.0 | M77: 8-12 | N77: 12.5-17.0 | O77: Chevalier College | P77: Emirates Hospital | Q77: Nakheel Mall | R77: Sheikh Zayed E11 | S77: 20 | T77: 10 | U77: 25 | V77: 35 | W77: 2 | X77: 3500000 | Y77: 3500000 | Z77: 4.5 | AA77: 5 | AB77: 8 | AC77: 12 | AD77: 12.5 | AE77: 17 | AF77: 2022 | AH77: Apartment | AI77: Prime | AJ77: TopTier | AK77: Prime resilient / selective | AL77: Better support from quality, branding, and scarcer prime stock; still entry-price sensitive. | AM77: 10 | AN77: 4.75 | AO77: 0.55 | AP77: 0.02 | AQ77: 0 | AR77: 0 | AS77: 0.03 | AT77: 0.005 | AU77: 0 | AV77: -0.005 | AW77: =IF(X77="","",(AM77/100*AO77)+AP77+AQ77+AR77) | AX77: =IF(X77="","",AS77+AT77+AU77+AV77) | AY77: =IF(AZ77="","",ROUND(AZ77*(1+Assumptions!$B$10),0)) | AZ77: =IF(X77="","",ROUND(X77*(1+AW77),0)) | BA77: =IF(AZ77="","",ROUND(AZ77*(1+Assumptions!$B$11),0)) | BB77: =IF(AZ77="","",ROUND(AZ77*(1+AX77+Assumptions!$B$10),0)) | BC77: =IF(AZ77="","",ROUND(AZ77*(1+AX77),0)) | BD77: =IF(AZ77="","",ROUND(AZ77*(1+AX77+Assumptions!$B$11),0)) | BE77: =IF(AZ77="","",ROUND(AZ77*(1+AX77)*(1+AX77),0)) | BF77: Rules-based enrichment using launch-price anchor, cap-app realization, and 2026 segment conditions. | BG77: 2026-03-17 | BH77: DLD / Digital Dubai / CBUAE / Savills / Knight Frank-Moody’s / Reuters
A78: 77 | B78: Palm Beach Towers 2 | C78: Nakheel | D78: Palm Jumeirah | E78: Apartments | F78: Luxury / View | G78: 3.5M | H78: 3000 | I78: 30 | J78: 60/40 | K78: 2022 | L78: 4.5-5.0 | M78: 8-12 | N78: 12.5-17.0 | O78: Chevalier College | P78: Emirates Hospital | Q78: Nakheel Mall | R78: Sheikh Zayed E11 | S78: 20 | T78: 10 | U78: 25 | V78: 35 | W78: 2 | X78: 3500000 | Y78: 3500000 | Z78: 4.5 | AA78: 5 | AB78: 8 | AC78: 12 | AD78: 12.5 | AE78: 17 | AF78: 2022 | AH78: Apartment | AI78: Prime | AJ78: TopTier | AK78: Prime resilient / selective | AL78: Better support from quality, branding, and scarcer prime stock; still entry-price sensitive. | AM78: 10 | AN78: 4.75 | AO78: 0.55 | AP78: 0.02 | AQ78: 0 | AR78: 0 | AS78: 0.03 | AT78: 0.005 | AU78: 0 | AV78: -0.005 | AW78: =IF(X78="","",(AM78/100*AO78)+AP78+AQ78+AR78) | AX78: =IF(X78="","",AS78+AT78+AU78+AV78) | AY78: =IF(AZ78="","",ROUND(AZ78*(1+Assumptions!$B$10),0)) | AZ78: =IF(X78="","",ROUND(X78*(1+AW78),0)) | BA78: =IF(AZ78="","",ROUND(AZ78*(1+Assumptions!$B$11),0)) | BB78: =IF(AZ78="","",ROUND(AZ78*(1+AX78+Assumptions!$B$10),0)) | BC78: =IF(AZ78="","",ROUND(AZ78*(1+AX78),0)) | BD78: =IF(AZ78="","",ROUND(AZ78*(1+AX78+Assumptions!$B$11),0)) | BE78: =IF(AZ78="","",ROUND(AZ78*(1+AX78)*(1+AX78),0)) | BF78: Rules-based enrichment using launch-price anchor, cap-app realization, and 2026 segment conditions. | BG78: 2026-03-17 | BH78: DLD / Digital Dubai / CBUAE / Savills / Knight Frank-Moody’s / Reuters
A79: 78 | B79: Palm Beach Towers 3 | C79: Nakheel | D79: Palm Jumeirah | E79: Apartments | F79: Luxury / View | G79: 3.6M | H79: 3000 | I79: 30 | J79: 60/40 | K79: 2022 | L79: 4.5-5.0 | M79: 8-12 | N79: 12.5-17.0 | O79: Chevalier College | P79: Emirates Hospital | Q79: Nakheel Mall | R79: Sheikh Zayed E11 | S79: 20 | T79: 10 | U79: 25 | V79: 35 | W79: 2 | X79: 3600000 | Y79: 3600000 | Z79: 4.5 | AA79: 5 | AB79: 8 | AC79: 12 | AD79: 12.5 | AE79: 17 | AF79: 2022 | AH79: Apartment | AI79: Prime | AJ79: TopTier | AK79: Prime resilient / selective | AL79: Better support from quality, branding, and scarcer prime stock; still entry-price sensitive. | AM79: 10 | AN79: 4.75 | AO79: 0.55 | AP79: 0.02 | AQ79: 0 | AR79: 0 | AS79: 0.03 | AT79: 0.005 | AU79: 0 | AV79: -0.005 | AW79: =IF(X79="","",(AM79/100*AO79)+AP79+AQ79+AR79) | AX79: =IF(X79="","",AS79+AT79+AU79+AV79) | AY79: =IF(AZ79="","",ROUND(AZ79*(1+Assumptions!$B$10),0)) | AZ79: =IF(X79="","",ROUND(X79*(1+AW79),0)) | BA79: =IF(AZ79="","",ROUND(AZ79*(1+Assumptions!$B$11),0)) | BB79: =IF(AZ79="","",ROUND(AZ79*(1+AX79+Assumptions!$B$10),0)) | BC79: =IF(AZ79="","",ROUND(AZ79*(1+AX79),0)) | BD79: =IF(AZ79="","",ROUND(AZ79*(1+AX79+Assumptions!$B$11),0)) | BE79: =IF(AZ79="","",ROUND(AZ79*(1+AX79)*(1+AX79),0)) | BF79: Rules-based enrichment using launch-price anchor, cap-app realization, and 2026 segment conditions. | BG79: 2026-03-17 | BH79: DLD / Digital Dubai / CBUAE / Savills / Knight Frank-Moody’s / Reuters
A80: 79 | B80: The Palm Tower | C80: Nakheel | D80: Palm Jumeirah | E80: Hotel/Residences | F80: Luxury / View | G80: Resale (2.5M+) | H80: 3500 | I80: 35 | J80: Completed | K80: 2017 | L80: 5.0-5.5 | M80: 6-8 | N80: 11.0-13.5 | O80: Chevalier College | P80: Emirates Hospital | Q80: Nakheel Mall | R80: Sheikh Zayed E11 | S80: 20 | T80: 10 | U80: 25 | V80: 35 | W80: 2 | X80: 2500000 | Y80: 2500000 | Z80: 5 | AA80: 5.5 | AB80: 6 | AC80: 8 | AD80: 11 | AE80: 13.5 | AF80: 2017 | AH80: Apartment | AI80: Prime | AJ80: TopTier | AK80: Prime resilient / selective | AL80: Better support from quality, branding, and scarcer prime stock; still entry-price sensitive. | AM80: 7 | AN80: 5.25 | AO80: 0.55 | AP80: 0.02 | AQ80: 0 | AR80: 0 | AS80: 0.03 | AT80: 0.005 | AU80: 0 | AV80: -0.005 | AW80: =IF(X80="","",(AM80/100*AO80)+AP80+AQ80+AR80) | AX80: =IF(X80="","",AS80+AT80+AU80+AV80) | AY80: =IF(AZ80="","",ROUND(AZ80*(1+Assumptions!$B$10),0)) | AZ80: =IF(X80="","",ROUND(X80*(1+AW80),0)) | BA80: =IF(AZ80="","",ROUND(AZ80*(1+Assumptions!$B$11),0)) | BB80: =IF(AZ80="","",ROUND(AZ80*(1+AX80+Assumptions!$B$10),0)) | BC80: =IF(AZ80="","",ROUND(AZ80*(1+AX80),0)) | BD80: =IF(AZ80="","",ROUND(AZ80*(1+AX80+Assumptions!$B$11),0)) | BE80: =IF(AZ80="","",ROUND(AZ80*(1+AX80)*(1+AX80),0)) | BF80: Rules-based enrichment using launch-price anchor, cap-app realization, and 2026 segment conditions. | BG80: 2026-03-17 | BH80: DLD / Digital Dubai / CBUAE / Savills / Knight Frank-Moody’s / Reuters
A81: 80 | B81: Azure Residences | C81: Nakheel | D81: Palm Jumeirah | E81: Apartments | F81: Beachfront | G81: Resale (1.8M+) | H81: 2000 | I81: 25 | J81: Completed | K81: 2016 | L81: 5.5-6.0 | M81: 6-8 | N81: 11.5-14.0 | O81: Chevalier College | P81: Emirates Hospital | Q81: Nakheel Mall | R81: Sheikh Zayed E11 | S81: 20 | T81: 10 | U81: 25 | V81: 35 | W81: 2 | X81: 1800000 | Y81: 1800000 | Z81: 5.5 | AA81: 6 | AB81: 6 | AC81: 8 | AD81: 11.5 | AE81: 14 | AF81: 2016 | AH81: Apartment | AI81: Prime | AJ81: TopTier | AK81: Prime resilient / selective | AL81: Better support from quality, branding, and scarcer prime stock; still entry-price sensitive. | AM81: 7 | AN81: 5.75 | AO81: 0.55 | AP81: 0.02 | AQ81: 0 | AR81: 0 | AS81: 0.03 | AT81: 0.005 | AU81: 0 | AV81: -0.005 | AW81: =IF(X81="","",(AM81/100*AO81)+AP81+AQ81+AR81) | AX81: =IF(X81="","",AS81+AT81+AU81+AV81) | AY81: =IF(AZ81="","",ROUND(AZ81*(1+Assumptions!$B$10),0)) | AZ81: =IF(X81="","",ROUND(X81*(1+AW81),0)) | BA81: =IF(AZ81="","",ROUND(AZ81*(1+Assumptions!$B$11),0)) | BB81: =IF(AZ81="","",ROUND(AZ81*(1+AX81+Assumptions!$B$10),0)) | BC81: =IF(AZ81="","",ROUND(AZ81*(1+AX81),0)) | BD81: =IF(AZ81="","",ROUND(AZ81*(1+AX81+Assumptions!$B$11),0)) | BE81: =IF(AZ81="","",ROUND(AZ81*(1+AX81)*(1+AX81),0)) | BF81: Rules-based enrichment using launch-price anchor, cap-app realization, and 2026 segment conditions. | BG81: 2026-03-17 | BH81: DLD / Digital Dubai / CBUAE / Savills / Knight Frank-Moody’s / Reuters
A82: 81 | B82: Club Vista Mare | C82: Nakheel | D82: Palm Jumeirah | E82: Apartments | F82: Dining / Beach | G82: Resale | H82: 2200 | I82: 25 | J82: Completed | K82: 2016 | L82: 5.0-5.5 | M82: 6-8 | N82: 11.0-13.5 | O82: Chevalier College | P82: Emirates Hospital | Q82: Nakheel Mall | R82: Sheikh Zayed E11 | S82: 20 | T82: 10 | U82: 25 | V82: 35 | W82: 2 | Z82: 5 | AA82: 5.5 | AB82: 6 | AC82: 8 | AD82: 11 | AE82: 13.5 | AF82: 2016 | AH82: Apartment | AI82: Prime | AJ82: TopTier | AK82: Prime resilient / selective | AL82: Better support from quality, branding, and scarcer prime stock; still entry-price sensitive. | AM82: 7 | AN82: 5.25 | AO82: 0.55 | AP82: 0.02 | AQ82: 0 | AR82: 0 | AS82: 0.03 | AT82: 0.005 | AU82: 0 | AV82: -0.005 | AW82: =IF(X82="","",(AM82/100*AO82)+AP82+AQ82+AR82) | AX82: =IF(X82="","",AS82+AT82+AU82+AV82) | AY82: =IF(AZ82="","",ROUND(AZ82*(1+Assumptions!$B$10),0)) | AZ82: =IF(X82="","",ROUND(X82*(1+AW82),0)) | BA82: =IF(AZ82="","",ROUND(AZ82*(1+Assumptions!$B$11),0)) | BB82: =IF(AZ82="","",ROUND(AZ82*(1+AX82+Assumptions!$B$10),0)) | BC82: =IF(AZ82="","",ROUND(AZ82*(1+AX82),0)) | BD82: =IF(AZ82="","",ROUND(AZ82*(1+AX82+Assumptions!$B$11),0)) | BE82: =IF(AZ82="","",ROUND(AZ82*(1+AX82)*(1+AX82),0)) | BF82: Rules-based enrichment using launch-price anchor, cap-app realization, and 2026 segment conditions. | BG82: 2026-03-17 | BH82: DLD / Digital Dubai / CBUAE / Savills / Knight Frank-Moody’s / Reuters
A83: 82 | B83: Jumeirah Islands | C83: Nakheel | D83: Jumeirah Islands | E83: Villas | F83: Luxury / Lake | G83: Resale (12M+) | H83: 1800 | I83: 18 | J83: Completed | K83: 2004 | L83: 4.5-5.0 | M83: 5-7 | N83: 9.5-12.0 | O83: Dubai British School | P83: Mediclinic Meadows | Q83: Pavilion JI | R83: Sheikh Zayed E11 | S83: 20 | T83: 10 | U83: 25 | V83: 30 | W83: 2 | X83: 12000000 | Y83: 12000000 | Z83: 4.5 | AA83: 5 | AB83: 5 | AC83: 7 | AD83: 9.5 | AE83: 12 | AF83: 2004 | AH83: Villa | AI83: MainstreamSelective | AJ83: TopTier | AK83: Family-villa resilient | AL83: Villa/townhouse demand remains relatively firmer, though growth should be slower than the post-2020 surge. | AM83: 6 | AN83: 4.75 | AO83: 0.55 | AP83: 0 | AQ83: 0.015 | AR83: 0 | AS83: 0.025 | AT83: 0.005 | AU83: 0 | AV83: -0.005 | AW83: =IF(X83="","",(AM83/100*AO83)+AP83+AQ83+AR83) | AX83: =IF(X83="","",AS83+AT83+AU83+AV83) | AY83: =IF(AZ83="","",ROUND(AZ83*(1+Assumptions!$B$10),0)) | AZ83: =IF(X83="","",ROUND(X83*(1+AW83),0)) | BA83: =IF(AZ83="","",ROUND(AZ83*(1+Assumptions!$B$11),0)) | BB83: =IF(AZ83="","",ROUND(AZ83*(1+AX83+Assumptions!$B$10),0)) | BC83: =IF(AZ83="","",ROUND(AZ83*(1+AX83),0)) | BD83: =IF(AZ83="","",ROUND(AZ83*(1+AX83+Assumptions!$B$11),0)) | BE83: =IF(AZ83="","",ROUND(AZ83*(1+AX83)*(1+AX83),0)) | BF83: Rules-based enrichment using launch-price anchor, cap-app realization, and 2026 segment conditions. | BG83: 2026-03-17 | BH83: DLD / Digital Dubai / CBUAE / Savills / Knight Frank-Moody’s / Reuters
A84: 83 | B84: Jumeirah Park | C84: Nakheel | D84: Jumeirah Park | E84: Villas | F84: Family / Gated | G84: Resale (6M+) | H84: 1400 | I84: 12 | J84: Completed | K84: 2013 | L84: 5.0-5.5 | M84: 5-7 | N84: 10.0-12.5 | O84: Dubai British School | P84: Mediclinic Meadows | Q84: Pavilion JP | R84: Sheikh Zayed E11 | S84: 20 | T84: 10 | U84: 25 | V84: 30 | W84: 2 | X84: 6000000 | Y84: 6000000 | Z84: 5 | AA84: 5.5 | AB84: 5 | AC84: 7 | AD84: 10 | AE84: 12.5 | AF84: 2013 | AH84: Villa | AI84: MainstreamSelective | AJ84: TopTier | AK84: Family-villa resilient | AL84: Villa/townhouse demand remains relatively firmer, though growth should be slower than the post-2020 surge. | AM84: 6 | AN84: 5.25 | AO84: 0.55 | AP84: 0 | AQ84: 0.015 | AR84: 0 | AS84: 0.025 | AT84: 0.005 | AU84: 0 | AV84: -0.005 | AW84: =IF(X84="","",(AM84/100*AO84)+AP84+AQ84+AR84) | AX84: =IF(X84="","",AS84+AT84+AU84+AV84) | AY84: =IF(AZ84="","",ROUND(AZ84*(1+Assumptions!$B$10),0)) | AZ84: =IF(X84="","",ROUND(X84*(1+AW84),0)) | BA84: =IF(AZ84="","",ROUND(AZ84*(1+Assumptions!$B$11),0)) | BB84: =IF(AZ84="","",ROUND(AZ84*(1+AX84+Assumptions!$B$10),0)) | BC84: =IF(AZ84="","",ROUND(AZ84*(1+AX84),0)) | BD84: =IF(AZ84="","",ROUND(AZ84*(1+AX84+Assumptions!$B$11),0)) | BE84: =IF(AZ84="","",ROUND(AZ84*(1+AX84)*(1+AX84),0)) | BF84: Rules-based enrichment using launch-price anchor, cap-app realization, and 2026 segment conditions. | BG84: 2026-03-17 | BH84: DLD / Digital Dubai / CBUAE / Savills / Knight Frank-Moody’s / Reuters
A85: 84 | B85: Al Furjan (West & East) | C85: Nakheel | D85: Jebel Ali Area | E85: Villas & TH | F85: Family | G85: Resale (2.5M+) | H85: 1100 | I85: 10 | J85: Completed | K85: 2014 | L85: 6.5-7.0 | M85: 5-7 | N85: 11.5-14.0 | O85: The Arbor School | P85: NMC Royal DIP | Q85: Ibn Battuta Mall | R85: Yalayis / E311 | S85: 25 | T85: 15 | U85: 30 | V85: 20 | W85: 2 | X85: 2500000 | Y85: 2500000 | Z85: 6.5 | AA85: 7 | AB85: 5 | AC85: 7 | AD85: 11.5 | AE85: 14 | AF85: 2014 | AH85: Villa | AI85: MainstreamSelective | AJ85: TopTier | AK85: Family-villa resilient | AL85: Villa/townhouse demand remains relatively firmer, though growth should be slower than the post-2020 surge. | AM85: 6 | AN85: 6.75 | AO85: 0.55 | AP85: 0 | AQ85: 0.015 | AR85: 0 | AS85: 0.025 | AT85: 0.005 | AU85: 0.0025 | AV85: -0.005 | AW85: =IF(X85="","",(AM85/100*AO85)+AP85+AQ85+AR85) | AX85: =IF(X85="","",AS85+AT85+AU85+AV85) | AY85: =IF(AZ85="","",ROUND(AZ85*(1+Assumptions!$B$10),0)) | AZ85: =IF(X85="","",ROUND(X85*(1+AW85),0)) | BA85: =IF(AZ85="","",ROUND(AZ85*(1+Assumptions!$B$11),0)) | BB85: =IF(AZ85="","",ROUND(AZ85*(1+AX85+Assumptions!$B$10),0)) | BC85: =IF(AZ85="","",ROUND(AZ85*(1+AX85),0)) | BD85: =IF(AZ85="","",ROUND(AZ85*(1+AX85+Assumptions!$B$11),0)) | BE85: =IF(AZ85="","",ROUND(AZ85*(1+AX85)*(1+AX85),0)) | BF85: Rules-based enrichment using launch-price anchor, cap-app realization, and 2026 segment conditions. | BG85: 2026-03-17 | BH85: DLD / Digital Dubai / CBUAE / Savills / Knight Frank-Moody’s / Reuters
A86: 85 | B86: Tilal Al Furjan | C86: Nakheel | D86: Al Furjan | E86: Villas | F86: Gated Community | G86: 3.2M | H86: 1200 | I86: 12 | J86: Completed | K86: 2022 | L86: 6.0-6.5 | M86: 6-8 | N86: 12.0-14.5 | O86: The Arbor School | P86: NMC Royal DIP | Q86: Ibn Battuta Mall | R86: Yalayis / E311 | S86: 25 | T86: 15 | U86: 30 | V86: 20 | W86: 2 | X86: 3200000 | Y86: 3200000 | Z86: 6 | AA86: 6.5 | AB86: 6 | AC86: 8 | AD86: 12 | AE86: 14.5 | AF86: 2022 | AH86: Villa | AI86: MainstreamSelective | AJ86: TopTier | AK86: Family-villa resilient | AL86: Villa/townhouse demand remains relatively firmer, though growth should be slower than the post-2020 surge. | AM86: 7 | AN86: 6.25 | AO86: 0.55 | AP86: 0 | AQ86: 0.015 | AR86: 0 | AS86: 0.025 | AT86: 0.005 | AU86: 0.0025 | AV86: -0.005 | AW86: =IF(X86="","",(AM86/100*AO86)+AP86+AQ86+AR86) | AX86: =IF(X86="","",AS86+AT86+AU86+AV86) | AY86: =IF(AZ86="","",ROUND(AZ86*(1+Assumptions!$B$10),0)) | AZ86: =IF(X86="","",ROUND(X86*(1+AW86),0)) | BA86: =IF(AZ86="","",ROUND(AZ86*(1+Assumptions!$B$11),0)) | BB86: =IF(AZ86="","",ROUND(AZ86*(1+AX86+Assumptions!$B$10),0)) | BC86: =IF(AZ86="","",ROUND(AZ86*(1+AX86),0)) | BD86: =IF(AZ86="","",ROUND(AZ86*(1+AX86+Assumptions!$B$11),0)) | BE86: =IF(AZ86="","",ROUND(AZ86*(1+AX86)*(1+AX86),0)) | BF86: Rules-based enrichment using launch-price anchor, cap-app realization, and 2026 segment conditions. | BG86: 2026-03-17 | BH86: DLD / Digital Dubai / CBUAE / Savills / Knight Frank-Moody’s / Reuters
A87: 86 | B87: Murooj Al Furjan | C87: Nakheel | D87: Al Furjan | E87: Townhouses | F87: Gated Community | G87: 2.8M | H87: 1150 | I87: 12 | J87: Completed | K87: 2021 | L87: 6.5-7.0 | M87: 6-8 | N87: 12.5-15.0 | O87: The Arbor School | P87: NMC Royal DIP | Q87: Ibn Battuta Mall | R87: Yalayis / E311 | S87: 25 | T87: 15 | U87: 30 | V87: 20 | W87: 2 | X87: 2800000 | Y87: 2800000 | Z87: 6.5 | AA87: 7 | AB87: 6 | AC87: 8 | AD87: 12.5 | AE87: 15 | AF87: 2021 | AH87: Townhouse | AI87: MainstreamSelective | AJ87: TopTier | AK87: Family-villa resilient | AL87: Villa/townhouse demand remains relatively firmer, though growth should be slower than the post-2020 surge. | AM87: 7 | AN87: 6.75 | AO87: 0.55 | AP87: 0 | AQ87: 0.015 | AR87: 0 | AS87: 0.025 | AT87: 0.005 | AU87: 0.0025 | AV87: -0.005 | AW87: =IF(X87="","",(AM87/100*AO87)+AP87+AQ87+AR87) | AX87: =IF(X87="","",AS87+AT87+AU87+AV87) | AY87: =IF(AZ87="","",ROUND(AZ87*(1+Assumptions!$B$10),0)) | AZ87: =IF(X87="","",ROUND(X87*(1+AW87),0)) | BA87: =IF(AZ87="","",ROUND(AZ87*(1+Assumptions!$B$11),0)) | BB87: =IF(AZ87="","",ROUND(AZ87*(1+AX87+Assumptions!$B$10),0)) | BC87: =IF(AZ87="","",ROUND(AZ87*(1+AX87),0)) | BD87: =IF(AZ87="","",ROUND(AZ87*(1+AX87+Assumptions!$B$11),0)) | BE87: =IF(AZ87="","",ROUND(AZ87*(1+AX87)*(1+AX87),0)) | BF87: Rules-based enrichment using launch-price anchor, cap-app realization, and 2026 segment conditions. | BG87: 2026-03-17 | BH87: DLD / Digital Dubai / CBUAE / Savills / Knight Frank-Moody’s / Reuters
A88: 87 | B88: Discovery Gardens | C88: Nakheel | D88: Jebel Ali Area | E88: Apartments | F88: Budget / Garden | G88: Resale (500k+) | H88: 700 | I88: 12 | J88: Completed | K88: 2008 | L88: 8.0-8.5 | M88: 4-6 | N88: 12.0-14.5 | O88: Winchester School | P88: Aster Cedars | Q88: Ibn Battuta Mall | R88: Sheikh Zayed E11 | S88: 25 | T88: 10 | U88: 30 | V88: 25 | W88: 2 | X88: 500000 | Y88: 500000 | Z88: 8 | AA88: 8.5 | AB88: 4 | AC88: 6 | AD88: 12 | AE88: 14.5 | AF88: 2008 | AH88: Apartment | AI88: MainstreamSelective | AJ88: TopTier | AK88: Balanced / selective | AL88: Market remains active but increasingly differentiated by developer, micro-location, livability, and pricing discipline. | AM88: 5 | AN88: 8.25 | AO88: 0.55 | AP88: 0 | AQ88: 0 | AR88: 0 | AS88: 0.01 | AT88: 0.005 | AU88: 0.0025 | AV88: -0.005 | AW88: =IF(X88="","",(AM88/100*AO88)+AP88+AQ88+AR88) | AX88: =IF(X88="","",AS88+AT88+AU88+AV88) | AY88: =IF(AZ88="","",ROUND(AZ88*(1+Assumptions!$B$10),0)) | AZ88: =IF(X88="","",ROUND(X88*(1+AW88),0)) | BA88: =IF(AZ88="","",ROUND(AZ88*(1+Assumptions!$B$11),0)) | BB88: =IF(AZ88="","",ROUND(AZ88*(1+AX88+Assumptions!$B$10),0)) | BC88: =IF(AZ88="","",ROUND(AZ88*(1+AX88),0)) | BD88: =IF(AZ88="","",ROUND(AZ88*(1+AX88+Assumptions!$B$11),0)) | BE88: =IF(AZ88="","",ROUND(AZ88*(1+AX88)*(1+AX88),0)) | BF88: Rules-based enrichment using launch-price anchor, cap-app realization, and 2026 segment conditions. | BG88: 2026-03-17 | BH88: DLD / Digital Dubai / CBUAE / Savills / Knight Frank-Moody’s / Reuters
A89: 88 | B89: The Gardens | C89: Nakheel | D89: Jebel Ali Area | E89: Apartments | F89: Garden / Low Rise | G89: Resale | H89: 700 | I89: 12 | J89: Completed | K89: 2003 | L89: 8.0-8.5 | M89: 4-6 | N89: 12.0-14.5 | O89: Winchester School | P89: Aster Cedars | Q89: Ibn Battuta Mall | R89: Sheikh Zayed E11 | S89: 25 | T89: 10 | U89: 30 | V89: 25 | W89: 2 | Z89: 8 | AA89: 8.5 | AB89: 4 | AC89: 6 | AD89: 12 | AE89: 14.5 | AF89: 2003 | AH89: Apartment | AI89: MainstreamSelective | AJ89: TopTier | AK89: Balanced / selective | AL89: Market remains active but increasingly differentiated by developer, micro-location, livability, and pricing discipline. | AM89: 5 | AN89: 8.25 | AO89: 0.55 | AP89: 0 | AQ89: 0 | AR89: 0 | AS89: 0.01 | AT89: 0.005 | AU89: 0.0025 | AV89: -0.005 | AW89: =IF(X89="","",(AM89/100*AO89)+AP89+AQ89+AR89) | AX89: =IF(X89="","",AS89+AT89+AU89+AV89) | AY89: =IF(AZ89="","",ROUND(AZ89*(1+Assumptions!$B$10),0)) | AZ89: =IF(X89="","",ROUND(X89*(1+AW89),0)) | BA89: =IF(AZ89="","",ROUND(AZ89*(1+Assumptions!$B$11),0)) | BB89: =IF(AZ89="","",ROUND(AZ89*(1+AX89+Assumptions!$B$10),0)) | BC89: =IF(AZ89="","",ROUND(AZ89*(1+AX89),0)) | BD89: =IF(AZ89="","",ROUND(AZ89*(1+AX89+Assumptions!$B$11),0)) | BE89: =IF(AZ89="","",ROUND(AZ89*(1+AX89)*(1+AX89),0)) | BF89: Rules-based enrichment using launch-price anchor, cap-app realization, and 2026 segment conditions. | BG89: 2026-03-17 | BH89: DLD / Digital Dubai / CBUAE / Savills / Knight Frank-Moody’s / Reuters
A90: 89 | B90: Rixos Financial Center Road | C90: Nakheel | D90: Downtown Dubai | E90: Branded Residences | F90: Luxury / City | G90: 4.0M | H90: 3800 | I90: 45+ | J90: 60/40 | K90: 2024 | L90: 4.0-4.5 | M90: 10-15 | N90: 14.0-19.5 | O90: Hartland Intl | P90: Mediclinic Dubai Mall | Q90: Dubai Mall | R90: Financial Ctr Rd | S90: 5 | T90: 20 | U90: 15 | V90: 35 | W90: 2 | X90: 4000000 | Y90: 4000000 | Z90: 4 | AA90: 4.5 | AB90: 10 | AC90: 15 | AD90: 14 | AE90: 19.5 | AF90: 2024 | AH90: Apartment | AI90: Prime | AJ90: TopTier | AK90: Prime resilient / selective | AL90: Better support from quality, branding, and scarcer prime stock; still entry-price sensitive. | AM90: 12.5 | AN90: 4.25 | AO90: 0.55 | AP90: 0.02 | AQ90: 0 | AR90: 0 | AS90: 0.03 | AT90: 0.005 | AU90: 0 | AV90: -0.005 | AW90: =IF(X90="","",(AM90/100*AO90)+AP90+AQ90+AR90) | AX90: =IF(X90="","",AS90+AT90+AU90+AV90) | AY90: =IF(AZ90="","",ROUND(AZ90*(1+Assumptions!$B$10),0)) | AZ90: =IF(X90="","",ROUND(X90*(1+AW90),0)) | BA90: =IF(AZ90="","",ROUND(AZ90*(1+Assumptions!$B$11),0)) | BB90: =IF(AZ90="","",ROUND(AZ90*(1+AX90+Assumptions!$B$10),0)) | BC90: =IF(AZ90="","",ROUND(AZ90*(1+AX90),0)) | BD90: =IF(AZ90="","",ROUND(AZ90*(1+AX90+Assumptions!$B$11),0)) | BE90: =IF(AZ90="","",ROUND(AZ90*(1+AX90)*(1+AX90),0)) | BF90: Rules-based enrichment using launch-price anchor, cap-app realization, and 2026 segment conditions. | BG90: 2026-03-17 | BH90: DLD / Digital Dubai / CBUAE / Savills / Knight Frank-Moody’s / Reuters
A91: 90 | B91: Nad Al Sheba Villas | C91: Nakheel | D91: Nad Al Sheba | E91: Villas | F91: Gated | G91: Resale (3.5M+) | H91: 1000 | I91: 10 | J91: Completed | K91: 2019 | L91: 6.0-6.5 | M91: 6-8 | N91: 12.0-14.5 | O91: Repton School | P91: Nad Al Sheba Health | Q91: Avenue Mall | R91: E311 / E66 | S91: 15 | T91: 25 | U91: 15 | V91: 30 | W91: 2 | X91: 3500000 | Y91: 3500000 | Z91: 6 | AA91: 6.5 | AB91: 6 | AC91: 8 | AD91: 12 | AE91: 14.5 | AF91: 2019 | AH91: Villa | AI91: MainstreamSelective | AJ91: TopTier | AK91: Family-villa resilient | AL91: Villa/townhouse demand remains relatively firmer, though growth should be slower than the post-2020 surge. | AM91: 7 | AN91: 6.25 | AO91: 0.55 | AP91: 0 | AQ91: 0.015 | AR91: 0 | AS91: 0.025 | AT91: 0.005 | AU91: 0.0025 | AV91: -0.005 | AW91: =IF(X91="","",(AM91/100*AO91)+AP91+AQ91+AR91) | AX91: =IF(X91="","",AS91+AT91+AU91+AV91) | AY91: =IF(AZ91="","",ROUND(AZ91*(1+Assumptions!$B$10),0)) | AZ91: =IF(X91="","",ROUND(X91*(1+AW91),0)) | BA91: =IF(AZ91="","",ROUND(AZ91*(1+Assumptions!$B$11),0)) | BB91: =IF(AZ91="","",ROUND(AZ91*(1+AX91+Assumptions!$B$10),0)) | BC91: =IF(AZ91="","",ROUND(AZ91*(1+AX91),0)) | BD91: =IF(AZ91="","",ROUND(AZ91*(1+AX91+Assumptions!$B$11),0)) | BE91: =IF(AZ91="","",ROUND(AZ91*(1+AX91)*(1+AX91),0)) | BF91: Rules-based enrichment using launch-price anchor, cap-app realization, and 2026 segment conditions. | BG91: 2026-03-17 | BH91: DLD / Digital Dubai / CBUAE / Savills / Knight Frank-Moody’s / Reuters
A92: 91 | B92: Warsan Village | C92: Nakheel | D92: International City | E92: Townhouses | F92: Budget | G92: Resale (1.5M+) | H92: 800 | I92: 8 | J92: Completed | K92: 2016 | L92: 7.5-8.0 | M92: 5-7 | N92: 12.5-15.0 | O92: Intl School of Arts | P92: Aster Hospital | Q92: Dragon Mart | R92: E44 / E311 | S92: 20 | T92: 30 | U92: 15 | V92: 35 | W92: 2 | X92: 1500000 | Y92: 1500000 | Z92: 7.5 | AA92: 8 | AB92: 5 | AC92: 7 | AD92: 12.5 | AE92: 15 | AF92: 2016 | AH92: Townhouse | AI92: MainstreamSelective | AJ92: TopTier | AK92: Family-villa resilient | AL92: Villa/townhouse demand remains relatively firmer, though growth should be slower than the post-2020 surge. | AM92: 6 | AN92: 7.75 | AO92: 0.55 | AP92: 0 | AQ92: 0.015 | AR92: 0 | AS92: 0.025 | AT92: 0.005 | AU92: 0.0025 | AV92: -0.005 | AW92: =IF(X92="","",(AM92/100*AO92)+AP92+AQ92+AR92) | AX92: =IF(X92="","",AS92+AT92+AU92+AV92) | AY92: =IF(AZ92="","",ROUND(AZ92*(1+Assumptions!$B$10),0)) | AZ92: =IF(X92="","",ROUND(X92*(1+AW92),0)) | BA92: =IF(AZ92="","",ROUND(AZ92*(1+Assumptions!$B$11),0)) | BB92: =IF(AZ92="","",ROUND(AZ92*(1+AX92+Assumptions!$B$10),0)) | BC92: =IF(AZ92="","",ROUND(AZ92*(1+AX92),0)) | BD92: =IF(AZ92="","",ROUND(AZ92*(1+AX92+Assumptions!$B$11),0)) | BE92: =IF(AZ92="","",ROUND(AZ92*(1+AX92)*(1+AX92),0)) | BF92: Rules-based enrichment using launch-price anchor, cap-app realization, and 2026 segment conditions. | BG92: 2026-03-17 | BH92: DLD / Digital Dubai / CBUAE / Savills / Knight Frank-Moody’s / Reuters
A93: 92 | B93: International City | C93: Nakheel | D93: International City | E93: Apartments | F93: Budget | G93: Resale (350k+) | H93: 600 | I93: 10 | J93: Completed | K93: 2004 | L93: 9.0-15.0 | M93: 5-7 | N93: 14.0-22.0 | O93: Intl School of Arts | P93: Aster Hospital | Q93: Dragon Mart | R93: E44 / E311 | S93: 20 | T93: 30 | U93: 15 | V93: 35 | W93: 2 | X93: 350000 | Y93: 350000 | Z93: 9 | AA93: 15 | AB93: 5 | AC93: 7 | AD93: 14 | AE93: 22 | AF93: 2004 | AH93: Apartment | AI93: SupplySensitiveApartment | AJ93: TopTier | AK93: Supply-sensitive / selective | AL93: Higher delivery risk in more price-sensitive apartment clusters; building selection and exit liquidity matter. | AM93: 6 | AN93: 12 | AO93: 0.55 | AP93: 0 | AQ93: 0 | AR93: -0.01 | AS93: -0.01 | AT93: 0.005 | AU93: 0.0025 | AV93: -0.005 | AW93: =IF(X93="","",(AM93/100*AO93)+AP93+AQ93+AR93) | AX93: =IF(X93="","",AS93+AT93+AU93+AV93) | AY93: =IF(AZ93="","",ROUND(AZ93*(1+Assumptions!$B$10),0)) | AZ93: =IF(X93="","",ROUND(X93*(1+AW93),0)) | BA93: =IF(AZ93="","",ROUND(AZ93*(1+Assumptions!$B$11),0)) | BB93: =IF(AZ93="","",ROUND(AZ93*(1+AX93+Assumptions!$B$10),0)) | BC93: =IF(AZ93="","",ROUND(AZ93*(1+AX93),0)) | BD93: =IF(AZ93="","",ROUND(AZ93*(1+AX93+Assumptions!$B$11),0)) | BE93: =IF(AZ93="","",ROUND(AZ93*(1+AX93)*(1+AX93),0)) | BF93: Rules-based enrichment using launch-price anchor, cap-app realization, and 2026 segment conditions. | BG93: 2026-03-17 | BH93: DLD / Digital Dubai / CBUAE / Savills / Knight Frank-Moody’s / Reuters
A94: 93 | B94: City Walk (Master Community) | C94: Meraas | D94: Jumeirah | E94: Mixed | F94: Urban / Retail | I94: 25-30 | J94: Varies | K94: Ongoing | L94: 5.5-6.5 | M94: 8-12 | N94: 13.5-18.5 | O94: Jumeirah Baccalaureate | P94: Valiant Clinic | Q94: City Walk | R94: Al Wasl / SZR | S94: 5 | T94: 15 | U94: 15 | V94: 35 | W94: 2 | Z94: 5.5 | AA94: 6.5 | AB94: 8 | AC94: 12 | AD94: 13.5 | AE94: 18.5 | AH94: Mixed/Other | AI94: Prime | AJ94: TopTier | AK94: Prime resilient / selective | AL94: Better support from quality, branding, and scarcer prime stock; still entry-price sensitive. | AM94: 10 | AN94: 6 | AO94: 0.25 | AP94: 0.02 | AQ94: 0 | AR94: 0 | AS94: 0.03 | AT94: 0.005 | AU94: 0 | AV94: -0.005 | AW94: =IF(X94="","",(AM94/100*AO94)+AP94+AQ94+AR94) | AX94: =IF(X94="","",AS94+AT94+AU94+AV94) | AY94: =IF(AZ94="","",ROUND(AZ94*(1+Assumptions!$B$10),0)) | AZ94: =IF(X94="","",ROUND(X94*(1+AW94),0)) | BA94: =IF(AZ94="","",ROUND(AZ94*(1+Assumptions!$B$11),0)) | BB94: =IF(AZ94="","",ROUND(AZ94*(1+AX94+Assumptions!$B$10),0)) | BC94: =IF(AZ94="","",ROUND(AZ94*(1+AX94),0)) | BD94: =IF(AZ94="","",ROUND(AZ94*(1+AX94+Assumptions!$B$11),0)) | BE94: =IF(AZ94="","",ROUND(AZ94*(1+AX94)*(1+AX94),0)) | BF94: Rules-based enrichment using launch-price anchor, cap-app realization, and 2026 segment conditions. | BG94: 2026-03-17 | BH94: DLD / Digital Dubai / CBUAE / Savills / Knight Frank-Moody’s / Reuters
A95: 94 | B95: Design Quarter at d3 (Phase 1) | C95: Meraas | D95: Dubai Design District | E95: Apartments | F95: Creative / Modern | G95: 2.1M | H95: 2000 | I95: 25 | J95: 60/40 | K95: 2023 | L95: 5.5-6.0 | M95: 8-12 | N95: 13.5-18.0 | O95: Hartland Intl | P95: Mediclinic Dubai Mall | Q95: Dubai Mall | R95: Ras Al Khor / E44 | S95: 8 | T95: 20 | U95: 12 | V95: 35 | W95: 2 | X95: 2100000 | Y95: 2100000 | Z95: 5.5 | AA95: 6 | AB95: 8 | AC95: 12 | AD95: 13.5 | AE95: 18 | AF95: 2023 | AH95: Apartment | AI95: MainstreamSelective | AJ95: TopTier | AK95: Balanced / selective | AL95: Market remains active but increasingly differentiated by developer, micro-location, livability, and pricing discipline. | AM95: 10 | AN95: 5.75 | AO95: 0.55 | AP95: 0 | AQ95: 0 | AR95: 0 | AS95: 0.01 | AT95: 0.005 | AU95: 0 | AV95: -0.005 | AW95: =IF(X95="","",(AM95/100*AO95)+AP95+AQ95+AR95) | AX95: =IF(X95="","",AS95+AT95+AU95+AV95) | AY95: =IF(AZ95="","",ROUND(AZ95*(1+Assumptions!$B$10),0)) | AZ95: =IF(X95="","",ROUND(X95*(1+AW95),0)) | BA95: =IF(AZ95="","",ROUND(AZ95*(1+Assumptions!$B$11),0)) | BB95: =IF(AZ95="","",ROUND(AZ95*(1+AX95+Assumptions!$B$10),0)) | BC95: =IF(AZ95="","",ROUND(AZ95*(1+AX95),0)) | BD95: =IF(AZ95="","",ROUND(AZ95*(1+AX95+Assumptions!$B$11),0)) | BE95: =IF(AZ95="","",ROUND(AZ95*(1+AX95)*(1+AX95),0)) | BF95: Rules-based enrichment using launch-price anchor, cap-app realization, and 2026 segment conditions. | BG95: 2026-03-17 | BH95: DLD / Digital Dubai / CBUAE / Savills / Knight Frank-Moody’s / Reuters
A96: 95 | B96: Design Quarter at d3 (Phase 2) | C96: Meraas | D96: Dubai Design District | E96: Apartments | F96: Creative / Modern | G96: 2.2M | H96: 2100 | I96: 25 | J96: 60/40 | K96: 2023 | L96: 5.5-6.0 | M96: 8-12 | N96: 13.5-18.0 | O96: Hartland Intl | P96: Mediclinic Dubai Mall | Q96: Dubai Mall | R96: Ras Al Khor / E44 | S96: 8 | T96: 20 | U96: 12 | V96: 35 | W96: 2 | X96: 2200000 | Y96: 2200000 | Z96: 5.5 | AA96: 6 | AB96: 8 | AC96: 12 | AD96: 13.5 | AE96: 18 | AF96: 2023 | AH96: Apartment | AI96: MainstreamSelective | AJ96: TopTier | AK96: Balanced / selective | AL96: Market remains active but increasingly differentiated by developer, micro-location, livability, and pricing discipline. | AM96: 10 | AN96: 5.75 | AO96: 0.55 | AP96: 0 | AQ96: 0 | AR96: 0 | AS96: 0.01 | AT96: 0.005 | AU96: 0 | AV96: -0.005 | AW96: =IF(X96="","",(AM96/100*AO96)+AP96+AQ96+AR96) | AX96: =IF(X96="","",AS96+AT96+AU96+AV96) | AY96: =IF(AZ96="","",ROUND(AZ96*(1+Assumptions!$B$10),0)) | AZ96: =IF(X96="","",ROUND(X96*(1+AW96),0)) | BA96: =IF(AZ96="","",ROUND(AZ96*(1+Assumptions!$B$11),0)) | BB96: =IF(AZ96="","",ROUND(AZ96*(1+AX96+Assumptions!$B$10),0)) | BC96: =IF(AZ96="","",ROUND(AZ96*(1+AX96),0)) | BD96: =IF(AZ96="","",ROUND(AZ96*(1+AX96+Assumptions!$B$11),0)) | BE96: =IF(AZ96="","",ROUND(AZ96*(1+AX96)*(1+AX96),0)) | BF96: Rules-based enrichment using launch-price anchor, cap-app realization, and 2026 segment conditions. | BG96: 2026-03-17 | BH96: DLD / Digital Dubai / CBUAE / Savills / Knight Frank-Moody’s / Reuters
A97: 96 | B97: Central Park: Fern | C97: Meraas | D97: City Walk | E97: Apartments | F97: Park / Green | G97: 1.8M | H97: 2300 | I97: 25 | J97: 50/50 | K97: 2023 | L97: 5.5-6.0 | M97: 8-10 | N97: 13.5-16.0 | O97: Jumeirah Baccalaureate | P97: Valiant Clinic | Q97: City Walk | R97: Al Wasl / SZR | S97: 5 | T97: 15 | U97: 15 | V97: 35 | W97: 2 | X97: 1800000 | Y97: 1800000 | Z97: 5.5 | AA97: 6 | AB97: 8 | AC97: 10 | AD97: 13.5 | AE97: 16 | AF97: 2023 | AH97: Apartment | AI97: Prime | AJ97: TopTier | AK97: Prime resilient / selective | AL97: Better support from quality, branding, and scarcer prime stock; still entry-price sensitive. | AM97: 9 | AN97: 5.75 | AO97: 0.55 | AP97: 0.02 | AQ97: 0 | AR97: 0 | AS97: 0.03 | AT97: 0.005 | AU97: 0 | AV97: -0.005 | AW97: =IF(X97="","",(AM97/100*AO97)+AP97+AQ97+AR97) | AX97: =IF(X97="","",AS97+AT97+AU97+AV97) | AY97: =IF(AZ97="","",ROUND(AZ97*(1+Assumptions!$B$10),0)) | AZ97: =IF(X97="","",ROUND(X97*(1+AW97),0)) | BA97: =IF(AZ97="","",ROUND(AZ97*(1+Assumptions!$B$11),0)) | BB97: =IF(AZ97="","",ROUND(AZ97*(1+AX97+Assumptions!$B$10),0)) | BC97: =IF(AZ97="","",ROUND(AZ97*(1+AX97),0)) | BD97: =IF(AZ97="","",ROUND(AZ97*(1+AX97+Assumptions!$B$11),0)) | BE97: =IF(AZ97="","",ROUND(AZ97*(1+AX97)*(1+AX97),0)) | BF97: Rules-based enrichment using launch-price anchor, cap-app realization, and 2026 segment conditions. | BG97: 2026-03-17 | BH97: DLD / Digital Dubai / CBUAE / Savills / Knight Frank-Moody’s / Reuters
A98: 97 | B98: Central Park: Laurel | C98: Meraas | D98: City Walk | E98: Apartments | F98: Park / Green | G98: 1.9M | H98: 2350 | I98: 25 | J98: 50/50 | K98: 2023 | L98: 5.5-6.0 | M98: 8-10 | N98: 13.5-16.0 | O98: Jumeirah Baccalaureate | P98: Valiant Clinic | Q98: City Walk | R98: Al Wasl / SZR | S98: 5 | T98: 15 | U98: 15 | V98: 35 | W98: 2 | X98: 1900000 | Y98: 1900000 | Z98: 5.5 | AA98: 6 | AB98: 8 | AC98: 10 | AD98: 13.5 | AE98: 16 | AF98: 2023 | AH98: Apartment | AI98: Prime | AJ98: TopTier | AK98: Prime resilient / selective | AL98: Better support from quality, branding, and scarcer prime stock; still entry-price sensitive. | AM98: 9 | AN98: 5.75 | AO98: 0.55 | AP98: 0.02 | AQ98: 0 | AR98: 0 | AS98: 0.03 | AT98: 0.005 | AU98: 0 | AV98: -0.005 | AW98: =IF(X98="","",(AM98/100*AO98)+AP98+AQ98+AR98) | AX98: =IF(X98="","",AS98+AT98+AU98+AV98) | AY98: =IF(AZ98="","",ROUND(AZ98*(1+Assumptions!$B$10),0)) | AZ98: =IF(X98="","",ROUND(X98*(1+AW98),0)) | BA98: =IF(AZ98="","",ROUND(AZ98*(1+Assumptions!$B$11),0)) | BB98: =IF(AZ98="","",ROUND(AZ98*(1+AX98+Assumptions!$B$10),0)) | BC98: =IF(AZ98="","",ROUND(AZ98*(1+AX98),0)) | BD98: =IF(AZ98="","",ROUND(AZ98*(1+AX98+Assumptions!$B$11),0)) | BE98: =IF(AZ98="","",ROUND(AZ98*(1+AX98)*(1+AX98),0)) | BF98: Rules-based enrichment using launch-price anchor, cap-app realization, and 2026 segment conditions. | BG98: 2026-03-17 | BH98: DLD / Digital Dubai / CBUAE / Savills / Knight Frank-Moody’s / Reuters
A99: 98 | B99: Central Park: Myrtle | C99: Meraas | D99: City Walk | E99: Apartments | F99: Park / Green | G99: 1.7M | H99: 2200 | I99: 25 | J99: 50/50 | K99: 2022 | L99: 5.5-6.0 | M99: 7-9 | N99: 12.5-15.0 | O99: Jumeirah Baccalaureate | P99: Valiant Clinic | Q99: City Walk | R99: Al Wasl / SZR | S99: 5 | T99: 15 | U99: 15 | V99: 35 | W99: 2 | X99: 1700000 | Y99: 1700000 | Z99: 5.5 | AA99: 6 | AB99: 7 | AC99: 9 | AD99: 12.5 | AE99: 15 | AF99: 2022 | AH99: Apartment | AI99: Prime | AJ99: TopTier | AK99: Prime resilient / selective | AL99: Better support from quality, branding, and scarcer prime stock; still entry-price sensitive. | AM99: 8 | AN99: 5.75 | AO99: 0.55 | AP99: 0.02 | AQ99: 0 | AR99: 0 | AS99: 0.03 | AT99: 0.005 | AU99: 0 | AV99: -0.005 | AW99: =IF(X99="","",(AM99/100*AO99)+AP99+AQ99+AR99) | AX99: =IF(X99="","",AS99+AT99+AU99+AV99) | AY99: =IF(AZ99="","",ROUND(AZ99*(1+Assumptions!$B$10),0)) | AZ99: =IF(X99="","",ROUND(X99*(1+AW99),0)) | BA99: =IF(AZ99="","",ROUND(AZ99*(1+Assumptions!$B$11),0)) | BB99: =IF(AZ99="","",ROUND(AZ99*(1+AX99+Assumptions!$B$10),0)) | BC99: =IF(AZ99="","",ROUND(AZ99*(1+AX99),0)) | BD99: =IF(AZ99="","",ROUND(AZ99*(1+AX99+Assumptions!$B$11),0)) | BE99: =IF(AZ99="","",ROUND(AZ99*(1+AX99)*(1+AX99),0)) | BF99: Rules-based enrichment using launch-price anchor, cap-app realization, and 2026 segment conditions. | BG99: 2026-03-17 | BH99: DLD / Digital Dubai / CBUAE / Savills / Knight Frank-Moody’s / Reuters
A100: 99 | B100: Central Park: Thyme | C100: Meraas | D100: City Walk | E100: Apartments | F100: Park / Green | G100: 1.75M | H100: 2250 | I100: 25 | J100: 50/50 | K100: 2023 | L100: 5.5-6.0 | M100: 8-10 | N100: 13.5-16.0 | O100: Jumeirah Baccalaureate | P100: Valiant Clinic | Q100: City Walk | R100: Al Wasl / SZR | S100: 5 | T100: 15 | U100: 15 | V100: 35 | W100: 2 | X100: 1750000 | Y100: 1750000 | Z100: 5.5 | AA100: 6 | AB100: 8 | AC100: 10 | AD100: 13.5 | AE100: 16 | AF100: 2023 | AH100: Apartment | AI100: Prime | AJ100: TopTier | AK100: Prime resilient / selective | AL100: Better support from quality, branding, and scarcer prime stock; still entry-price sensitive. | AM100: 9 | AN100: 5.75 | AO100: 0.55 | AP100: 0.02 | AQ100: 0 | AR100: 0 | AS100: 0.03 | AT100: 0.005 | AU100: 0 | AV100: -0.005 | AW100: =IF(X100="","",(AM100/100*AO100)+AP100+AQ100+AR100) | AX100: =IF(X100="","",AS100+AT100+AU100+AV100) | AY100: =IF(AZ100="","",ROUND(AZ100*(1+Assumptions!$B$10),0)) | AZ100: =IF(X100="","",ROUND(X100*(1+AW100),0)) | BA100: =IF(AZ100="","",ROUND(AZ100*(1+Assumptions!$B$11),0)) | BB100: =IF(AZ100="","",ROUND(AZ100*(1+AX100+Assumptions!$B$10),0)) | BC100: =IF(AZ100="","",ROUND(AZ100*(1+AX100),0)) | BD100: =IF(AZ100="","",ROUND(AZ100*(1+AX100+Assumptions!$B$11),0)) | BE100: =IF(AZ100="","",ROUND(AZ100*(1+AX100)*(1+AX100),0)) | BF100: Rules-based enrichment using launch-price anchor, cap-app realization, and 2026 segment conditions. | BG100: 2026-03-17 | BH100: DLD / Digital Dubai / CBUAE / Savills / Knight Frank-Moody’s / Reuters
...

Sheet Master_Values_Frozen
A1: ID | B1: Name | C1: Developer | D1: Location | E1: Unit Type | F1: Community Type | G1: Start Price (AED) | H1: Price per Sqm (AED) | I1: Service Charge | J1: Payment Plan | K1: Launch Date | L1: Annual Yield % | M1: Cap Appr % | N1: Total Return % | O1: Nearest Schools | P1: Nearest Hospitals | Q1: Nearest Malls | R1: Main Access Roads | S1: Mins to DT | T1: Mins to Marina | U1: Mins to DXB | V1: Mins to DWC | W1: Duplicate_Count_From_Merge | X1: Helper_Start_Price_Min_AED | Y1: Helper_Start_Price_Max_AED | Z1: Helper_Annual_Yield_Low_Pct | AA1: Helper_Annual_Yield_High_Pct | AB1: Helper_Cap_App_Low_Pct | AC1: Helper_Cap_App_High_Pct | AD1: Helper_Total_Return_Low_Pct | AE1: Helper_Total_Return_High_Pct | AF1: Helper_Launch_Year | AG1: Helper_Launch_Quarter | AH1: Helper_Asset_Class | AI1: Helper_Area_Segment | AJ1: Helper_Developer_Tier | AK1: Market_Condition | AL1: Conditions_Notes | AM1: Helper_Cap_App_Mid_Pct | AN1: Helper_Annual_Yield_Mid_Pct | AO1: Helper_Current_Realization_Factor | AP1: Helper_Current_Prime_Premium_Pct | AQ1: Helper_Current_Asset_Adjustment_Pct | AR1: Helper_Current_Supply_Adjustment_Pct | AS1: Helper_Forecast_Segment_Base_Pct | AT1: Helper_Forecast_Developer_Adjustment_Pct | AU1: Helper_Forecast_Yield_Adjustment_Pct | AV1: Helper_Forecast_Risk_Adjustment_Pct | AW1: Current_Adjustment_Rate | AX1: Forecast_12M_Base_Pct | AY1: Current_Value_Low_AED | AZ1: Current_Value_Base_AED | BA1: Current_Value_High_AED | BB1: Forecast_12M_Low_AED | BC1: Forecast_12M_Base_AED | BD1: Forecast_12M_High_AED | BE1: Forecast_24M_Base_AED | BF1: Forecast_Method | BG1: Enrichment_Refresh_Date | BH1: Source_Summary | BI1: Added_Project_Source_URL | BJ1: Added_Project_Status | BK1: Added_On
A2: 1 | B2: Grand Polo Club & Resort | C2: Emaar Properties | D2: Near The Oasis/DIP | E2: Villas & Townhouses | F2: Gated / Golf / Equine | G2: 3.6M (TH) / 5.7M (Villa) | H2: 1400-1600 | I2: TBA | J2: 80/20 | K2: Q1 2025 | L2: 5.5-6.5 | M2: 8-12 | N2: 13.5-18.5 | O2: Victory Heights / South View | P2: NMC Royal DIP | Q2: Damac Mall / First Ave | R2: Yalayis St / E611 | S2: 25 | T2: 20 | U2: 30 | V2: 18 | W2: 2 | X2: 3600000 | Y2: 5700000 | Z2: 5.5 | AA2: 6.5 | AB2: 8 | AC2: 12 | AD2: 13.5 | AE2: 18.5 | AF2: 2025 | AG2: 1 | AH2: Villa/Townhouse | AI2: FamilyVilla | AJ2: TopTier | AK2: Family-villa resilient | AL2: Villa/townhouse demand remains relatively firmer, though growth should be slower than the post-2020 surge. | AM2: 10 | AN2: 6 | AO2: 0.4 | AP2: 0 | AQ2: 0.015 | AR2: 0 | AS2: 0.025 | AT2: 0.005 | AU2: 0 | AV2: -0.005 | AW2: 0.055 | AX2: 0.025 | AY2: 3684060 | AZ2: 3798000 | BA2: 3911940 | BB2: 3779010 | BC2: 3892950 | BD2: 4006890 | BE2: 3990274 | BF2: Frozen values from same rules-based model as formula sheet. | BG2: 2026-03-17 | BH2: DLD / Digital Dubai / CBUAE / Savills / Knight Frank-Moody’s / Reuters
A3: 2 | B3: Equiterra (Phases 1 & 2) | C3: Emaar Properties | D3: Grand Polo Club | E3: Townhouses | F3: Gated Community | G3: 3.6M | H3: 1450 | I3: TBA | J3: 80/20 | K3: Q1 2025 | L3: 5.5-6.0 | M3: 8-12 | N3: 13.5-18.0 | O3: Victory Heights / South View | P3: NMC Royal DIP | Q3: Damac Mall / First Ave | R3: Yalayis St / E611 | S3: 25 | T3: 20 | U3: 30 | V3: 18 | W3: 2 | X3: 3600000 | Y3: 3600000 | Z3: 5.5 | AA3: 6 | AB3: 8 | AC3: 12 | AD3: 13.5 | AE3: 18 | AF3: 2025 | AG3: 1 | AH3: Townhouse | AI3: FamilyVilla | AJ3: TopTier | AK3: Family-villa resilient | AL3: Villa/townhouse demand remains relatively firmer, though growth should be slower than the post-2020 surge. | AM3: 10 | AN3: 5.75 | AO3: 0.4 | AP3: 0 | AQ3: 0.015 | AR3: 0 | AS3: 0.025 | AT3: 0.005 | AU3: 0 | AV3: -0.005 | AW3: 0.055 | AX3: 0.025 | AY3: 3684060 | AZ3: 3798000 | BA3: 3911940 | BB3: 3779010 | BC3: 3892950 | BD3: 4006890 | BE3: 3990274 | BF3: Frozen values from same rules-based model as formula sheet. | BG3: 2026-03-17 | BH3: DLD / Digital Dubai / CBUAE / Savills / Knight Frank-Moody’s / Reuters
A4: 3 | B4: Equestra | C4: Emaar Properties | D4: Grand Polo Club | E4: Townhouses | F4: Gated Community | G4: 3.7M | H4: 1450 | I4: TBA | J4: 80/20 | K4: Q1 2025 | L4: 5.5-6.0 | M4: 8-12 | N4: 13.5-18.0 | O4: Victory Heights / South View | P4: NMC Royal DIP | Q4: Damac Mall / First Ave | R4: Yalayis St / E611 | S4: 25 | T4: 20 | U4: 30 | V4: 18 | W4: 2 | X4: 3700000 | Y4: 3700000 | Z4: 5.5 | AA4: 6 | AB4: 8 | AC4: 12 | AD4: 13.5 | AE4: 18 | AF4: 2025 | AG4: 1 | AH4: Townhouse | AI4: FamilyVilla | AJ4: TopTier | AK4: Family-villa resilient | AL4: Villa/townhouse demand remains relatively firmer, though growth should be slower than the post-2020 surge. | AM4: 10 | AN4: 5.75 | AO4: 0.4 | AP4: 0 | AQ4: 0.015 | AR4: 0 | AS4: 0.025 | AT4: 0.005 | AU4: 0 | AV4: -0.005 | AW4: 0.055 | AX4: 0.025 | AY4: 3786395 | AZ4: 3903500 | BA4: 4020605 | BB4: 3883982 | BC4: 4001087 | BD4: 4118192 | BE4: 4101115 | BF4: Frozen values from same rules-based model as formula sheet. | BG4: 2026-03-17 | BH4: DLD / Digital Dubai / CBUAE / Savills / Knight Frank-Moody’s / Reuters
A5: 4 | B5: Chevalia Estate 2 | C5: Emaar Properties | D5: Grand Polo Club | E5: Villas (Large) | F5: Gated Community | G5: 7.9M | H5: 1600 | I5: TBA | J5: 80/20 | K5: Q1 2025 | L5: 4.5-5.5 | M5: 8-12 | N5: 12.5-17.5 | O5: Victory Heights / South View | P5: NMC Royal DIP | Q5: Damac Mall / First Ave | R5: Yalayis St / E611 | S5: 25 | T5: 20 | U5: 30 | V5: 18 | W5: 2 | X5: 7900000 | Y5: 7900000 | Z5: 4.5 | AA5: 5.5 | AB5: 8 | AC5: 12 | AD5: 12.5 | AE5: 17.5 | AF5: 2025 | AG5: 1 | AH5: Villa | AI5: FamilyVilla | AJ5: TopTier | AK5: Family-villa resilient | AL5: Villa/townhouse demand remains relatively firmer, though growth should be slower than the post-2020 surge. | AM5: 10 | AN5: 5 | AO5: 0.4 | AP5: 0 | AQ5: 0.015 | AR5: 0 | AS5: 0.025 | AT5: 0.005 | AU5: 0 | AV5: -0.005 | AW5: 0.055 | AX5: 0.025 | AY5: 8084465 | AZ5: 8334500 | BA5: 8584535 | BB5: 8292827 | BC5: 8542862 | BD5: 8792898 | BE5: 8756434 | BF5: Frozen values from same rules-based model as formula sheet. | BG5: 2026-03-17 | BH5: DLD / Digital Dubai / CBUAE / Savills / Knight Frank-Moody’s / Reuters
A6: 5 | B6: Selvara (Phases 3 & 4) | C6: Emaar Properties | D6: Grand Polo Club | E6: Villas | F6: Gated Community | G6: 6.2M | H6: 1550 | I6: TBA | J6: 80/20 | K6: Q1 2025 | L6: 5.0-5.5 | M6: 8-12 | N6: 13.0-17.5 | O6: Victory Heights / South View | P6: NMC Royal DIP | Q6: Damac Mall / First Ave | R6: Yalayis St / E611 | S6: 25 | T6: 20 | U6: 30 | V6: 18 | W6: 2 | X6: 6200000 | Y6: 6200000 | Z6: 5 | AA6: 5.5 | AB6: 8 | AC6: 12 | AD6: 13 | AE6: 17.5 | AF6: 2025 | AG6: 1 | AH6: Villa | AI6: FamilyVilla | AJ6: TopTier | AK6: Family-villa resilient | AL6: Villa/townhouse demand remains relatively firmer, though growth should be slower than the post-2020 surge. | AM6: 10 | AN6: 5.25 | AO6: 0.4 | AP6: 0 | AQ6: 0.015 | AR6: 0 | AS6: 0.025 | AT6: 0.005 | AU6: 0 | AV6: -0.005 | AW6: 0.055 | AX6: 0.025 | AY6: 6344770 | AZ6: 6541000 | BA6: 6737230 | BB6: 6508295 | BC6: 6704525 | BD6: 6900755 | BE6: 6872138 | BF6: Frozen values from same rules-based model as formula sheet. | BG6: 2026-03-17 | BH6: DLD / Digital Dubai / CBUAE / Savills / Knight Frank-Moody’s / Reuters
A7: 6 | B7: Rashid Yachts & Marina | C7: Emaar Properties | D7: Mina Rashid | E7: Mixed | F7: Waterfront / Marina | I7: 25-30 | J7: Varies | K7: 2023-2025 | L7: 5.5-6.5 | M7: 10-15 | N7: 15.5-21.5 | O7: New Academy School | P7: Aster Hospital Mankhool | Q7: Dubai Mall / City Centre | R7: Al Khaleej / E11 | S7: 15 | T7: 25 | U7: 15 | V7: 45 | W7: 2 | Z7: 5.5 | AA7: 6.5 | AB7: 10 | AC7: 15 | AD7: 15.5 | AE7: 21.5 | AF7: 2023 | AH7: Mixed/Other | AI7: MainstreamSelective | AJ7: TopTier | AK7: Balanced / selective | AL7: Market remains active but increasingly differentiated by developer, micro-location, livability, and pricing discipline. | AM7: 12.5 | AN7: 6 | AO7: 0.55 | AP7: 0 | AQ7: 0 | AR7: 0 | AS7: 0.01 | AT7: 0.005 | AU7: 0 | AV7: -0.005 | AW7: 0.06875 | AX7: 0.01 | BF7: Frozen values from same rules-based model as formula sheet. | BG7: 2026-03-17 | BH7: DLD / Digital Dubai / CBUAE / Savills / Knight Frank-Moody’s / Reuters
A8: 7 | B8: Aurea | C8: Emaar Properties | D8: Rashid Yachts & Marina | E8: Apartments | F8: Waterfront | G8: 1.8M | H8: 2200 | I8: 25 | J8: 80/20 | K8: 2024 | L8: 5.5-6.0 | M8: 10-12 | N8: 15.5-18.0 | O8: New Academy School | P8: Aster Hospital Mankhool | Q8: Dubai Mall / City Centre | R8: Al Khaleej / E11 | S8: 15 | T8: 25 | U8: 15 | V8: 45 | W8: 2 | X8: 1800000 | Y8: 1800000 | Z8: 5.5 | AA8: 6 | AB8: 10 | AC8: 12 | AD8: 15.5 | AE8: 18 | AF8: 2024 | AH8: Apartment | AI8: MainstreamSelective | AJ8: TopTier | AK8: Balanced / selective | AL8: Market remains active but increasingly differentiated by developer, micro-location, livability, and pricing discipline. | AM8: 11 | AN8: 5.75 | AO8: 0.55 | AP8: 0 | AQ8: 0 | AR8: 0 | AS8: 0.01 | AT8: 0.005 | AU8: 0 | AV8: -0.005 | AW8: 0.0605 | AX8: 0.01 | AY8: 1851633 | AZ8: 1908900 | BA8: 1966167 | BB8: 1870722 | BC8: 1927989 | BD8: 1985256 | BE8: 1947269 | BF8: Frozen values from same rules-based model as formula sheet. | BG8: 2026-03-17 | BH8: DLD / Digital Dubai / CBUAE / Savills / Knight Frank-Moody’s / Reuters
A9: 8 | B9: Pier Point | C9: Emaar Properties | D9: Rashid Yachts & Marina | E9: Apartments | F9: Waterfront | G9: 2.1M | H9: 2300 | I9: 25 | J9: 80/20 | K9: 2024 | L9: 5.5-6.0 | M9: 10-12 | N9: 15.5-18.0 | O9: New Academy School | P9: Aster Hospital Mankhool | Q9: Dubai Mall / City Centre | R9: Al Khaleej / E11 | S9: 15 | T9: 25 | U9: 15 | V9: 45 | W9: 2 | X9: 2100000 | Y9: 2100000 | Z9: 5.5 | AA9: 6 | AB9: 10 | AC9: 12 | AD9: 15.5 | AE9: 18 | AF9: 2024 | AH9: Apartment | AI9: MainstreamSelective | AJ9: TopTier | AK9: Balanced / selective | AL9: Market remains active but increasingly differentiated by developer, micro-location, livability, and pricing discipline. | AM9: 11 | AN9: 5.75 | AO9: 0.55 | AP9: 0 | AQ9: 0 | AR9: 0 | AS9: 0.01 | AT9: 0.005 | AU9: 0 | AV9: -0.005 | AW9: 0.0605 | AX9: 0.01 | AY9: 2160238 | AZ9: 2227050 | BA9: 2293862 | BB9: 2182509 | BC9: 2249320 | BD9: 2316132 | BE9: 2271814 | BF9: Frozen values from same rules-based model as formula sheet. | BG9: 2026-03-17 | BH9: DLD / Digital Dubai / CBUAE / Savills / Knight Frank-Moody’s / Reuters
A10: 9 | B10: Marina Cove | C10: Emaar Properties | D10: Rashid Yachts & Marina | E10: Apartments | F10: Waterfront | G10: 1.9M | H10: 2250 | I10: 25 | J10: 80/20 | K10: 2024 | L10: 5.5-6.0 | M10: 10-12 | N10: 15.5-18.0 | O10: New Academy School | P10: Aster Hospital Mankhool | Q10: Dubai Mall / City Centre | R10: Al Khaleej / E11 | S10: 15 | T10: 25 | U10: 15 | V10: 45 | W10: 2 | X10: 1900000 | Y10: 1900000 | Z10: 5.5 | AA10: 6 | AB10: 10 | AC10: 12 | AD10: 15.5 | AE10: 18 | AF10: 2024 | AH10: Apartment | AI10: MainstreamSelective | AJ10: TopTier | AK10: Balanced / selective | AL10: Market remains active but increasingly differentiated by developer, micro-location, livability, and pricing discipline. | AM10: 11 | AN10: 5.75 | AO10: 0.55 | AP10: 0 | AQ10: 0 | AR10: 0 | AS10: 0.01 | AT10: 0.005 | AU10: 0 | AV10: -0.005 | AW10: 0.0605 | AX10: 0.01 | AY10: 1954502 | AZ10: 2014950 | BA10: 2075398 | BB10: 1974651 | BC10: 2035100 | BD10: 2095548 | BE10: 2055450 | BF10: Frozen values from same rules-based model as formula sheet. | BG10: 2026-03-17 | BH10: DLD / Digital Dubai / CBUAE / Savills / Knight Frank-Moody’s / Reuters
A11: 10 | B11: Sera 2 | C11: Emaar Properties | D11: Rashid Yachts & Marina | E11: Apartments | F11: Waterfront | G11: 1.7M | H11: 2100 | I11: 25 | J11: 80/20 | K11: 2024 | L11: 6.0-6.5 | M11: 10-12 | N11: 16.0-18.5 | O11: New Academy School | P11: Aster Hospital Mankhool | Q11: Dubai Mall / City Centre | R11: Al Khaleej / E11 | S11: 15 | T11: 25 | U11: 15 | V11: 45 | W11: 2 | X11: 1700000 | Y11: 1700000 | Z11: 6 | AA11: 6.5 | AB11: 10 | AC11: 12 | AD11: 16 | AE11: 18.5 | AF11: 2024 | AH11: Apartment | AI11: MainstreamSelective | AJ11: TopTier | AK11: Balanced / selective | AL11: Market remains active but increasingly differentiated by developer, micro-location, livability, and pricing discipline. | AM11: 11 | AN11: 6.25 | AO11: 0.55 | AP11: 0 | AQ11: 0 | AR11: 0 | AS11: 0.01 | AT11: 0.005 | AU11: 0.0025 | AV11: -0.005 | AW11: 0.0605 | AX11: 0.0125 | AY11: 1748764 | AZ11: 1802850 | BA11: 1856936 | BB11: 1771300 | BC11: 1825386 | BD11: 1879471 | BE11: 1848203 | BF11: Frozen values from same rules-based model as formula sheet. | BG11: 2026-03-17 | BH11: DLD / Digital Dubai / CBUAE / Savills / Knight Frank-Moody’s / Reuters
A12: 11 | B12: Ocean Cove | C12: Emaar Properties | D12: Rashid Yachts & Marina | E12: Apartments | F12: Waterfront | G12: 1.8M | H12: 2200 | I12: 25 | J12: 80/20 | K12: 2024 | L12: 5.5-6.0 | M12: 10-12 | N12: 15.5-18.0 | O12: New Academy School | P12: Aster Hospital Mankhool | Q12: Dubai Mall / City Centre | R12: Al Khaleej / E11 | S12: 15 | T12: 25 | U12: 15 | V12: 45 | W12: 2 | X12: 1800000 | Y12: 1800000 | Z12: 5.5 | AA12: 6 | AB12: 10 | AC12: 12 | AD12: 15.5 | AE12: 18 | AF12: 2024 | AH12: Apartment | AI12: MainstreamSelective | AJ12: TopTier | AK12: Balanced / selective | AL12: Market remains active but increasingly differentiated by developer, micro-location, livability, and pricing discipline. | AM12: 11 | AN12: 5.75 | AO12: 0.55 | AP12: 0 | AQ12: 0 | AR12: 0 | AS12: 0.01 | AT12: 0.005 | AU12: 0 | AV12: -0.005 | AW12: 0.0605 | AX12: 0.01 | AY12: 1851633 | AZ12: 1908900 | BA12: 1966167 | BB12: 1870722 | BC12: 1927989 | BD12: 1985256 | BE12: 1947269 | BF12: Frozen values from same rules-based model as formula sheet. | BG12: 2026-03-17 | BH12: DLD / Digital Dubai / CBUAE / Savills / Knight Frank-Moody’s / Reuters
A13: 12 | B13: Baystar | C13: Emaar Properties | D13: Rashid Yachts & Marina | E13: Apartments | F13: Waterfront | G13: 1.75M | H13: 2150 | I13: 25 | J13: 80/20 | K13: 2024 | L13: 5.5-6.0 | M13: 10-12 | N13: 15.5-18.0 | O13: New Academy School | P13: Aster Hospital Mankhool | Q13: Dubai Mall / City Centre | R13: Al Khaleej / E11 | S13: 15 | T13: 25 | U13: 15 | V13: 45 | W13: 2 | X13: 1750000 | Y13: 1750000 | Z13: 5.5 | AA13: 6 | AB13: 10 | AC13: 12 | AD13: 15.5 | AE13: 18 | AF13: 2024 | AH13: Apartment | AI13: MainstreamSelective | AJ13: TopTier | AK13: Balanced / selective | AL13: Market remains active but increasingly differentiated by developer, micro-location, livability, and pricing discipline. | AM13: 11 | AN13: 5.75 | AO13: 0.55 | AP13: 0 | AQ13: 0 | AR13: 0 | AS13: 0.01 | AT13: 0.005 | AU13: 0 | AV13: -0.005 | AW13: 0.0605 | AX13: 0.01 | AY13: 1800199 | AZ13: 1855875 | BA13: 1911551 | BB13: 1818758 | BC13: 1874434 | BD13: 1930110 | BE13: 1893178 | BF13: Frozen values from same rules-based model as formula sheet. | BG13: 2026-03-17 | BH13: DLD / Digital Dubai / CBUAE / Savills / Knight Frank-Moody’s / Reuters
A14: 13 | B14: Seagate | C14: Emaar Properties | D14: Rashid Yachts & Marina | E14: Apartments | F14: Waterfront | G14: 1.6M | H14: 2000 | I14: 25 | J14: 80/20 | K14: 2023 | L14: 6.0-6.5 | M14: 8-10 | N14: 14.0-16.5 | O14: New Academy School | P14: Aster Hospital Mankhool | Q14: Dubai Mall / City Centre | R14: Al Khaleej / E11 | S14: 15 | T14: 25 | U14: 15 | V14: 45 | W14: 2 | X14: 1600000 | Y14: 1600000 | Z14: 6 | AA14: 6.5 | AB14: 8 | AC14: 10 | AD14: 14 | AE14: 16.5 | AF14: 2023 | AH14: Apartment | AI14: MainstreamSelective | AJ14: TopTier | AK14: Balanced / selective | AL14: Market remains active but increasingly differentiated by developer, micro-location, livability, and pricing discipline. | AM14: 9 | AN14: 6.25 | AO14: 0.55 | AP14: 0 | AQ14: 0 | AR14: 0 | AS14: 0.01 | AT14: 0.005 | AU14: 0.0025 | AV14: -0.005 | AW14: 0.0495 | AX14: 0.0125 | AY14: 1628824 | AZ14: 1679200 | BA14: 1729576 | BB14: 1649814 | BC14: 1700190 | BD14: 1750566 | BE14: 1721442 | BF14: Frozen values from same rules-based model as formula sheet. | BG14: 2026-03-17 | BH14: DLD / Digital Dubai / CBUAE / Savills / Knight Frank-Moody’s / Reuters
A15: 14 | B15: Clearpoint | C15: Emaar Properties | D15: Rashid Yachts & Marina | E15: Apartments | F15: Waterfront | G15: 1.6M | H15: 2000 | I15: 25 | J15: 80/20 | K15: 2023 | L15: 6.0-6.5 | M15: 8-10 | N15: 14.0-16.5 | O15: New Academy School | P15: Aster Hospital Mankhool | Q15: Dubai Mall / City Centre | R15: Al Khaleej / E11 | S15: 15 | T15: 25 | U15: 15 | V15: 45 | W15: 2 | X15: 1600000 | Y15: 1600000 | Z15: 6 | AA15: 6.5 | AB15: 8 | AC15: 10 | AD15: 14 | AE15: 16.5 | AF15: 2023 | AH15: Apartment | AI15: MainstreamSelective | AJ15: TopTier | AK15: Balanced / selective | AL15: Market remains active but increasingly differentiated by developer, micro-location, livability, and pricing discipline. | AM15: 9 | AN15: 6.25 | AO15: 0.55 | AP15: 0 | AQ15: 0 | AR15: 0 | AS15: 0.01 | AT15: 0.005 | AU15: 0.0025 | AV15: -0.005 | AW15: 0.0495 | AX15: 0.0125 | AY15: 1628824 | AZ15: 1679200 | BA15: 1729576 | BB15: 1649814 | BC15: 1700190 | BD15: 1750566 | BE15: 1721442 | BF15: Frozen values from same rules-based model as formula sheet. | BG15: 2026-03-17 | BH15: DLD / Digital Dubai / CBUAE / Savills / Knight Frank-Moody’s / Reuters
A16: 15 | B16: Sunridge | C16: Emaar Properties | D16: Rashid Yachts & Marina | E16: Apartments | F16: Waterfront | G16: 1.55M | H16: 1950 | I16: 25 | J16: 80/20 | K16: 2023 | L16: 6.0-6.5 | M16: 8-10 | N16: 14.0-16.5 | O16: New Academy School | P16: Aster Hospital Mankhool | Q16: Dubai Mall / City Centre | R16: Al Khaleej / E11 | S16: 15 | T16: 25 | U16: 15 | V16: 45 | W16: 2 | X16: 1550000 | Y16: 1550000 | Z16: 6 | AA16: 6.5 | AB16: 8 | AC16: 10 | AD16: 14 | AE16: 16.5 | AF16: 2023 | AH16: Apartment | AI16: MainstreamSelective | AJ16: TopTier | AK16: Balanced / selective | AL16: Market remains active but increasingly differentiated by developer, micro-location, livability, and pricing discipline. | AM16: 9 | AN16: 6.25 | AO16: 0.55 | AP16: 0 | AQ16: 0 | AR16: 0 | AS16: 0.01 | AT16: 0.005 | AU16: 0.0025 | AV16: -0.005 | AW16: 0.0495 | AX16: 0.0125 | AY16: 1577923 | AZ16: 1626725 | BA16: 1675527 | BB16: 1598257 | BC16: 1647059 | BD16: 1695861 | BE16: 1667647 | BF16: Frozen values from same rules-based model as formula sheet. | BG16: 2026-03-17 | BH16: DLD / Digital Dubai / CBUAE / Savills / Knight Frank-Moody’s / Reuters
A17: 16 | B17: Dubai Creek Harbour | C17: Emaar Properties | D17: The Creek | E17: Mixed | F17: Waterfront / City | I17: 25-30 | J17: Varies | K17: Ongoing | L17: 5.5-6.5 | M17: 9-12 | N17: 14.5-18.5 | O17: Swiss Intl School | P17: American Hospital | Q17: Dubai Festival City | R17: Ras Al Khor / E44 | S17: 12 | T17: 25 | U17: 10 | V17: 40 | W17: 2 | Z17: 5.5 | AA17: 6.5 | AB17: 9 | AC17: 12 | AD17: 14.5 | AE17: 18.5 | AH17: Mixed/Other | AI17: MainstreamSelective | AJ17: TopTier | AK17: Balanced / selective | AL17: Market remains active but increasingly differentiated by developer, micro-location, livability, and pricing discipline. | AM17: 10.5 | AN17: 6 | AO17: 0.25 | AP17: 0 | AQ17: 0 | AR17: 0 | AS17: 0.01 | AT17: 0.005 | AU17: 0 | AV17: -0.005 | AW17: 0.02625 | AX17: 0.01 | BF17: Frozen values from same rules-based model as formula sheet. | BG17: 2026-03-17 | BH17: DLD / Digital Dubai / CBUAE / Savills / Knight Frank-Moody’s / Reuters
A18: 17 | B18: Valo | C18: Emaar Properties | D18: Dubai Creek Harbour | E18: Apartments | F18: Waterfront / Metro | G18: 1.9M | H18: 2300 | I18: 25 | J18: 80/20 | K18: 2024 | L18: 5.5-6.0 | M18: 9-12 | N18: 14.5-18.0 | O18: Swiss Intl School | P18: American Hospital | Q18: Dubai Festival City | R18: Ras Al Khor / E44 | S18: 12 | T18: 25 | U18: 10 | V18: 40 | W18: 2 | X18: 1900000 | Y18: 1900000 | Z18: 5.5 | AA18: 6 | AB18: 9 | AC18: 12 | AD18: 14.5 | AE18: 18 | AF18: 2024 | AH18: Apartment | AI18: Prime | AJ18: TopTier | AK18: Prime resilient / selective | AL18: Better support from quality, branding, and scarcer prime stock; still entry-price sensitive. | AM18: 10.5 | AN18: 5.75 | AO18: 0.55 | AP18: 0.02 | AQ18: 0 | AR18: 0 | AS18: 0.03 | AT18: 0.005 | AU18: 0 | AV18: -0.005 | AW18: 0.07775 | AX18: 0.03 | AY18: 1986293 | AZ18: 2047725 | BA18: 2109157 | BB18: 2047725 | BC18: 2109157 | BD18: 2170588 | BE18: 2172431 | BF18: Frozen values from same rules-based model as formula sheet. | BG18: 2026-03-17 | BH18: DLD / Digital Dubai / CBUAE / Savills / Knight Frank-Moody’s / Reuters
A19: 18 | B19: Aeon | C19: Emaar Properties | D19: Dubai Creek Harbour | E19: Apartments | F19: Waterfront | G19: 1.8M | H19: 2200 | I19: 25 | J19: 80/20 | K19: 2024 | L19: 5.5-6.0 | M19: 9-12 | N19: 14.5-18.0 | O19: Swiss Intl School | P19: American Hospital | Q19: Dubai Festival City | R19: Ras Al Khor / E44 | S19: 12 | T19: 25 | U19: 10 | V19: 40 | W19: 2 | X19: 1800000 | Y19: 1800000 | Z19: 5.5 | AA19: 6 | AB19: 9 | AC19: 12 | AD19: 14.5 | AE19: 18 | AF19: 2024 | AH19: Apartment | AI19: Prime | AJ19: TopTier | AK19: Prime resilient / selective | AL19: Better support from quality, branding, and scarcer prime stock; still entry-price sensitive. | AM19: 10.5 | AN19: 5.75 | AO19: 0.55 | AP19: 0.02 | AQ19: 0 | AR19: 0 | AS19: 0.03 | AT19: 0.005 | AU19: 0 | AV19: -0.005 | AW19: 0.07775 | AX19: 0.03 | AY19: 1881752 | AZ19: 1939950 | BA19: 1998148 | BB19: 1939950 | BC19: 1998148 | BD19: 2056347 | BE19: 2058093 | BF19: Frozen values from same rules-based model as formula sheet. | BG19: 2026-03-17 | BH19: DLD / Digital Dubai / CBUAE / Savills / Knight Frank-Moody’s / Reuters
A20: 19 | B20: Oria | C20: Emaar Properties | D20: Dubai Creek Harbour | E20: Apartments | F20: Waterfront | G20: 1.7M | H20: 2100 | I20: 25 | J20: 80/20 | K20: 2024 | L20: 6.0-6.5 | M20: 9-12 | N20: 15.0-18.5 | O20: Swiss Intl School | P20: American Hospital | Q20: Dubai Festival City | R20: Ras Al Khor / E44 | S20: 12 | T20: 25 | U20: 10 | V20: 40 | W20: 2 | X20: 1700000 | Y20: 1700000 | Z20: 6 | AA20: 6.5 | AB20: 9 | AC20: 12 | AD20: 15 | AE20: 18.5 | AF20: 2024 | AH20: Apartment | AI20: Prime | AJ20: TopTier | AK20: Prime resilient / selective | AL20: Better support from quality, branding, and scarcer prime stock; still entry-price sensitive. | AM20: 10.5 | AN20: 6.25 | AO20: 0.55 | AP20: 0.02 | AQ20: 0 | AR20: 0 | AS20: 0.03 | AT20: 0.005 | AU20: 0.0025 | AV20: -0.005 | AW20: 0.07775 | AX20: 0.0325 | AY20: 1777210 | AZ20: 1832175 | BA20: 1887140 | BB20: 1836755 | BC20: 1891721 | BD20: 1946686 | BE20: 1953202 | BF20: Frozen values from same rules-based model as formula sheet. | BG20: 2026-03-17 | BH20: DLD / Digital Dubai / CBUAE / Savills / Knight Frank-Moody’s / Reuters
A21: 20 | B21: Mangrove (Creek Beach) | C21: Emaar Properties | D21: Dubai Creek Harbour | E21: Apartments | F21: Beachfront | G21: 1.6M | H21: 2000 | I21: 25 | J21: 80/20 | K21: 2024 | L21: 6.0-6.5 | M21: 9-12 | N21: 15.0-18.5 | O21: Swiss Intl School | P21: American Hospital | Q21: Dubai Festival City | R21: Ras Al Khor / E44 | S21: 12 | T21: 25 | U21: 10 | V21: 40 | W21: 2 | X21: 1600000 | Y21: 1600000 | Z21: 6 | AA21: 6.5 | AB21: 9 | AC21: 12 | AD21: 15 | AE21: 18.5 | AF21: 2024 | AH21: Apartment | AI21: Prime | AJ21: TopTier | AK21: Prime resilient / selective | AL21: Better support from quality, branding, and scarcer prime stock; still entry-price sensitive. | AM21: 10.5 | AN21: 6.25 | AO21: 0.55 | AP21: 0.02 | AQ21: 0 | AR21: 0 | AS21: 0.03 | AT21: 0.005 | AU21: 0.0025 | AV21: -0.005 | AW21: 0.07775 | AX21: 0.0325 | AY21: 1672668 | AZ21: 1724400 | BA21: 1776132 | BB21: 1728711 | BC21: 1780443 | BD21: 1832175 | BE21: 1838307 | BF21: Frozen values from same rules-based model as formula sheet. | BG21: 2026-03-17 | BH21: DLD / Digital Dubai / CBUAE / Savills / Knight Frank-Moody’s / Reuters
A22: 21 | B22: Altan | C22: Emaar Properties | D22: Dubai Creek Harbour | E22: Apartments | F22: Waterfront | G22: 1.8M | H22: 2200 | I22: 25 | J22: 80/20 | K22: 2024 | L22: 5.5-6.0 | M22: 9-12 | N22: 14.5-18.0 | O22: Swiss Intl School | P22: American Hospital | Q22: Dubai Festival City | R22: Ras Al Khor / E44 | S22: 12 | T22: 25 | U22: 10 | V22: 40 | W22: 2 | X22: 1800000 | Y22: 1800000 | Z22: 5.5 | AA22: 6 | AB22: 9 | AC22: 12 | AD22: 14.5 | AE22: 18 | AF22: 2024 | AH22: Apartment | AI22: Prime | AJ22: TopTier | AK22: Prime resilient / selective | AL22: Better support from quality, branding, and scarcer prime stock; still entry-price sensitive. | AM22: 10.5 | AN22: 5.75 | AO22: 0.55 | AP22: 0.02 | AQ22: 0 | AR22: 0 | AS22: 0.03 | AT22: 0.005 | AU22: 0 | AV22: -0.005 | AW22: 0.07775 | AX22: 0.03 | AY22: 1881752 | AZ22: 1939950 | BA22: 1998148 | BB22: 1939950 | BC22: 1998148 | BD22: 2056347 | BE22: 2058093 | BF22: Frozen values from same rules-based model as formula sheet. | BG22: 2026-03-17 | BH22: DLD / Digital Dubai / CBUAE / Savills / Knight Frank-Moody’s / Reuters
A23: 22 | B23: Silva | C23: Emaar Properties | D23: Dubai Creek Harbour | E23: Apartments | F23: Waterfront | G23: 1.85M | H23: 2250 | I23: 25 | J23: 80/20 | K23: 2024 | L23: 5.5-6.0 | M23: 9-12 | N23: 14.5-18.0 | O23: Swiss Intl School | P23: American Hospital | Q23: Dubai Festival City | R23: Ras Al Khor / E44 | S23: 12 | T23: 25 | U23: 10 | V23: 40 | W23: 2 | X23: 1850000 | Y23: 1850000 | Z23: 5.5 | AA23: 6 | AB23: 9 | AC23: 12 | AD23: 14.5 | AE23: 18 | AF23: 2024 | AH23: Apartment | AI23: Prime | AJ23: TopTier | AK23: Prime resilient / selective | AL23: Better support from quality, branding, and scarcer prime stock; still entry-price sensitive. | AM23: 10.5 | AN23: 5.75 | AO23: 0.55 | AP23: 0.02 | AQ23: 0 | AR23: 0 | AS23: 0.03 | AT23: 0.005 | AU23: 0 | AV23: -0.005 | AW23: 0.07775 | AX23: 0.03 | AY23: 1934023 | AZ23: 1993838 | BA23: 2053653 | BB23: 1993838 | BC23: 2053653 | BD23: 2113468 | BE23: 2115263 | BF23: Frozen values from same rules-based model as formula sheet. | BG23: 2026-03-17 | BH23: DLD / Digital Dubai / CBUAE / Savills / Knight Frank-Moody’s / Reuters
A24: 23 | B24: Albero | C24: Emaar Properties | D24: Dubai Creek Harbour | E24: Apartments | F24: Waterfront | G24: 1.75M | H24: 2150 | I24: 25 | J24: 80/20 | K24: 2024 | L24: 5.5-6.0 | M24: 9-12 | N24: 14.5-18.0 | O24: Swiss Intl School | P24: American Hospital | Q24: Dubai Festival City | R24: Ras Al Khor / E44 | S24: 12 | T24: 25 | U24: 10 | V24: 40 | W24: 2 | X24: 1750000 | Y24: 1750000 | Z24: 5.5 | AA24: 6 | AB24: 9 | AC24: 12 | AD24: 14.5 | AE24: 18 | AF24: 2024 | AH24: Apartment | AI24: Prime | AJ24: TopTier | AK24: Prime resilient / selective | AL24: Better support from quality, branding, and scarcer prime stock; still entry-price sensitive. | AM24: 10.5 | AN24: 5.75 | AO24: 0.55 | AP24: 0.02 | AQ24: 0 | AR24: 0 | AS24: 0.03 | AT24: 0.005 | AU24: 0 | AV24: -0.005 | AW24: 0.07775 | AX24: 0.03 | AY24: 1829480 | AZ24: 1886062 | BA24: 1942644 | BB24: 1886062 | BC24: 1942644 | BD24: 1999226 | BE24: 2000923 | BF24: Frozen values from same rules-based model as formula sheet. | BG24: 2026-03-17 | BH24: DLD / Digital Dubai / CBUAE / Savills / Knight Frank-Moody’s / Reuters
A25: 24 | B25: Montiva | C25: Emaar Properties | D25: Dubai Creek Harbour | E25: Apartments | F25: Waterfront | G25: 1.8M | H25: 2200 | I25: 25 | J25: 80/20 | K25: 2024 | L25: 5.5-6.0 | M25: 9-12 | N25: 14.5-18.0 | O25: Swiss Intl School | P25: American Hospital | Q25: Dubai Festival City | R25: Ras Al Khor / E44 | S25: 12 | T25: 25 | U25: 10 | V25: 40 | W25: 2 | X25: 1800000 | Y25: 1800000 | Z25: 5.5 | AA25: 6 | AB25: 9 | AC25: 12 | AD25: 14.5 | AE25: 18 | AF25: 2024 | AH25: Apartment | AI25: Prime | AJ25: TopTier | AK25: Prime resilient / selective | AL25: Better support from quality, branding, and scarcer prime stock; still entry-price sensitive. | AM25: 10.5 | AN25: 5.75 | AO25: 0.55 | AP25: 0.02 | AQ25: 0 | AR25: 0 | AS25: 0.03 | AT25: 0.005 | AU25: 0 | AV25: -0.005 | AW25: 0.07775 | AX25: 0.03 | AY25: 1881752 | AZ25: 1939950 | BA25: 1998148 | BB25: 1939950 | BC25: 1998148 | BD25: 2056347 | BE25: 2058093 | BF25: Frozen values from same rules-based model as formula sheet. | BG25: 2026-03-17 | BH25: DLD / Digital Dubai / CBUAE / Savills / Knight Frank-Moody’s / Reuters
A26: 25 | B26: Creek Waters 1 | C26: Emaar Properties | D26: Dubai Creek Harbour | E26: Apartments | F26: Waterfront / Island | G26: 2.2M | H26: 2400 | I26: 25 | J26: 80/20 | K26: 2023 | L26: 5.0-5.5 | M26: 8-10 | N26: 13.0-15.5 | O26: Swiss Intl School | P26: American Hospital | Q26: Dubai Festival City | R26: Ras Al Khor / E44 | S26: 12 | T26: 25 | U26: 10 | V26: 40 | W26: 2 | X26: 2200000 | Y26: 2200000 | Z26: 5 | AA26: 5.5 | AB26: 8 | AC26: 10 | AD26: 13 | AE26: 15.5 | AF26: 2023 | AH26: Apartment | AI26: Prime | AJ26: TopTier | AK26: Prime resilient / selective | AL26: Better support from quality, branding, and scarcer prime stock; still entry-price sensitive. | AM26: 9 | AN26: 5.25 | AO26: 0.55 | AP26: 0.02 | AQ26: 0 | AR26: 0 | AS26: 0.03 | AT26: 0.005 | AU26: 0 | AV26: -0.005 | AW26: 0.0695 | AX26: 0.03 | AY26: 2282313 | AZ26: 2352900 | BA26: 2423487 | BB26: 2352900 | BC26: 2423487 | BD26: 2494074 | BE26: 2496192 | BF26: Frozen values from same rules-based model as formula sheet. | BG26: 2026-03-17 | BH26: DLD / Digital Dubai / CBUAE / Savills / Knight Frank-Moody’s / Reuters
A27: 26 | B27: Creek Waters 2 | C27: Emaar Properties | D27: Dubai Creek Harbour | E27: Apartments | F27: Waterfront / Island | G27: 2.3M | H27: 2450 | I27: 25 | J27: 80/20 | K27: 2023 | L27: 5.0-5.5 | M27: 8-10 | N27: 13.0-15.5 | O27: Swiss Intl School | P27: American Hospital | Q27: Dubai Festival City | R27: Ras Al Khor / E44 | S27: 12 | T27: 25 | U27: 10 | V27: 40 | W27: 2 | X27: 2300000 | Y27: 2300000 | Z27: 5 | AA27: 5.5 | AB27: 8 | AC27: 10 | AD27: 13 | AE27: 15.5 | AF27: 2023 | AH27: Apartment | AI27: Prime | AJ27: TopTier | AK27: Prime resilient / selective | AL27: Better support from quality, branding, and scarcer prime stock; still entry-price sensitive. | AM27: 9 | AN27: 5.25 | AO27: 0.55 | AP27: 0.02 | AQ27: 0 | AR27: 0 | AS27: 0.03 | AT27: 0.005 | AU27: 0 | AV27: -0.005 | AW27: 0.0695 | AX27: 0.03 | AY27: 2386054 | AZ27: 2459850 | BA27: 2533646 | BB27: 2459850 | BC27: 2533646 | BD27: 2607441 | BE27: 2609655 | BF27: Frozen values from same rules-based model as formula sheet. | BG27: 2026-03-17 | BH27: DLD / Digital Dubai / CBUAE / Savills / Knight Frank-Moody’s / Reuters
A28: 27 | B28: Creek Gate | C28: Emaar Properties | D28: Dubai Creek Harbour | E28: Apartments | F28: Waterfront | G28: Resale | H28: 1800 | I28: 25 | J28: Completed | K28: 2017 | L28: 6.0-6.5 | M28: 5-7 | N28: 11.0-13.5 | O28: Swiss Intl School | P28: American Hospital | Q28: Dubai Festival City | R28: Ras Al Khor / E44 | S28: 12 | T28: 25 | U28: 10 | V28: 40 | W28: 2 | Z28: 6 | AA28: 6.5 | AB28: 5 | AC28: 7 | AD28: 11 | AE28: 13.5 | AF28: 2017 | AH28: Apartment | AI28: Prime | AJ28: TopTier | AK28: Prime resilient / selective | AL28: Better support from quality, branding, and scarcer prime stock; still entry-price sensitive. | AM28: 6 | AN28: 6.25 | AO28: 0.55 | AP28: 0.02 | AQ28: 0 | AR28: 0 | AS28: 0.03 | AT28: 0.005 | AU28: 0.0025 | AV28: -0.005 | AW28: 0.053 | AX28: 0.0325 | BF28: Frozen values from same rules-based model as formula sheet. | BG28: 2026-03-17 | BH28: DLD / Digital Dubai / CBUAE / Savills / Knight Frank-Moody’s / Reuters
A29: 28 | B29: Address Grand Creek | C29: Emaar Properties | D29: Dubai Creek Harbour | E29: Branded Residences | F29: Luxury Hotel | G29: 3.5M | H29: 3500 | I29: 45+ | J29: Varies | K29: 2023 | L29: 4.0-5.0 | M29: 8-10 | N29: 12.0-15.0 | O29: Swiss Intl School | P29: American Hospital | Q29: Dubai Festival City | R29: Ras Al Khor / E44 | S29: 12 | T29: 25 | U29: 10 | V29: 40 | W29: 2 | X29: 3500000 | Y29: 3500000 | Z29: 4 | AA29: 5 | AB29: 8 | AC29: 10 | AD29: 12 | AE29: 15 | AF29: 2023 | AH29: Apartment | AI29: Prime | AJ29: TopTier | AK29: Prime resilient / selective | AL29: Better support from quality, branding, and scarcer prime stock; still entry-price sensitive. | AM29: 9 | AN29: 4.5 | AO29: 0.55 | AP29: 0.02 | AQ29: 0 | AR29: 0 | AS29: 0.03 | AT29: 0.005 | AU29: 0 | AV29: -0.005 | AW29: 0.0695 | AX29: 0.03 | AY29: 3630952 | AZ29: 3743250 | BA29: 3855548 | BB29: 3743250 | BC29: 3855548 | BD29: 3967845 | BE29: 3971214 | BF29: Frozen values from same rules-based model as formula sheet. | BG29: 2026-03-17 | BH29: DLD / Digital Dubai / CBUAE / Savills / Knight Frank-Moody’s / Reuters
A30: 29 | B30: Dubai Hills Estate | C30: Emaar Properties | D30: Al Khail Road | E30: Mixed | F30: Golf / Central Park | I30: 20-25 | J30: Varies | K30: Ongoing | L30: 5.5-6.5 | M30: 8-12 | N30: 13.5-18.5 | O30: GEMS Wellington | P30: King's College Hospital | Q30: Dubai Hills Mall | R30: Al Khail E44 | S30: 15 | T30: 15 | U30: 20 | V30: 30 | W30: 2 | Z30: 5.5 | AA30: 6.5 | AB30: 8 | AC30: 12 | AD30: 13.5 | AE30: 18.5 | AH30: Mixed/Other | AI30: MainstreamSelective | AJ30: TopTier | AK30: Balanced / selective | AL30: Market remains active but increasingly differentiated by developer, micro-location, livability, and pricing discipline. | AM30: 10 | AN30: 6 | AO30: 0.25 | AP30: 0 | AQ30: 0 | AR30: 0 | AS30: 0.01 | AT30: 0.005 | AU30: 0 | AV30: -0.005 | AW30: 0.025 | AX30: 0.01 | BF30: Frozen values from same rules-based model as formula sheet. | BG30: 2026-03-17 | BH30: DLD / Digital Dubai / CBUAE / Savills / Knight Frank-Moody’s / Reuters
A31: 30 | B31: Park Gate 2 | C31: Emaar Properties | D31: Dubai Hills Estate | E31: Villas | F31: Gated / Park | G31: 4.5M | H31: 1800 | I31: 20 | J31: 80/20 | K31: 2024 | L31: 5.0-5.5 | M31: 8-12 | N31: 13.0-17.5 | O31: GEMS Wellington | P31: King's College Hospital | Q31: Dubai Hills Mall | R31: Al Khail E44 | S31: 15 | T31: 15 | U31: 20 | V31: 30 | W31: 2 | X31: 4500000 | Y31: 4500000 | Z31: 5 | AA31: 5.5 | AB31: 8 | AC31: 12 | AD31: 13 | AE31: 17.5 | AF31: 2024 | AH31: Villa | AI31: Prime | AJ31: TopTier | AK31: Prime resilient / selective | AL31: Better support from quality, branding, and scarcer prime stock; still entry-price sensitive. | AM31: 10 | AN31: 5.25 | AO31: 0.55 | AP31: 0.02 | AQ31: 0.015 | AR31: 0 | AS31: 0.03 | AT31: 0.005 | AU31: 0 | AV31: -0.005 | AW31: 0.09 | AX31: 0.03 | AY31: 4757850 | AZ31: 4905000 | BA31: 5052150 | BB31: 4905000 | BC31: 5052150 | BD31: 5199300 | BE31: 5203714 | BF31: Frozen values from same rules-based model as formula sheet. | BG31: 2026-03-17 | BH31: DLD / Digital Dubai / CBUAE / Savills / Knight Frank-Moody’s / Reuters
A32: 31 | B32: Rosehill | C32: Emaar Properties | D32: Dubai Hills Estate | E32: Apartments | F32: Community View | G32: 1.6M | H32: 1900 | I32: 22 | J32: 80/20 | K32: 2024 | L32: 6.0-6.5 | M32: 8-12 | N32: 14.0-18.5 | O32: GEMS Wellington | P32: King's College Hospital | Q32: Dubai Hills Mall | R32: Al Khail E44 | S32: 15 | T32: 15 | U32: 20 | V32: 30 | W32: 2 | X32: 1600000 | Y32: 1600000 | Z32: 6 | AA32: 6.5 | AB32: 8 | AC32: 12 | AD32: 14 | AE32: 18.5 | AF32: 2024 | AH32: Apartment | AI32: Prime | AJ32: TopTier | AK32: Prime resilient / selective | AL32: Better support from quality, branding, and scarcer prime stock; still entry-price sensitive. | AM32: 10 | AN32: 6.25 | AO32: 0.55 | AP32: 0.02 | AQ32: 0 | AR32: 0 | AS32: 0.03 | AT32: 0.005 | AU32: 0.0025 | AV32: -0.005 | AW32: 0.075 | AX32: 0.0325 | AY32: 1668400 | AZ32: 1720000 | BA32: 1771600 | BB32: 1724300 | BC32: 1775900 | BD32: 1827500 | BE32: 1833617 | BF32: Frozen values from same rules-based model as formula sheet. | BG32: 2026-03-17 | BH32: DLD / Digital Dubai / CBUAE / Savills / Knight Frank-Moody’s / Reuters
A33: 32 | B33: Greencrest | C33: Emaar Properties | D33: Dubai Hills Estate | E33: Apartments | F33: Community View | G33: 1.55M | H33: 1850 | I33: 22 | J33: 80/20 | K33: 2024 | L33: 6.0-6.5 | M33: 8-12 | N33: 14.0-18.5 | O33: GEMS Wellington | P33: King's College Hospital | Q33: Dubai Hills Mall | R33: Al Khail E44 | S33: 15 | T33: 15 | U33: 20 | V33: 30 | W33: 2 | X33: 1550000 | Y33: 1550000 | Z33: 6 | AA33: 6.5 | AB33: 8 | AC33: 12 | AD33: 14 | AE33: 18.5 | AF33: 2024 | AH33: Apartment | AI33: Prime | AJ33: TopTier | AK33: Prime resilient / selective | AL33: Better support from quality, branding, and scarcer prime stock; still entry-price sensitive. | AM33: 10 | AN33: 6.25 | AO33: 0.55 | AP33: 0.02 | AQ33: 0 | AR33: 0 | AS33: 0.03 | AT33: 0.005 | AU33: 0.0025 | AV33: -0.005 | AW33: 0.075 | AX33: 0.0325 | AY33: 1616262 | AZ33: 1666250 | BA33: 1716238 | BB33: 1670416 | BC33: 1720403 | BD33: 1770391 | BE33: 1776316 | BF33: Frozen values from same rules-based model as formula sheet. | BG33: 2026-03-17 | BH33: DLD / Digital Dubai / CBUAE / Savills / Knight Frank-Moody’s / Reuters
A34: 33 | B34: Palace Residences Hillside | C34: Emaar Properties | D34: Dubai Hills Estate | E34: Branded Apartments | F34: Golf / Park | G34: 2.5M | H34: 2400 | I34: 35 | J34: 80/20 | K34: 2024 | L34: 4.5-5.0 | M34: 8-12 | N34: 12.5-17.0 | O34: GEMS Wellington | P34: King's College Hospital | Q34: Dubai Hills Mall | R34: Al Khail E44 | S34: 15 | T34: 15 | U34: 20 | V34: 30 | W34: 2 | X34: 2500000 | Y34: 2500000 | Z34: 4.5 | AA34: 5 | AB34: 8 | AC34: 12 | AD34: 12.5 | AE34: 17 | AF34: 2024 | AH34: Apartment | AI34: Prime | AJ34: TopTier | AK34: Prime resilient / selective | AL34: Better support from quality, branding, and scarcer prime stock; still entry-price sensitive. | AM34: 10 | AN34: 4.75 | AO34: 0.55 | AP34: 0.02 | AQ34: 0 | AR34: 0 | AS34: 0.03 | AT34: 0.005 | AU34: 0 | AV34: -0.005 | AW34: 0.075 | AX34: 0.03 | AY34: 2606875 | AZ34: 2687500 | BA34: 2768125 | BB34: 2687500 | BC34: 2768125 | BD34: 2848750 | BE34: 2851169 | BF34: Frozen values from same rules-based model as formula sheet. | BG34: 2026-03-17 | BH34: DLD / Digital Dubai / CBUAE / Savills / Knight Frank-Moody’s / Reuters
A35: 34 | B35: Vida Residences Hillside | C35: Emaar Properties | D35: Dubai Hills Estate | E35: Branded Apartments | F35: Golf / Park | G35: 2.2M | H35: 2200 | I35: 30 | J35: 80/20 | K35: 2024 | L35: 5.0-5.5 | M35: 8-12 | N35: 13.0-17.5 | O35: GEMS Wellington | P35: King's College Hospital | Q35: Dubai Hills Mall | R35: Al Khail E44 | S35: 15 | T35: 15 | U35: 20 | V35: 30 | W35: 2 | X35: 2200000 | Y35: 2200000 | Z35: 5 | AA35: 5.5 | AB35: 8 | AC35: 12 | AD35: 13 | AE35: 17.5 | AF35: 2024 | AH35: Apartment | AI35: Prime | AJ35: TopTier | AK35: Prime resilient / selective | AL35: Better support from quality, branding, and scarcer prime stock; still entry-price sensitive. | AM35: 10 | AN35: 5.25 | AO35: 0.55 | AP35: 0.02 | AQ35: 0 | AR35: 0 | AS35: 0.03 | AT35: 0.005 | AU35: 0 | AV35: -0.005 | AW35: 0.075 | AX35: 0.03 | AY35: 2294050 | AZ35: 2365000 | BA35: 2435950 | BB35: 2365000 | BC35: 2435950 | BD35: 2506900 | BE35: 2509028 | BF35: Frozen values from same rules-based model as formula sheet. | BG35: 2026-03-17 | BH35: DLD / Digital Dubai / CBUAE / Savills / Knight Frank-Moody’s / Reuters
A36: 35 | B36: Golf Hillside | C36: Emaar Properties | D36: Dubai Hills Estate | E36: Apartments | F36: Golf Course | G36: 1.8M | H36: 2000 | I36: 22 | J36: 80/20 | K36: 2024 | L36: 5.5-6.0 | M36: 8-12 | N36: 13.5-18.0 | O36: GEMS Wellington | P36: King's College Hospital | Q36: Dubai Hills Mall | R36: Al Khail E44 | S36: 15 | T36: 15 | U36: 20 | V36: 30 | W36: 2 | X36: 1800000 | Y36: 1800000 | Z36: 5.5 | AA36: 6 | AB36: 8 | AC36: 12 | AD36: 13.5 | AE36: 18 | AF36: 2024 | AH36: Apartment | AI36: Prime | AJ36: TopTier | AK36: Prime resilient / selective | AL36: Better support from quality, branding, and scarcer prime stock; still entry-price sensitive. | AM36: 10 | AN36: 5.75 | AO36: 0.55 | AP36: 0.02 | AQ36: 0 | AR36: 0 | AS36: 0.03 | AT36: 0.005 | AU36: 0 | AV36: -0.005 | AW36: 0.075 | AX36: 0.03 | AY36: 1876950 | AZ36: 1935000 | BA36: 1993050 | BB36: 1935000 | BC36: 1993050 | BD36: 2051100 | BE36: 2052842 | BF36: Frozen values from same rules-based model as formula sheet. | BG36: 2026-03-17 | BH36: DLD / Digital Dubai / CBUAE / Savills / Knight Frank-Moody’s / Reuters
A37: 36 | B37: Parkland | C37: Emaar Properties | D37: Dubai Hills Estate | E37: Apartments | F37: Park View | G37: 1.7M | H37: 1950 | I37: 22 | J37: 80/20 | K37: 2024 | L37: 5.5-6.0 | M37: 8-12 | N37: 13.5-18.0 | O37: GEMS Wellington | P37: King's College Hospital | Q37: Dubai Hills Mall | R37: Al Khail E44 | S37: 15 | T37: 15 | U37: 20 | V37: 30 | W37: 2 | X37: 1700000 | Y37: 1700000 | Z37: 5.5 | AA37: 6 | AB37: 8 | AC37: 12 | AD37: 13.5 | AE37: 18 | AF37: 2024 | AH37: Apartment | AI37: Prime | AJ37: TopTier | AK37: Prime resilient / selective | AL37: Better support from quality, branding, and scarcer prime stock; still entry-price sensitive. | AM37: 10 | AN37: 5.75 | AO37: 0.55 | AP37: 0.02 | AQ37: 0 | AR37: 0 | AS37: 0.03 | AT37: 0.005 | AU37: 0 | AV37: -0.005 | AW37: 0.075 | AX37: 0.03 | AY37: 1772675 | AZ37: 1827500 | BA37: 1882325 | BB37: 1827500 | BC37: 1882325 | BD37: 1937150 | BE37: 1938795 | BF37: Frozen values from same rules-based model as formula sheet. | BG37: 2026-03-17 | BH37: DLD / Digital Dubai / CBUAE / Savills / Knight Frank-Moody’s / Reuters
A38: 37 | B38: Sidra Villas | C38: Emaar Properties | D38: Dubai Hills Estate | E38: Villas | F38: Gated Community | G38: Resale (5M+) | H38: 1600 | I38: 15 | J38: Completed | K38: 2016 | L38: 5.5-6.0 | M38: 6-8 | N38: 11.5-14.0 | O38: GEMS Wellington | P38: King's College Hospital | Q38: Dubai Hills Mall | R38: Al Khail E44 | S38: 15 | T38: 15 | U38: 20 | V38: 30 | W38: 2 | X38: 5000000 | Y38: 5000000 | Z38: 5.5 | AA38: 6 | AB38: 6 | AC38: 8 | AD38: 11.5 | AE38: 14 | AF38: 2016 | AH38: Villa | AI38: Prime | AJ38: TopTier | AK38: Prime resilient / selective | AL38: Better support from quality, branding, and scarcer prime stock; still entry-price sensitive. | AM38: 7 | AN38: 5.75 | AO38: 0.55 | AP38: 0.02 | AQ38: 0.015 | AR38: 0 | AS38: 0.03 | AT38: 0.005 | AU38: 0 | AV38: -0.005 | AW38: 0.0735 | AX38: 0.03 | AY38: 5206475 | AZ38: 5367500 | BA38: 5528525 | BB38: 5367500 | BC38: 5528525 | BD38: 5689550 | BE38: 5694381 | BF38: Frozen values from same rules-based model as formula sheet. | BG38: 2026-03-17 | BH38: DLD / Digital Dubai / CBUAE / Savills / Knight Frank-Moody’s / Reuters
A39: 38 | B39: Maple Townhouses | C39: Emaar Properties | D39: Dubai Hills Estate | E39: Townhouses | F39: Gated Community | G39: Resale (3.5M+) | H39: 1500 | I39: 15 | J39: Completed | K39: 2016 | L39: 6.0-6.5 | M39: 6-8 | N39: 12.0-14.5 | O39: GEMS Wellington | P39: King's College Hospital | Q39: Dubai Hills Mall | R39: Al Khail E44 | S39: 15 | T39: 15 | U39: 20 | V39: 30 | W39: 2 | X39: 3500000 | Y39: 3500000 | Z39: 6 | AA39: 6.5 | AB39: 6 | AC39: 8 | AD39: 12 | AE39: 14.5 | AF39: 2016 | AH39: Townhouse | AI39: Prime | AJ39: TopTier | AK39: Prime resilient / selective | AL39: Better support from quality, branding, and scarcer prime stock; still entry-price sensitive. | AM39: 7 | AN39: 6.25 | AO39: 0.55 | AP39: 0.02 | AQ39: 0.015 | AR39: 0 | AS39: 0.03 | AT39: 0.005 | AU39: 0.0025 | AV39: -0.005 | AW39: 0.0735 | AX39: 0.0325 | AY39: 3644532 | AZ39: 3757250 | BA39: 3869968 | BB39: 3766643 | BC39: 3879361 | BD39: 3992078 | BE39: 4005440 | BF39: Frozen values from same rules-based model as formula sheet. | BG39: 2026-03-17 | BH39: DLD / Digital Dubai / CBUAE / Savills / Knight Frank-Moody’s / Reuters
A40: 39 | B40: Address Villas Hillcrest | C40: Emaar Properties | D40: Dubai Hills Estate | E40: Villas | F40: Luxury / Golf | G40: 8.0M | H40: 2200 | I40: 25 | J40: 80/20 | K40: 2023 | L40: 4.5-5.0 | M40: 8-10 | N40: 12.5-15.0 | O40: GEMS Wellington | P40: King's College Hospital | Q40: Dubai Hills Mall | R40: Al Khail E44 | S40: 15 | T40: 15 | U40: 20 | V40: 30 | W40: 2 | X40: 8000000 | Y40: 8000000 | Z40: 4.5 | AA40: 5 | AB40: 8 | AC40: 10 | AD40: 12.5 | AE40: 15 | AF40: 2023 | AH40: Villa | AI40: Prime | AJ40: TopTier | AK40: Prime resilient / selective | AL40: Better support from quality, branding, and scarcer prime stock; still entry-price sensitive. | AM40: 9 | AN40: 4.75 | AO40: 0.55 | AP40: 0.02 | AQ40: 0.015 | AR40: 0 | AS40: 0.03 | AT40: 0.005 | AU40: 0 | AV40: -0.005 | AW40: 0.0845 | AX40: 0.03 | AY40: 8415720 | AZ40: 8676000 | BA40: 8936280 | BB40: 8676000 | BC40: 8936280 | BD40: 9196560 | BE40: 9204368 | BF40: Frozen values from same rules-based model as formula sheet. | BG40: 2026-03-17 | BH40: DLD / Digital Dubai / CBUAE / Savills / Knight Frank-Moody’s / Reuters
A41: 40 | B41: The Valley (Master Community) | C41: Emaar Properties | D41: Dubailand (Al Ain Rd) | E41: Mixed | F41: Suburban / Family | I41: 12-15 | J41: Varies | K41: Ongoing | L41: 6.5-7.5 | M41: 10-15 | N41: 16.5-22.5 | O41: The Aquila School | P41: Fakeeh University Hosp | Q41: Dubai Outlet Mall | R41: Al Ain Rd E66 | S41: 25 | T41: 35 | U41: 25 | V41: 35 | W41: 2 | Z41: 6.5 | AA41: 7.5 | AB41: 10 | AC41: 15 | AD41: 16.5 | AE41: 22.5 | AH41: Mixed/Other | AI41: MainstreamSelective | AJ41: TopTier | AK41: Balanced / selective | AL41: Market remains active but increasingly differentiated by developer, micro-location, livability, and pricing discipline. | AM41: 12.5 | AN41: 7 | AO41: 0.25 | AP41: 0 | AQ41: 0 | AR41: 0 | AS41: 0.01 | AT41: 0.005 | AU41: 0.0025 | AV41: -0.005 | AW41: 0.03125 | AX41: 0.0125 | BF41: Frozen values from same rules-based model as formula sheet. | BG41: 2026-03-17 | BH41: DLD / Digital Dubai / CBUAE / Savills / Knight Frank-Moody’s / Reuters
A42: 41 | B42: Velora | C42: Emaar Properties | D42: The Valley (Phase 2) | E42: Townhouses | F42: Nature / Hills | G42: 2.48M | H42: 1100 | I42: 15 | J42: 80/20 | K42: Aug 2028 | L42: 6.5-7.0 | M42: 10-15 | N42: 16.5-22.0 | O42: The Aquila School | P42: Fakeeh University Hosp | Q42: Dubai Outlet Mall | R42: Al Ain Rd E66 | S42: 25 | T42: 35 | U42: 25 | V42: 35 | W42: 2 | X42: 2480000 | Y42: 2480000 | Z42: 6.5 | AA42: 7 | AB42: 10 | AC42: 15 | AD42: 16.5 | AE42: 22 | AF42: 2028 | AH42: Townhouse | AI42: MainstreamSelective | AJ42: TopTier | AK42: Family-villa resilient | AL42: Villa/townhouse demand remains relatively firmer, though growth should be slower than the post-2020 surge. | AM42: 12.5 | AN42: 6.75 | AO42: 0.25 | AP42: 0 | AQ42: 0.015 | AR42: 0 | AS42: 0.025 | AT42: 0.005 | AU42: 0.0025 | AV42: -0.005 | AW42: 0.04625 | AX42: 0.0275 | AY42: 2516859 | AZ42: 2594700 | BA42: 2672541 | BB42: 2588213 | BC42: 2666054 | BD42: 2743895 | BE42: 2739371 | BF42: Frozen values from same rules-based model as formula sheet. | BG42: 2026-03-17 | BH42: DLD / Digital Dubai / CBUAE / Savills / Knight Frank-Moody’s / Reuters
A43: 42 | B43: Venera | C43: Emaar Properties | D43: The Valley (Phase 2) | E43: Townhouses | F43: Nature / Hills | G43: 2.5M | H43: 1100 | I43: 15 | J43: 80/20 | K43: 2024 | L43: 6.5-7.0 | M43: 10-15 | N43: 16.5-22.0 | O43: The Aquila School | P43: Fakeeh University Hosp | Q43: Dubai Outlet Mall | R43: Al Ain Rd E66 | S43: 25 | T43: 35 | U43: 25 | V43: 35 | W43: 2 | X43: 2500000 | Y43: 2500000 | Z43: 6.5 | AA43: 7 | AB43: 10 | AC43: 15 | AD43: 16.5 | AE43: 22 | AF43: 2024 | AH43: Townhouse | AI43: MainstreamSelective | AJ43: TopTier | AK43: Family-villa resilient | AL43: Villa/townhouse demand remains relatively firmer, though growth should be slower than the post-2020 surge. | AM43: 12.5 | AN43: 6.75 | AO43: 0.55 | AP43: 0 | AQ43: 0.015 | AR43: 0 | AS43: 0.025 | AT43: 0.005 | AU43: 0.0025 | AV43: -0.005 | AW43: 0.08375 | AX43: 0.0275 | AY43: 2628094 | AZ43: 2709375 | BA43: 2790656 | BB43: 2702602 | BC43: 2783883 | BD43: 2865164 | BE43: 2860440 | BF43: Frozen values from same rules-based model as formula sheet. | BG43: 2026-03-17 | BH43: DLD / Digital Dubai / CBUAE / Savills / Knight Frank-Moody’s / Reuters
A44: 43 | B44: Rivera | C44: Emaar Properties | D44: The Valley | E44: Townhouses | F44: Water / Lagoon | G44: 2.6M | H44: 1150 | I44: 15 | J44: 80/20 | K44: 2024 | L44: 6.5-7.0 | M44: 10-15 | N44: 16.5-22.0 | O44: The Aquila School | P44: Fakeeh University Hosp | Q44: Dubai Outlet Mall | R44: Al Ain Rd E66 | S44: 25 | T44: 35 | U44: 25 | V44: 35 | W44: 2 | X44: 2600000 | Y44: 2600000 | Z44: 6.5 | AA44: 7 | AB44: 10 | AC44: 15 | AD44: 16.5 | AE44: 22 | AF44: 2024 | AH44: Townhouse | AI44: FamilyVilla | AJ44: TopTier | AK44: Family-villa resilient | AL44: Villa/townhouse demand remains relatively firmer, though growth should be slower than the post-2020 surge. | AM44: 12.5 | AN44: 6.75 | AO44: 0.55 | AP44: 0 | AQ44: 0.015 | AR44: 0 | AS44: 0.025 | AT44: 0.005 | AU44: 0.0025 | AV44: -0.005 | AW44: 0.08375 | AX44: 0.0275 | AY44: 2733218 | AZ44: 2817750 | BA44: 2902282 | BB44: 2810706 | BC44: 2895238 | BD44: 2979771 | BE44: 2974857 | BF44: Frozen values from same rules-based model as formula sheet. | BG44: 2026-03-17 | BH44: DLD / Digital Dubai / CBUAE / Savills / Knight Frank-Moody’s / Reuters
A45: 44 | B45: Avena | C45: Emaar Properties | D45: The Valley | E45: Villas | F45: Nature | G45: 3.2M | H45: 1200 | I45: 15 | J45: 80/20 | K45: 2024 | L45: 6.0-6.5 | M45: 10-15 | N45: 16.0-21.5 | O45: The Aquila School | P45: Fakeeh University Hosp | Q45: Dubai Outlet Mall | R45: Al Ain Rd E66 | S45: 25 | T45: 35 | U45: 25 | V45: 35 | W45: 2 | X45: 3200000 | Y45: 3200000 | Z45: 6 | AA45: 6.5 | AB45: 10 | AC45: 15 | AD45: 16 | AE45: 21.5 | AF45: 2024 | AH45: Villa | AI45: FamilyVilla | AJ45: TopTier | AK45: Family-villa resilient | AL45: Villa/townhouse demand remains relatively firmer, though growth should be slower than the post-2020 surge. | AM45: 12.5 | AN45: 6.25 | AO45: 0.55 | AP45: 0 | AQ45: 0.015 | AR45: 0 | AS45: 0.025 | AT45: 0.005 | AU45: 0.0025 | AV45: -0.005 | AW45: 0.08375 | AX45: 0.0275 | AY45: 3363960 | AZ45: 3468000 | BA45: 3572040 | BB45: 3459330 | BC45: 3563370 | BD45: 3667410 | BE45: 3661363 | BF45: Frozen values from same rules-based model as formula sheet. | BG45: 2026-03-17 | BH45: DLD / Digital Dubai / CBUAE / Savills / Knight Frank-Moody’s / Reuters
A46: 45 | B46: Ovelle | C46: Emaar Properties | D46: The Valley | E46: Townhouses | F46: Family | G46: 2.4M | H46: 1050 | I46: 15 | J46: 80/20 | K46: 2024 | L46: 6.5-7.0 | M46: 10-15 | N46: 16.5-22.0 | O46: The Aquila School | P46: Fakeeh University Hosp | Q46: Dubai Outlet Mall | R46: Al Ain Rd E66 | S46: 25 | T46: 35 | U46: 25 | V46: 35 | W46: 2 | X46: 2400000 | Y46: 2400000 | Z46: 6.5 | AA46: 7 | AB46: 10 | AC46: 15 | AD46: 16.5 | AE46: 22 | AF46: 2024 | AH46: Townhouse | AI46: FamilyVilla | AJ46: TopTier | AK46: Family-villa resilient | AL46: Villa/townhouse demand remains relatively firmer, though growth should be slower than the post-2020 surge. | AM46: 12.5 | AN46: 6.75 | AO46: 0.55 | AP46: 0 | AQ46: 0.015 | AR46: 0 | AS46: 0.025 | AT46: 0.005 | AU46: 0.0025 | AV46: -0.005 | AW46: 0.08375 | AX46: 0.0275 | AY46: 2522970 | AZ46: 2601000 | BA46: 2679030 | BB46: 2594498 | BC46: 2672528 | BD46: 2750558 | BE46: 2746022 | BF46: Frozen values from same rules-based model as formula sheet. | BG46: 2026-03-17 | BH46: DLD / Digital Dubai / CBUAE / Savills / Knight Frank-Moody’s / Reuters
